Workbook

Sheet README
A1: ASCENDANCE — Master Data Tables v3
A3: Legend | B3: Blue text = hardcoded design inputs (tunable). Black = formulas. Yellow fill = cells you edit (Level_Calculator!D1).
A4: Grades_Realms | B4: The 42-grade spine (14 cultivation realms × 3 stages) shared by buildings, research disciplines, and player cultivation. Levels 0–1337; a grade every 32 levels.
A5: Building_Levels | B5: Parametric multipliers for every building at levels 0–1337 (cost/time/output curves).
A6: Buildings_Master | B6: All 483 buildings (69 per era × 7 eras) with categories and base costs in era-currency equivalents.
A7: Level_Calculator | B7: Type any building name into the yellow cell; the sheet computes its full 0–1337 cost/time/output table.
A8: Archetypes / Unit_Grades / Unit_Paths | B8: Base unit stats and the multipliers that generate the full roster.
A9: Units_Master | B9: 2,268 units (18 archetypes × 3 identity paths × 6 grades × 7 eras), stats computed by formula from the three parameter sheets. "100s of troop types per era" arises combinatorially from research grade + identity path progression.
A10: Counter_Matrix | B10: Role-vs-role damage multipliers (34 roles). Applied on top of unit stats in combat resolution.
A11: Research_Disciplines | B11: 21 disciplines (3 branches × 7 eras), each 0–1337 levels / 42 grades, with prerequisites.
A12: Equipment_Catalog | B12: 135 equipment lines (3 slots × 9 tiers × 5 qualities) with formula-driven bonuses.
A13: Celestial_Sites | B13: 41 site types: barren villages and ruins through planets, moons, asteroids, and intergalactic void sites.
A14: Cultivation | B14: The Sovereign's Path system summary (full design in GDD v3 addendum).
... A42: Empire_Weight_Multiplier | B42: Veterancy XP REQUIREMENT multiplier by empire size: the soft-knee curve to a 9,918,521x cap, why the requirement side beats the earn side, scope, the Champion economy, and countermeasures.

Sheet Grades_Realms
A1: Grade # | B1: Realm · Stage | C1: Min Level | D1: Max Level | E1: Breakthrough Qi Cost | F1: Tribulation (cultivation) | G1: Building Breakthrough Project | H1: Research Grade Prerequisite
A2: 1 | B2: Mortal Vessel · Initial | C2: =(A2-1)*32 -> 0 | D2: =MIN(1337, A2*32-1) -> 31 | E2: =ROUND(100*A2^3.2*1.15^A2,0) -> 115 | F2: None — mortal effort only | G2: Grade-Up Project G1: consumes era resources; 32×level-time; attackable while building | H2: None
A3: 2 | B3: Mortal Vessel · Advanced | C3: =(A3-1)*32 -> 32 | D3: =MIN(1337, A3*32-1) -> 63 | E3: =ROUND(100*A3^3.2*1.15^A3,0) -> 1215 | F3: None — mortal effort only | G3: Grade-Up Project G2: consumes era resources; 32×level-time; attackable while building | H3: All 3 same-era disciplines at Grade 1; cultivation realm ≥ G1
A4: 3 | B4: Mortal Vessel · Perfected | C4: =(A4-1)*32 -> 64 | D4: =MIN(1337, A4*32-1) -> 95 | E4: =ROUND(100*A4^3.2*1.15^A4,0) -> 5115 | F4: None — mortal effort only | G4: Grade-Up Project G3: consumes era resources; 32×level-time; attackable while building | H4: All 3 same-era disciplines at Grade 2; cultivation realm ≥ G2
A5: 4 | B5: Awakened Meridian · Initial | C5: =(A5-1)*32 -> 96 | D5: =MIN(1337, A5*32-1) -> 127 | E5: =ROUND(100*A5^3.2*1.15^A5,0) -> 14770 | F5: Minor Awakened Meridian trial | G5: Grade-Up Project G4: consumes era resources; 32×level-time; attackable while building | H5: All 3 same-era disciplines at Grade 3; cultivation realm ≥ G3
A6: 5 | B6: Awakened Meridian · Advanced | C6: =(A6-1)*32 -> 128 | D6: =MIN(1337, A6*32-1) -> 159 | E6: =ROUND(100*A6^3.2*1.15^A6,0) -> 34689 | F6: Minor Awakened Meridian trial | G6: Grade-Up Project G5: consumes era resources; 32×level-time; attackable while building | H6: All 3 same-era disciplines at Grade 4; cultivation realm ≥ G4
A7: 6 | B7: Awakened Meridian · Perfected | C7: =(A7-1)*32 -> 160 | D7: =MIN(1337, A7*32-1) -> 191 | E7: =ROUND(100*A7^3.2*1.15^A7,0) -> 71494 | F7: Trial of Hunger: survive a famine tick without starvation losses | G7: Grade-Up Project G6: consumes era resources; 32×level-time; attackable while building | H7: All 3 same-era disciplines at Grade 5; cultivation realm ≥ G5
A8: 7 | B8: Tempered Body · Initial | C8: =(A8-1)*32 -> 192 | D8: =MIN(1337, A8*32-1) -> 223 | E8: =ROUND(100*A8^3.2*1.15^A8,0) -> 134648 | F8: Minor Tempered Body trial | G8: Grade-Up Project G7: consumes era resources; 32×level-time; attackable while building | H8: All 3 same-era disciplines at Grade 6; cultivation realm ≥ G6
A9: 8 | B9: Tempered Body · Advanced | C9: =(A9-1)*32 -> 224 | D9: =MIN(1337, A9*32-1) -> 255 | E9: =ROUND(100*A9^3.2*1.15^A9,0) -> 237395 | F9: Minor Tempered Body trial | G9: Grade-Up Project G8: consumes era resources; 32×level-time; attackable while building | H9: All 3 same-era disciplines at Grade 7; cultivation realm ≥ G7
A10: 9 | B10: Tempered Body · Perfected | C10: =(A10-1)*32 -> 256 | D10: =MIN(1337, A10*32-1) -> 287 | E10: =ROUND(100*A10^3.2*1.15^A10,0) -> 397976 | F10: Beast Tide: defend home settlement vs. NPC wave | G10: Grade-Up Project G9: consumes era resources; 32×level-time; attackable while building | H10: All 3 same-era disciplines at Grade 8; cultivation realm ≥ G8
A11: 10 | B11: Foundation · Initial | C11: =(A11-1)*32 -> 288 | D11: =MIN(1337, A11*32-1) -> 319 | E11: =ROUND(100*A11^3.2*1.15^A11,0) -> 641178 | F11: Minor Foundation trial | G11: Grade-Up Project G10: consumes era resources; 32×level-time; attackable while building | H11: All 3 same-era disciplines at Grade 9; cultivation realm ≥ G9
A12: 11 | B12: Foundation · Advanced | C12: =(A12-1)*32 -> 320 | D12: =MIN(1337, A12*32-1) -> 351 | E12: =ROUND(100*A12^3.2*1.15^A12,0) -> 1000306 | F12: Minor Foundation trial | G12: Grade-Up Project G11: consumes era resources; 32×level-time; attackable while building | H12: All 3 same-era disciplines at Grade 10; cultivation realm ≥ G10
A13: 12 | B13: Foundation · Perfected | C13: =(A13-1)*32 -> 352 | D13: =MIN(1337, A13*32-1) -> 383 | E13: =ROUND(100*A13^3.2*1.15^A13,0) -> 1519687 | F13: Heart Demon: agent-op puzzle event; failure stuns cultivation 48h | G13: Grade-Up Project G12: consumes era resources; 32×level-time; attackable while building | H13: All 3 same-era disciplines at Grade 11; cultivation realm ≥ G11
... A43: 42 | B43: Transcendent Dao · Perfected | C43: =(A43-1)*32 -> 1312 | D43: =MIN(1337, A43*32-1) -> 1337 | E43: =ROUND(100*A43^3.2*1.15^A43,0) -> 5542516876 | F43: The Question: universe-unique riddle-quest chain, one per epoch may pass | G43: Grade-Up Project G42: consumes era resources; 32×level-time; attackable while building | H43: All 3 same-era disciplines at Grade 41; cultivation realm ≥ G41
B45: Assumption: 42 grades × 32 levels = 1344 cap, truncated to level 1337 (Grade 42 spans 1312–1337). Qi cost curve is a design input (blue-style constant), tunable server-side.

Sheet Building_Levels
A1: Level | B1: Grade # | C1: Realm · Stage | D1: Cost Multiplier | E1: Build/Research Time (hours) | F1: Output Multiplier | G1: Cumulative Hours 0→L | I1: Time constant K (h)
A2: 0 | B2: =MIN(42, FLOOR(A2/32,1)+1) -> 1 | C2: =INDEX(Grades_Realms!$B$2:$B$43, B2) -> Mortal Vessel · Initial | D2: =(A2+1)^2.4 * 1.004^A2 -> 1 | E2: =$I$2*(A2+1)^1.9*1.003^A2 -> 0.00043197749 | F2: =(A2+1)^1.12 -> 1 | G2: =E2 -> 0.00043197749 | I2: 0.00043197749
A3: 1 | B3: =MIN(42, FLOOR(A3/32,1)+1) -> 1 | C3: =INDEX(Grades_Realms!$B$2:$B$43, B3) -> Mortal Vessel · Initial | D3: =(A3+1)^2.4 * 1.004^A3 -> 5.2991438 | E3: =$I$2*(A3+1)^1.9*1.003^A3 -> 0.0016170336 | F3: =(A3+1)^1.12 -> 2.1734697 | G3: =G2+E3 -> 0.0020490111 | I3: Calibrated so SUM of time col = 500 years (1 yr = 8766 h). Design input.
A4: 2 | B4: =MIN(42, FLOOR(A4/32,1)+1) -> 1 | C4: =INDEX(Grades_Realms!$B$2:$B$43, B4) -> Mortal Vessel · Initial | D4: =(A4+1)^2.4 * 1.004^A4 -> 14.078567 | E4: =$I$2*(A4+1)^1.9*1.003^A4 -> 0.0035042361 | F4: =(A4+1)^1.12 -> 3.4227549 | G4: =G3+E4 -> 0.0055532472
A5: 3 | B5: =MIN(42, FLOOR(A5/32,1)+1) -> 1 | C5: =INDEX(Grades_Realms!$B$2:$B$43, B5) -> Mortal Vessel · Initial | D5: =(A5+1)^2.4 * 1.004^A5 -> 28.193248 | E5: =$I$2*(A5+1)^1.9*1.003^A5 -> 0.0060712469 | F5: =(A5+1)^1.12 -> 4.7239706 | G5: =G4+E5 -> 0.011624494 | I5: Total climb (hours) | J5: Total climb (years)
A6: 4 | B6: =MIN(42, FLOOR(A6/32,1)+1) -> 1 | C6: =INDEX(Grades_Realms!$B$2:$B$43, B6) -> Mortal Vessel · Initial | D6: =(A6+1)^2.4 * 1.004^A6 -> 48.357391 | E6: =$I$2*(A6+1)^1.9*1.003^A6 -> 0.0093048174 | F6: =(A6+1)^1.12 -> 6.0652179 | G6: =G5+E6 -> 0.020929312 | I6: =SUM(E2:E1339) -> 4383000 | J6: =SUM(E2:E1339)/8766 -> 500
A7: 5 | B7: =MIN(42, FLOOR(A7/32,1)+1) -> 1 | C7: =INDEX(Grades_Realms!$B$2:$B$43, B7) -> Mortal Vessel · Initial | D7: =(A7+1)^2.4 * 1.004^A7 -> 75.202376 | E7: =$I$2*(A7+1)^1.9*1.003^A7 -> 0.01319633 | F7: =(A7+1)^1.12 -> 7.4392542 | G7: =G6+E7 -> 0.034125641
A8: 6 | B8: =MIN(42, FLOOR(A8/32,1)+1) -> 1 | C8: =INDEX(Grades_Realms!$B$2:$B$43, B8) -> Mortal Vessel · Initial | D8: =(A8+1)^2.4 * 1.004^A8 -> 109.30438 | E8: =$I$2*(A8+1)^1.9*1.003^A8 -> 0.017739974 | F8: =(A8+1)^1.12 -> 8.8411713 | G8: =G7+E8 -> 0.051865616
A9: 7 | B9: =MIN(42, FLOOR(A9/32,1)+1) -> 1 | C9: =INDEX(Grades_Realms!$B$2:$B$43, B9) -> Mortal Vessel · Initial | D9: =(A9+1)^2.4 * 1.004^A9 -> 151.20006 | E9: =$I$2*(A9+1)^1.9*1.003^A9 -> 0.022931825 | F9: =(A9+1)^1.12 -> 10.267407 | G9: =G8+E9 -> 0.074797441
A10: 8 | B10: =MIN(42, FLOOR(A10/32,1)+1) -> 1 | C10: =INDEX(Grades_Realms!$B$2:$B$43, B10) -> Mortal Vessel · Initial | D10: =(A10+1)^2.4 * 1.004^A10 -> 201.39641 | E10: =$I$2*(A10+1)^1.9*1.003^A10 -> 0.028769303 | F10: =(A10+1)^1.12 -> 11.715251 | G10: =G9+E10 -> 0.10356674
A11: 9 | B11: =MIN(42, FLOOR(A11/32,1)+1) -> 1 | C11: =INDEX(Grades_Realms!$B$2:$B$43, B11) -> Mortal Vessel · Initial | D11: =(A11+1)^2.4 * 1.004^A11 -> 260.37748 | E11: =$I$2*(A11+1)^1.9*1.003^A11 -> 0.035250843 | F11: =(A11+1)^1.12 -> 13.182567 | G11: =G10+E11 -> 0.13881759
A12: 10 | B12: =MIN(42, FLOOR(A12/32,1)+1) -> 1 | C12: =INDEX(Grades_Realms!$B$2:$B$43, B12) -> Mortal Vessel · Initial | D12: =(A12+1)^2.4 * 1.004^A12 -> 328.60909 | E12: =$I$2*(A12+1)^1.9*1.003^A12 -> 0.042375667 | F12: =(A12+1)^1.12 -> 14.667625 | G12: =G11+E12 -> 0.18119325
A13: 11 | B13: =MIN(42, FLOOR(A13/32,1)+1) -> 1 | C13: =INDEX(Grades_Realms!$B$2:$B$43, B13) -> Mortal Vessel · Initial | D13: =(A13+1)^2.4 * 1.004^A13 -> 406.54239 | E13: =$I$2*(A13+1)^1.9*1.003^A13 -> 0.050143627 | F13: =(A13+1)^1.12 -> 16.168994 | G13: =G12+E13 -> 0.23133688
A14: 12 | B14: =MIN(42, FLOOR(A14/32,1)+1) -> 1 | C14: =INDEX(Grades_Realms!$B$2:$B$43, B14) -> Mortal Vessel · Initial | D14: =(A14+1)^2.4 * 1.004^A14 -> 494.6165 | E14: =$I$2*(A14+1)^1.9*1.003^A14 -> 0.058555094 | F14: =(A14+1)^1.12 -> 17.685468 | G14: =G13+E14 -> 0.28989197
A15: 13 | B15: =MIN(42, FLOOR(A15/32,1)+1) -> 1 | C15: =INDEX(Grades_Realms!$B$2:$B$43, B15) -> Mortal Vessel · Initial | D15: =(A15+1)^2.4 * 1.004^A15 -> 593.26066 | E15: =$I$2*(A15+1)^1.9*1.003^A15 -> 0.067610868 | F15: =(A15+1)^1.12 -> 19.216018 | G15: =G14+E15 -> 0.35750284
A16: 14 | B16: =MIN(42, FLOOR(A16/32,1)+1) -> 1 | C16: =INDEX(Grades_Realms!$B$2:$B$43, B16) -> Mortal Vessel · Initial | D16: =(A16+1)^2.4 * 1.004^A16 -> 702.89589 | E16: =$I$2*(A16+1)^1.9*1.003^A16 -> 0.077312118 | F16: =(A16+1)^1.12 -> 20.759754 | G16: =G15+E16 -> 0.43481496
A17: 15 | B17: =MIN(42, FLOOR(A17/32,1)+1) -> 1 | C17: =INDEX(Grades_Realms!$B$2:$B$43, B17) -> Mortal Vessel · Initial | D17: =(A17+1)^2.4 * 1.004^A17 -> 823.93633 | E17: =$I$2*(A17+1)^1.9*1.003^A17 -> 0.087660325 | F17: =(A17+1)^1.12 -> 22.315899 | G17: =G16+E17 -> 0.52247529
A18: 16 | B18: =MIN(42, FLOOR(A18/32,1)+1) -> 1 | C18: =INDEX(Grades_Realms!$B$2:$B$43, B18) -> Mortal Vessel · Initial | D18: =(A18+1)^2.4 * 1.004^A18 -> 956.79042 | E18: =$I$2*(A18+1)^1.9*1.003^A18 -> 0.098657247 | F18: =(A18+1)^1.12 -> 23.883765 | G18: =G17+E18 -> 0.62113253
... A1339: 1337 | B1339: =MIN(42, FLOOR(A1339/32,1)+1) -> 42 | C1339: =INDEX(Grades_Realms!$B$2:$B$43, B1339) -> Transcendent Dao · Perfected | D1339: =(A1339+1)^2.4 * 1.004^A1339 -> 6.6293156e+09 | E1339: =$I$2*(A1339+1)^1.9*1.003^A1339 -> 20657.377 | F1339: =(A1339+1)^1.12 -> 3174.1749 | G1339: =G1338+E1339 -> 4383000

Sheet Buildings_Master
A1: Era | B1: Building | C1: Category | D1: Function / Base Output | E1: Base Timber-eq | F1: Base Stone/Metal-eq | G1: Base Special-eq | H1: Cost @ Level L | I1: Time @ Level L | J1: Levels | K1: Grades
A2: 1 | B2: Chieftain's Hall | C2: HQ/Governance | D2: +1 queue slot / 8 grades | E2: 90 | F2: 80 | G2: 70 | H2: =E2&" × (L+1)^2.4 × 1.004^L (see Building_Levels)" -> 90 × (L+1)^2.4 × 1.004^L (see Building_Levels) | I2: base_time × (L+1)^1.9 × 1.003^L ÷ HQ_factor | J2: 0–1337 | K2: 42
A3: 1 | B3: Farm | C3: Extraction | D3: Grain 30/h base | E3: 45 | F3: 40 | G3: 30 | H3: =E3&" × (L+1)^2.4 × 1.004^L (see Building_Levels)" -> 45 × (L+1)^2.4 × 1.004^L (see Building_Levels) | I3: base_time × (L+1)^1.9 × 1.003^L ÷ HQ_factor | J3: 0–1337 | K3: 42
A4: 1 | B4: Fishery | C4: Extraction | D4: Fish 26/h | E4: 50 | F4: 30 | G4: 20 | H4: =E4&" × (L+1)^2.4 × 1.004^L (see Building_Levels)" -> 50 × (L+1)^2.4 × 1.004^L (see Building_Levels) | I4: base_time × (L+1)^1.9 × 1.003^L ÷ HQ_factor | J4: 0–1337 | K4: 42
A5: 1 | B5: Lumber Camp | C5: Extraction | D5: Timber 30/h | E5: 40 | F5: 50 | G5: 25 | H5: =E5&" × (L+1)^2.4 × 1.004^L (see Building_Levels)" -> 40 × (L+1)^2.4 × 1.004^L (see Building_Levels) | I5: base_time × (L+1)^1.9 × 1.003^L ÷ HQ_factor | J5: 0–1337 | K5: 42
A6: 1 | B6: Mine | C6: Extraction | D6: Ore 26/h | E6: 48 | F6: 60 | G6: 35 | H6: =E6&" × (L+1)^2.4 × 1.004^L (see Building_Levels)" -> 48 × (L+1)^2.4 × 1.004^L (see Building_Levels) | I6: base_time × (L+1)^1.9 × 1.003^L ÷ HQ_factor | J6: 0–1337 | K6: 42
A7: 1 | B7: Hunter's Lodge | C7: Extraction | D7: Hide 14/h | E7: 42 | F7: 32 | G7: 20 | H7: =E7&" × (L+1)^2.4 × 1.004^L (see Building_Levels)" -> 42 × (L+1)^2.4 × 1.004^L (see Building_Levels) | I7: base_time × (L+1)^1.9 × 1.003^L ÷ HQ_factor | J7: 0–1337 | K7: 42
A8: 1 | B8: Clay Pit | C8: Extraction | D8: Clay 20/h | E8: 38 | F8: 30 | G8: 18 | H8: =E8&" × (L+1)^2.4 × 1.004^L (see Building_Levels)" -> 38 × (L+1)^2.4 × 1.004^L (see Building_Levels) | I8: base_time × (L+1)^1.9 × 1.003^L ÷ HQ_factor | J8: 0–1337 | K8: 42
A9: 1 | B9: Herb Garden | C9: Extraction | D9: Spirit Herbs 6/h | E9: 40 | F9: 28 | G9: 22 | H9: =E9&" × (L+1)^2.4 × 1.004^L (see Building_Levels)" -> 40 × (L+1)^2.4 × 1.004^L (see Building_Levels) | I9: base_time × (L+1)^1.9 × 1.003^L ÷ HQ_factor | J9: 0–1337 | K9: 42
A10: 1 | B10: Apiary | C10: Extraction | D10: Honey (food+happiness) | E10: 35 | F10: 20 | G10: 15 | H10: =E10&" × (L+1)^2.4 × 1.004^L (see Building_Levels)" -> 35 × (L+1)^2.4 × 1.004^L (see Building_Levels) | I10: base_time × (L+1)^1.9 × 1.003^L ÷ HQ_factor | J10: 0–1337 | K10: 42
A11: 1 | B11: Orchard | C11: Extraction | D11: Fruit (food var.) | E11: 44 | F11: 26 | G11: 18 | H11: =E11&" × (L+1)^2.4 × 1.004^L (see Building_Levels)" -> 44 × (L+1)^2.4 × 1.004^L (see Building_Levels) | I11: base_time × (L+1)^1.9 × 1.003^L ÷ HQ_factor | J11: 0–1337 | K11: 42
A12: 1 | B12: Vegetable Garden | C12: Extraction | D12: Food 10/h | E12: 30 | F12: 18 | G12: 12 | H12: =E12&" × (L+1)^2.4 × 1.004^L (see Building_Levels)" -> 30 × (L+1)^2.4 × 1.004^L (see Building_Levels) | I12: base_time × (L+1)^1.9 × 1.003^L ÷ HQ_factor | J12: 0–1337 | K12: 42
A13: 1 | B13: Pig Pen | C13: Extraction | D13: Food 12/h | E13: 33 | F13: 22 | G13: 14 | H13: =E13&" × (L+1)^2.4 × 1.004^L (see Building_Levels)" -> 33 × (L+1)^2.4 × 1.004^L (see Building_Levels) | I13: base_time × (L+1)^1.9 × 1.003^L ÷ HQ_factor | J13: 0–1337 | K13: 42
... A484: 7 | B484: Dao Debate Hall | C484: Culture | D484: Cross-path diplomacy; Culture | E484: 1690 | F484: 1670 | G484: 1630 | H484: =E484&" × (L+1)^2.4 × 1.004^L (see Building_Levels)" -> 1690 × (L+1)^2.4 × 1.004^L (see Building_Levels) | I484: base_time × (L+1)^1.9 × 1.003^L ÷ HQ_factor | J484: 0–1337 | K484: 42
B486: Blue = design-input base costs (era-currency equivalents; map to era resources per Section 6 of the GDD). Every building: 1338 levels, grade breakthrough every 32 levels via Grade-Up Project (Grades_Realms sheet).

Sheet Level_Calculator
A1: Building name (type exactly as in Buildings_Master): | D1: Chieftain's Hall
A2: Base Timber-eq | B2: =INDEX(Buildings_Master!E:E, MATCH($D$1, Buildings_Master!B:B, 0)) -> 90 | C2: Base Stone/Metal-eq | D2: =INDEX(Buildings_Master!F:F, MATCH($D$1, Buildings_Master!B:B, 0)) -> 80 | E2: Base Special-eq | F2: =INDEX(Buildings_Master!G:G, MATCH($D$1, Buildings_Master!B:B, 0)) -> 70 | G2: Total climb 0→1337 (years): | H2: =SUM(F5:F1342)/8766 -> 500.00001
A4: Level | B4: Grade # | C4: Timber-eq Cost | D4: Stone/Metal-eq Cost | E4: Special-eq Cost | F4: Build Time (hours) | G4: Relative Output
A5: 0 | B5: =MIN(42, FLOOR(A5/32,1)+1) -> 1 | C5: =ROUND($B$2*(A5+1)^2.4*1.004^A5,0) -> 90 | D5: =ROUND($D$2*(A5+1)^2.4*1.004^A5,0) -> 80 | E5: =ROUND($F$2*(A5+1)^2.4*1.004^A5,0) -> 70 | F5: =ROUND(Building_Levels!$I$2*(A5+1)^1.9*1.003^A5,2) -> 0 | G5: =ROUND((A5+1)^1.12,1) -> 1
A6: 1 | B6: =MIN(42, FLOOR(A6/32,1)+1) -> 1 | C6: =ROUND($B$2*(A6+1)^2.4*1.004^A6,0) -> 477 | D6: =ROUND($D$2*(A6+1)^2.4*1.004^A6,0) -> 424 | E6: =ROUND($F$2*(A6+1)^2.4*1.004^A6,0) -> 371 | F6: =ROUND(Building_Levels!$I$2*(A6+1)^1.9*1.003^A6,2) -> 0 | G6: =ROUND((A6+1)^1.12,1) -> 2.2
A7: 2 | B7: =MIN(42, FLOOR(A7/32,1)+1) -> 1 | C7: =ROUND($B$2*(A7+1)^2.4*1.004^A7,0) -> 1267 | D7: =ROUND($D$2*(A7+1)^2.4*1.004^A7,0) -> 1126 | E7: =ROUND($F$2*(A7+1)^2.4*1.004^A7,0) -> 985 | F7: =ROUND(Building_Levels!$I$2*(A7+1)^1.9*1.003^A7,2) -> 0 | G7: =ROUND((A7+1)^1.12,1) -> 3.4
A8: 3 | B8: =MIN(42, FLOOR(A8/32,1)+1) -> 1 | C8: =ROUND($B$2*(A8+1)^2.4*1.004^A8,0) -> 2537 | D8: =ROUND($D$2*(A8+1)^2.4*1.004^A8,0) -> 2255 | E8: =ROUND($F$2*(A8+1)^2.4*1.004^A8,0) -> 1974 | F8: =ROUND(Building_Levels!$I$2*(A8+1)^1.9*1.003^A8,2) -> 0.01 | G8: =ROUND((A8+1)^1.12,1) -> 4.7
A9: 4 | B9: =MIN(42, FLOOR(A9/32,1)+1) -> 1 | C9: =ROUND($B$2*(A9+1)^2.4*1.004^A9,0) -> 4352 | D9: =ROUND($D$2*(A9+1)^2.4*1.004^A9,0) -> 3869 | E9: =ROUND($F$2*(A9+1)^2.4*1.004^A9,0) -> 3385 | F9: =ROUND(Building_Levels!$I$2*(A9+1)^1.9*1.003^A9,2) -> 0.01 | G9: =ROUND((A9+1)^1.12,1) -> 6.1
A10: 5 | B10: =MIN(42, FLOOR(A10/32,1)+1) -> 1 | C10: =ROUND($B$2*(A10+1)^2.4*1.004^A10,0) -> 6768 | D10: =ROUND($D$2*(A10+1)^2.4*1.004^A10,0) -> 6016 | E10: =ROUND($F$2*(A10+1)^2.4*1.004^A10,0) -> 5264 | F10: =ROUND(Building_Levels!$I$2*(A10+1)^1.9*1.003^A10,2) -> 0.01 | G10: =ROUND((A10+1)^1.12,1) -> 7.4
A11: 6 | B11: =MIN(42, FLOOR(A11/32,1)+1) -> 1 | C11: =ROUND($B$2*(A11+1)^2.4*1.004^A11,0) -> 9837 | D11: =ROUND($D$2*(A11+1)^2.4*1.004^A11,0) -> 8744 | E11: =ROUND($F$2*(A11+1)^2.4*1.004^A11,0) -> 7651 | F11: =ROUND(Building_Levels!$I$2*(A11+1)^1.9*1.003^A11,2) -> 0.02 | G11: =ROUND((A11+1)^1.12,1) -> 8.8
A12: 7 | B12: =MIN(42, FLOOR(A12/32,1)+1) -> 1 | C12: =ROUND($B$2*(A12+1)^2.4*1.004^A12,0) -> 13608 | D12: =ROUND($D$2*(A12+1)^2.4*1.004^A12,0) -> 12096 | E12: =ROUND($F$2*(A12+1)^2.4*1.004^A12,0) -> 10584 | F12: =ROUND(Building_Levels!$I$2*(A12+1)^1.9*1.003^A12,2) -> 0.02 | G12: =ROUND((A12+1)^1.12,1) -> 10.3
A13: 8 | B13: =MIN(42, FLOOR(A13/32,1)+1) -> 1 | C13: =ROUND($B$2*(A13+1)^2.4*1.004^A13,0) -> 18126 | D13: =ROUND($D$2*(A13+1)^2.4*1.004^A13,0) -> 16112 | E13: =ROUND($F$2*(A13+1)^2.4*1.004^A13,0) -> 14098 | F13: =ROUND(Building_Levels!$I$2*(A13+1)^1.9*1.003^A13,2) -> 0.03 | G13: =ROUND((A13+1)^1.12,1) -> 11.7
A14: 9 | B14: =MIN(42, FLOOR(A14/32,1)+1) -> 1 | C14: =ROUND($B$2*(A14+1)^2.4*1.004^A14,0) -> 23434 | D14: =ROUND($D$2*(A14+1)^2.4*1.004^A14,0) -> 20830 | E14: =ROUND($F$2*(A14+1)^2.4*1.004^A14,0) -> 18226 | F14: =ROUND(Building_Levels!$I$2*(A14+1)^1.9*1.003^A14,2) -> 0.04 | G14: =ROUND((A14+1)^1.12,1) -> 13.2
A15: 10 | B15: =MIN(42, FLOOR(A15/32,1)+1) -> 1 | C15: =ROUND($B$2*(A15+1)^2.4*1.004^A15,0) -> 29575 | D15: =ROUND($D$2*(A15+1)^2.4*1.004^A15,0) -> 26289 | E15: =ROUND($F$2*(A15+1)^2.4*1.004^A15,0) -> 23003 | F15: =ROUND(Building_Levels!$I$2*(A15+1)^1.9*1.003^A15,2) -> 0.04 | G15: =ROUND((A15+1)^1.12,1) -> 14.7
A16: 11 | B16: =MIN(42, FLOOR(A16/32,1)+1) -> 1 | C16: =ROUND($B$2*(A16+1)^2.4*1.004^A16,0) -> 36589 | D16: =ROUND($D$2*(A16+1)^2.4*1.004^A16,0) -> 32523 | E16: =ROUND($F$2*(A16+1)^2.4*1.004^A16,0) -> 28458 | F16: =ROUND(Building_Levels!$I$2*(A16+1)^1.9*1.003^A16,2) -> 0.05 | G16: =ROUND((A16+1)^1.12,1) -> 16.2
... A1342: 1337 | B1342: =MIN(42, FLOOR(A1342/32,1)+1) -> 42 | C1342: =ROUND($B$2*(A1342+1)^2.4*1.004^A1342,0) -> 596638408153 | D1342: =ROUND($D$2*(A1342+1)^2.4*1.004^A1342,0) -> 530345251691 | E1342: =ROUND($F$2*(A1342+1)^2.4*1.004^A1342,0) -> 464052095230 | F1342: =ROUND(Building_Levels!$I$2*(A1342+1)^1.9*1.003^A1342,2) -> 20657.38 | G1342: =ROUND((A1342+1)^1.12,1) -> 3174.2

Sheet Archetypes
A1: Key | B1: Era | C1: Archetype | D1: Role | E1: Base Atk | F1: Base Def | G1: Base HP | H1: Base Speed | I1: Base Upkeep | J1: Base Train (h) | L1: Train const (h per upkeep pt)
A2: 1|Militia | B2: 1 | C2: Militia | D2: Line Infantry | E2: 8 | F2: 14 | G2: 60 | H2: 18 | I2: 2 | J2: =ROUND(I2*$L$2,2) -> 0.81 | L2: =4383/(12*900) -> 0.40583333
A3: 1|Spearman | B3: 1 | C3: Spearman | D3: Anti-Cavalry | E3: 10 | F3: 22 | G3: 80 | H3: 16 | I3: 3 | J3: =ROUND(I3*$L$2,2) -> 1.22 | L3: Calibration: Mythic (12×) Path Avatar (upkeep 900) trains in 6 months = 4,383 h.
A4: 1|Axeman | B4: 1 | C4: Axeman | D4: Shock Infantry | E4: 22 | F4: 10 | G4: 85 | H4: 17 | I4: 3 | J4: =ROUND(I4*$L$2,2) -> 1.22
A5: 1|Slinger | B5: 1 | C5: Slinger | D5: Ranged | E5: 14 | F5: 6 | G5: 45 | H5: 18 | I5: 2 | J5: =ROUND(I5*$L$2,2) -> 0.81
A6: 1|Hunter-Archer | B6: 1 | C6: Hunter-Archer | D6: Ranged | E6: 18 | F6: 8 | G6: 50 | H6: 19 | I6: 3 | J6: =ROUND(I6*$L$2,2) -> 1.22
A7: 1|Raider | B7: 1 | C7: Raider | D7: Skirmisher | E7: 16 | F7: 8 | G7: 55 | H7: 26 | I7: 3 | J7: =ROUND(I7*$L$2,2) -> 1.22
A8: 1|Scout | B8: 1 | C8: Scout | D8: Recon | E8: 4 | F8: 4 | G8: 30 | H8: 34 | I8: 1 | J8: =ROUND(I8*$L$2,2) -> 0.41
A9: 1|Shield Bearer | B9: 1 | C9: Shield Bearer | D9: Screen | E9: 8 | F9: 26 | G9: 95 | H9: 15 | I9: 3 | J9: =ROUND(I9*$L$2,2) -> 1.22
A10: 1|Loot Carrier | B10: 1 | C10: Loot Carrier | D10: Logistics | E10: 2 | F10: 6 | G10: 50 | H10: 20 | I10: 2 | J10: =ROUND(I10*$L$2,2) -> 0.81
A11: 1|Chief Guard | B11: 1 | C11: Chief Guard | D11: Elite Shock | E11: 30 | F11: 20 | G11: 120 | H11: 17 | I11: 6 | J11: =ROUND(I11*$L$2,2) -> 2.44
A12: 1|Slave Levy | B12: 1 | C12: Slave Levy | D12: Line Infantry | E12: 6 | F12: 8 | G12: 50 | H12: 16 | I12: 1 | J12: =ROUND(I12*$L$2,2) -> 0.41
A13: 1|War Dog Pack | B13: 1 | C13: War Dog Pack | D13: Skirmisher | E13: 14 | F13: 6 | G13: 40 | H13: 30 | I13: 2 | J13: =ROUND(I13*$L$2,2) -> 0.81
A14: 1|Totem Warrior | B14: 1 | C14: Totem Warrior | D14: Elite Shock | E14: 26 | F14: 16 | G14: 105 | H14: 16 | I14: 5 | J14: =ROUND(I14*$L$2,2) -> 2.03
A15: 1|Stone Thrower | B15: 1 | C15: Stone Thrower | D15: Siege | E15: 20 | F15: 4 | G15: 60 | H15: 8 | I15: 4 | J15: =ROUND(I15*$L$2,2) -> 1.62
... A127: 7|Boundless Swarm | B127: 7 | C127: Boundless Swarm | D127: Drone | E127: 1900 | F127: 900 | G127: 7000 | H127: 80 | I127: 240 | J127: =ROUND(I127*$L$2,2) -> 97.4

Sheet Unit_Grades
A1: Grade | B1: Multiplier (Atk/Def/HP) | C1: Upkeep Mult | D1: Train Time Mult | E1: Unlock
A2: Mortal | B2: 1 | C2: 1 | D2: 1 | E2: Default
A3: Refined | B3: 1.35 | C3: 1.25 | D3: 1.5 | E3: Discipline grade ≥ 6 (Awakened Meridian ·Perfected)
A4: Elite | B4: 1.8 | C4: 1.6 | D4: 2.5 | E4: Grade ≥ 12 + Warfare rank 5
A5: Ascendant | B5: 2.4 | C5: 2.1 | D5: 4 | E5: Grade ≥ 21 + cultivation realm Sovereign
A6: Transcendent | B6: 3.2 | C6: 2.8 | D6: 7 | E6: Grade ≥ 30 + path chosen
A7: Mythic | B7: 4.2 | C7: 3.7 | D7: 12 | E7: Grade ≥ 39 + relic core (rare drop)

Sheet Unit_Paths
A1: Path | B1: Atk Mod | C1: Def Mod | D1: HP Mod | E1: Speed Mod | F1: Identity
A2: Orthodox (Balanced) | B2: 1 | C2: 1 | D2: 1 | E2: 1 | F2: No twist; cheapest to unlock
A3: Asura (Offense) | B3: 1.2 | C3: 0.85 | D3: 0.95 | E3: 1.05 | F3: Warfare-heavy identity; unlocked by battle deeds
A4: Guardian (Defense) | B4: 0.85 | C4: 1.25 | D4: 1.15 | E4: 0.92 | F4: Construction/defense identity; unlocked by defenses held

Sheet Units_Master
A1: Era | B1: Unit Name | C1: Archetype | D1: Key | E1: Path | F1: Grade | G1: Role | H1: Atk | I1: Def | J1: HP | K1: Speed | L1: Upkeep | M1: Train Time (h) | N1: Train Time (days)
A2: 1 | B2: Militia | C2: Militia | D2: =A2&"|"&C2 -> 1|Militia | E2: Orthodox (Balanced) | F2: Mortal | G2: =INDEX(Archetypes!$D$2:$D$127, MATCH(D2, Archetypes!$A$2:$A$127, 0)) -> Line Infantry | H2: =ROUND(INDEX(Archetypes!$E$2:$E$127, MATCH(D2, Archetypes!$A$2:$A$127, 0))*INDEX(Unit_Grades!$B$2:$B$7, MATCH(F2, Unit_Grades!$A$2:$A$7, 0))*INDEX(Unit_Paths!$B$2:$B$4, MATCH(E2, Unit_Paths!$A$2:$A$4, 0)),1) -> 8 | I2: =ROUND(INDEX(Archetypes!$F$2:$F$127, MATCH(D2, Archetypes!$A$2:$A$127, 0))*INDEX(Unit_Grades!$B$2:$B$7, MATCH(F2, Unit_Grades!$A$2:$A$7, 0))*INDEX(Unit_Paths!$C$2:$C$4, MATCH(E2, Unit_Paths!$A$2:$A$4, 0)),1) -> 14 | J2: =ROUND(INDEX(Archetypes!$G$2:$G$127, MATCH(D2, Archetypes!$A$2:$A$127, 0))*INDEX(Unit_Grades!$B$2:$B$7, MATCH(F2, Unit_Grades!$A$2:$A$7, 0))*INDEX(Unit_Paths!$D$2:$D$4, MATCH(E2, Unit_Paths!$A$2:$A$4, 0)),0) -> 60 | K2: =ROUND(INDEX(Archetypes!$H$2:$H$127, MATCH(D2, Archetypes!$A$2:$A$127, 0))*INDEX(Unit_Paths!$E$2:$E$4, MATCH(E2, Unit_Paths!$A$2:$A$4, 0)),1) -> 18 | L2: =ROUND(INDEX(Archetypes!$I$2:$I$127, MATCH(D2, Archetypes!$A$2:$A$127, 0))*INDEX(Unit_Grades!$C$2:$C$7, MATCH(F2, Unit_Grades!$A$2:$A$7, 0)),1) -> 2 | M2: =ROUND(INDEX(Archetypes!$J$2:$J$127, MATCH(D2, Archetypes!$A$2:$A$127, 0))*INDEX(Unit_Grades!$D$2:$D$7, MATCH(F2, Unit_Grades!$A$2:$A$7, 0)),1) -> 0.8 | N2: =ROUND(M2/24,2) -> 0.03
A3: 1 | B3: Refined Militia | C3: Militia | D3: =A3&"|"&C3 -> 1|Militia | E3: Orthodox (Balanced) | F3: Refined | G3: =INDEX(Archetypes!$D$2:$D$127, MATCH(D3, Archetypes!$A$2:$A$127, 0)) -> Line Infantry | H3: =ROUND(INDEX(Archetypes!$E$2:$E$127, MATCH(D3, Archetypes!$A$2:$A$127, 0))*INDEX(Unit_Grades!$B$2:$B$7, MATCH(F3, Unit_Grades!$A$2:$A$7, 0))*INDEX(Unit_Paths!$B$2:$B$4, MATCH(E3, Unit_Paths!$A$2:$A$4, 0)),1) -> 10.8 | I3: =ROUND(INDEX(Archetypes!$F$2:$F$127, MATCH(D3, Archetypes!$A$2:$A$127, 0))*INDEX(Unit_Grades!$B$2:$B$7, MATCH(F3, Unit_Grades!$A$2:$A$7, 0))*INDEX(Unit_Paths!$C$2:$C$4, MATCH(E3, Unit_Paths!$A$2:$A$4, 0)),1) -> 18.9 | J3: =ROUND(INDEX(Archetypes!$G$2:$G$127, MATCH(D3, Archetypes!$A$2:$A$127, 0))*INDEX(Unit_Grades!$B$2:$B$7, MATCH(F3, Unit_Grades!$A$2:$A$7, 0))*INDEX(Unit_Paths!$D$2:$D$4, MATCH(E3, Unit_Paths!$A$2:$A$4, 0)),0) -> 81 | K3: =ROUND(INDEX(Archetypes!$H$2:$H$127, MATCH(D3, Archetypes!$A$2:$A$127, 0))*INDEX(Unit_Paths!$E$2:$E$4, MATCH(E3, Unit_Paths!$A$2:$A$4, 0)),1) -> 18 | L3: =ROUND(INDEX(Archetypes!$I$2:$I$127, MATCH(D3, Archetypes!$A$2:$A$127, 0))*INDEX(Unit_Grades!$C$2:$C$7, MATCH(F3, Unit_Grades!$A$2:$A$7, 0)),1) -> 2.5 | M3: =ROUND(INDEX(Archetypes!$J$2:$J$127, MATCH(D3, Archetypes!$A$2:$A$127, 0))*INDEX(Unit_Grades!$D$2:$D$7, MATCH(F3, Unit_Grades!$A$2:$A$7, 0)),1) -> 1.2 | N3: =ROUND(M3/24,2) -> 0.05
A4: 1 | B4: Elite Militia | C4: Militia | D4: =A4&"|"&C4 -> 1|Militia | E4: Orthodox (Balanced) | F4: Elite | G4: =INDEX(Archetypes!$D$2:$D$127, MATCH(D4, Archetypes!$A$2:$A$127, 0)) -> Line Infantry | H4: =ROUND(INDEX(Archetypes!$E$2:$E$127, MATCH(D4, Archetypes!$A$2:$A$127, 0))*INDEX(Unit_Grades!$B$2:$B$7, MATCH(F4, Unit_Grades!$A$2:$A$7, 0))*INDEX(Unit_Paths!$B$2:$B$4, MATCH(E4, Unit_Paths!$A$2:$A$4, 0)),1) -> 14.4 | I4: =ROUND(INDEX(Archetypes!$F$2:$F$127, MATCH(D4, Archetypes!$A$2:$A$127, 0))*INDEX(Unit_Grades!$B$2:$B$7, MATCH(F4, Unit_Grades!$A$2:$A$7, 0))*INDEX(Unit_Paths!$C$2:$C$4, MATCH(E4, Unit_Paths!$A$2:$A$4, 0)),1) -> 25.2 | J4: =ROUND(INDEX(Archetypes!$G$2:$G$127, MATCH(D4, Archetypes!$A$2:$A$127, 0))*INDEX(Unit_Grades!$B$2:$B$7, MATCH(F4, Unit_Grades!$A$2:$A$7, 0))*INDEX(Unit_Paths!$D$2:$D$4, MATCH(E4, Unit_Paths!$A$2:$A$4, 0)),0) -> 108 | K4: =ROUND(INDEX(Archetypes!$H$2:$H$127, MATCH(D4, Archetypes!$A$2:$A$127, 0))*INDEX(Unit_Paths!$E$2:$E$4, MATCH(E4, Unit_Paths!$A$2:$A$4, 0)),1) -> 18 | L4: =ROUND(INDEX(Archetypes!$I$2:$I$127, MATCH(D4, Archetypes!$A$2:$A$127, 0))*INDEX(Unit_Grades!$C$2:$C$7, MATCH(F4, Unit_Grades!$A$2:$A$7, 0)),1) -> 3.2 | M4: =ROUND(INDEX(Archetypes!$J$2:$J$127, MATCH(D4, Archetypes!$A$2:$A$127, 0))*INDEX(Unit_Grades!$D$2:$D$7, MATCH(F4, Unit_Grades!$A$2:$A$7, 0)),1) -> 2 | N4: =ROUND(M4/24,2) -> 0.08
A5: 1 | B5: Ascendant Militia | C5: Militia | D5: =A5&"|"&C5 -> 1|Militia | E5: Orthodox (Balanced) | F5: Ascendant | G5: =INDEX(Archetypes!$D$2:$D$127, MATCH(D5, Archetypes!$A$2:$A$127, 0)) -> Line Infantry | H5: =ROUND(INDEX(Archetypes!$E$2:$E$127, MATCH(D5, Archetypes!$A$2:$A$127, 0))*INDEX(Unit_Grades!$B$2:$B$7, MATCH(F5, Unit_Grades!$A$2:$A$7, 0))*INDEX(Unit_Paths!$B$2:$B$4, MATCH(E5, Unit_Paths!$A$2:$A$4, 0)),1) -> 19.2 | I5: =ROUND(INDEX(Archetypes!$F$2:$F$127, MATCH(D5, Archetypes!$A$2:$A$127, 0))*INDEX(Unit_Grades!$B$2:$B$7, MATCH(F5, Unit_Grades!$A$2:$A$7, 0))*INDEX(Unit_Paths!$C$2:$C$4, MATCH(E5, Unit_Paths!$A$2:$A$4, 0)),1) -> 33.6 | J5: =ROUND(INDEX(Archetypes!$G$2:$G$127, MATCH(D5, Archetypes!$A$2:$A$127, 0))*INDEX(Unit_Grades!$B$2:$B$7, MATCH(F5, Unit_Grades!$A$2:$A$7, 0))*INDEX(Unit_Paths!$D$2:$D$4, MATCH(E5, Unit_Paths!$A$2:$A$4, 0)),0) -> 144 | K5: =ROUND(INDEX(Archetypes!$H$2:$H$127, MATCH(D5, Archetypes!$A$2:$A$127, 0))*INDEX(Unit_Paths!$E$2:$E$4, MATCH(E5, Unit_Paths!$A$2:$A$4, 0)),1) -> 18 | L5: =ROUND(INDEX(Archetypes!$I$2:$I$127, MATCH(D5, Archetypes!$A$2:$A$127, 0))*INDEX(Unit_Grades!$C$2:$C$7, MATCH(F5, Unit_Grades!$A$2:$A$7, 0)),1) -> 4.2 | M5: =ROUND(INDEX(Archetypes!$J$2:$J$127, MATCH(D5, Archetypes!$A$2:$A$127, 0))*INDEX(Unit_Grades!$D$2:$D$7, MATCH(F5, Unit_Grades!$A$2:$A$7, 0)),1) -> 3.2 | N5: =ROUND(M5/24,2) -> 0.13
A6: 1 | B6: Transcendent Militia | C6: Militia | D6: =A6&"|"&C6 -> 1|Militia | E6: Orthodox (Balanced) | F6: Transcendent | G6: =INDEX(Archetypes!$D$2:$D$127, MATCH(D6, Archetypes!$A$2:$A$127, 0)) -> Line Infantry | H6: =ROUND(INDEX(Archetypes!$E$2:$E$127, MATCH(D6, Archetypes!$A$2:$A$127, 0))*INDEX(Unit_Grades!$B$2:$B$7, MATCH(F6, Unit_Grades!$A$2:$A$7, 0))*INDEX(Unit_Paths!$B$2:$B$4, MATCH(E6, Unit_Paths!$A$2:$A$4, 0)),1) -> 25.6 | I6: =ROUND(INDEX(Archetypes!$F$2:$F$127, MATCH(D6, Archetypes!$A$2:$A$127, 0))*INDEX(Unit_Grades!$B$2:$B$7, MATCH(F6, Unit_Grades!$A$2:$A$7, 0))*INDEX(Unit_Paths!$C$2:$C$4, MATCH(E6, Unit_Paths!$A$2:$A$4, 0)),1) -> 44.8 | J6: =ROUND(INDEX(Archetypes!$G$2:$G$127, MATCH(D6, Archetypes!$A$2:$A$127, 0))*INDEX(Unit_Grades!$B$2:$B$7, MATCH(F6, Unit_Grades!$A$2:$A$7, 0))*INDEX(Unit_Paths!$D$2:$D$4, MATCH(E6, Unit_Paths!$A$2:$A$4, 0)),0) -> 192 | K6: =ROUND(INDEX(Archetypes!$H$2:$H$127, MATCH(D6, Archetypes!$A$2:$A$127, 0))*INDEX(Unit_Paths!$E$2:$E$4, MATCH(E6, Unit_Paths!$A$2:$A$4, 0)),1) -> 18 | L6: =ROUND(INDEX(Archetypes!$I$2:$I$127, MATCH(D6, Archetypes!$A$2:$A$127, 0))*INDEX(Unit_Grades!$C$2:$C$7, MATCH(F6, Unit_Grades!$A$2:$A$7, 0)),1) -> 5.6 | M6: =ROUND(INDEX(Archetypes!$J$2:$J$127, MATCH(D6, Archetypes!$A$2:$A$127, 0))*INDEX(Unit_Grades!$D$2:$D$7, MATCH(F6, Unit_Grades!$A$2:$A$7, 0)),1) -> 5.7 | N6: =ROUND(M6/24,2) -> 0.24
A7: 1 | B7: Mythic Militia | C7: Militia | D7: =A7&"|"&C7 -> 1|Militia | E7: Orthodox (Balanced) | F7: Mythic | G7: =INDEX(Archetypes!$D$2:$D$127, MATCH(D7, Archetypes!$A$2:$A$127, 0)) -> Line Infantry | H7: =ROUND(INDEX(Archetypes!$E$2:$E$127, MATCH(D7, Archetypes!$A$2:$A$127, 0))*INDEX(Unit_Grades!$B$2:$B$7, MATCH(F7, Unit_Grades!$A$2:$A$7, 0))*INDEX(Unit_Paths!$B$2:$B$4, MATCH(E7, Unit_Paths!$A$2:$A$4, 0)),1) -> 33.6 | I7: =ROUND(INDEX(Archetypes!$F$2:$F$127, MATCH(D7, Archetypes!$A$2:$A$127, 0))*INDEX(Unit_Grades!$B$2:$B$7, MATCH(F7, Unit_Grades!$A$2:$A$7, 0))*INDEX(Unit_Paths!$C$2:$C$4, MATCH(E7, Unit_Paths!$A$2:$A$4, 0)),1) -> 58.8 | J7: =ROUND(INDEX(Archetypes!$G$2:$G$127, MATCH(D7, Archetypes!$A$2:$A$127, 0))*INDEX(Unit_Grades!$B$2:$B$7, MATCH(F7, Unit_Grades!$A$2:$A$7, 0))*INDEX(Unit_Paths!$D$2:$D$4, MATCH(E7, Unit_Paths!$A$2:$A$4, 0)),0) -> 252 | K7: =ROUND(INDEX(Archetypes!$H$2:$H$127, MATCH(D7, Archetypes!$A$2:$A$127, 0))*INDEX(Unit_Paths!$E$2:$E$4, MATCH(E7, Unit_Paths!$A$2:$A$4, 0)),1) -> 18 | L7: =ROUND(INDEX(Archetypes!$I$2:$I$127, MATCH(D7, Archetypes!$A$2:$A$127, 0))*INDEX(Unit_Grades!$C$2:$C$7, MATCH(F7, Unit_Grades!$A$2:$A$7, 0)),1) -> 7.4 | M7: =ROUND(INDEX(Archetypes!$J$2:$J$127, MATCH(D7, Archetypes!$A$2:$A$127, 0))*INDEX(Unit_Grades!$D$2:$D$7, MATCH(F7, Unit_Grades!$A$2:$A$7, 0)),1) -> 9.7 | N7: =ROUND(M7/24,2) -> 0.4
A8: 1 | B8: Asura Militia | C8: Militia | D8: =A8&"|"&C8 -> 1|Militia | E8: Asura (Offense) | F8: Mortal | G8: =INDEX(Archetypes!$D$2:$D$127, MATCH(D8, Archetypes!$A$2:$A$127, 0)) -> Line Infantry | H8: =ROUND(INDEX(Archetypes!$E$2:$E$127, MATCH(D8, Archetypes!$A$2:$A$127, 0))*INDEX(Unit_Grades!$B$2:$B$7, MATCH(F8, Unit_Grades!$A$2:$A$7, 0))*INDEX(Unit_Paths!$B$2:$B$4, MATCH(E8, Unit_Paths!$A$2:$A$4, 0)),1) -> 9.6 | I8: =ROUND(INDEX(Archetypes!$F$2:$F$127, MATCH(D8, Archetypes!$A$2:$A$127, 0))*INDEX(Unit_Grades!$B$2:$B$7, MATCH(F8, Unit_Grades!$A$2:$A$7, 0))*INDEX(Unit_Paths!$C$2:$C$4, MATCH(E8, Unit_Paths!$A$2:$A$4, 0)),1) -> 11.9 | J8: =ROUND(INDEX(Archetypes!$G$2:$G$127, MATCH(D8, Archetypes!$A$2:$A$127, 0))*INDEX(Unit_Grades!$B$2:$B$7, MATCH(F8, Unit_Grades!$A$2:$A$7, 0))*INDEX(Unit_Paths!$D$2:$D$4, MATCH(E8, Unit_Paths!$A$2:$A$4, 0)),0) -> 57 | K8: =ROUND(INDEX(Archetypes!$H$2:$H$127, MATCH(D8, Archetypes!$A$2:$A$127, 0))*INDEX(Unit_Paths!$E$2:$E$4, MATCH(E8, Unit_Paths!$A$2:$A$4, 0)),1) -> 18.9 | L8: =ROUND(INDEX(Archetypes!$I$2:$I$127, MATCH(D8, Archetypes!$A$2:$A$127, 0))*INDEX(Unit_Grades!$C$2:$C$7, MATCH(F8, Unit_Grades!$A$2:$A$7, 0)),1) -> 2 | M8: =ROUND(INDEX(Archetypes!$J$2:$J$127, MATCH(D8, Archetypes!$A$2:$A$127, 0))*INDEX(Unit_Grades!$D$2:$D$7, MATCH(F8, Unit_Grades!$A$2:$A$7, 0)),1) -> 0.8 | N8: =ROUND(M8/24,2) -> 0.03
A9: 1 | B9: Refined Asura Militia | C9: Militia | D9: =A9&"|"&C9 -> 1|Militia | E9: Asura (Offense) | F9: Refined | G9: =INDEX(Archetypes!$D$2:$D$127, MATCH(D9, Archetypes!$A$2:$A$127, 0)) -> Line Infantry | H9: =ROUND(INDEX(Archetypes!$E$2:$E$127, MATCH(D9, Archetypes!$A$2:$A$127, 0))*INDEX(Unit_Grades!$B$2:$B$7, MATCH(F9, Unit_Grades!$A$2:$A$7, 0))*INDEX(Unit_Paths!$B$2:$B$4, MATCH(E9, Unit_Paths!$A$2:$A$4, 0)),1) -> 13 | I9: =ROUND(INDEX(Archetypes!$F$2:$F$127, MATCH(D9, Archetypes!$A$2:$A$127, 0))*INDEX(Unit_Grades!$B$2:$B$7, MATCH(F9, Unit_Grades!$A$2:$A$7, 0))*INDEX(Unit_Paths!$C$2:$C$4, MATCH(E9, Unit_Paths!$A$2:$A$4, 0)),1) -> 16.1 | J9: =ROUND(INDEX(Archetypes!$G$2:$G$127, MATCH(D9, Archetypes!$A$2:$A$127, 0))*INDEX(Unit_Grades!$B$2:$B$7, MATCH(F9, Unit_Grades!$A$2:$A$7, 0))*INDEX(Unit_Paths!$D$2:$D$4, MATCH(E9, Unit_Paths!$A$2:$A$4, 0)),0) -> 77 | K9: =ROUND(INDEX(Archetypes!$H$2:$H$127, MATCH(D9, Archetypes!$A$2:$A$127, 0))*INDEX(Unit_Paths!$E$2:$E$4, MATCH(E9, Unit_Paths!$A$2:$A$4, 0)),1) -> 18.9 | L9: =ROUND(INDEX(Archetypes!$I$2:$I$127, MATCH(D9, Archetypes!$A$2:$A$127, 0))*INDEX(Unit_Grades!$C$2:$C$7, MATCH(F9, Unit_Grades!$A$2:$A$7, 0)),1) -> 2.5 | M9: =ROUND(INDEX(Archetypes!$J$2:$J$127, MATCH(D9, Archetypes!$A$2:$A$127, 0))*INDEX(Unit_Grades!$D$2:$D$7, MATCH(F9, Unit_Grades!$A$2:$A$7, 0)),1) -> 1.2 | N9: =ROUND(M9/24,2) -> 0.05
A10: 1 | B10: Elite Asura Militia | C10: Militia | D10: =A10&"|"&C10 -> 1|Militia | E10: Asura (Offense) | F10: Elite | G10: =INDEX(Archetypes!$D$2:$D$127, MATCH(D10, Archetypes!$A$2:$A$127, 0)) -> Line Infantry | H10: =ROUND(INDEX(Archetypes!$E$2:$E$127, MATCH(D10, Archetypes!$A$2:$A$127, 0))*INDEX(Unit_Grades!$B$2:$B$7, MATCH(F10, Unit_Grades!$A$2:$A$7, 0))*INDEX(Unit_Paths!$B$2:$B$4, MATCH(E10, Unit_Paths!$A$2:$A$4, 0)),1) -> 17.3 | I10: =ROUND(INDEX(Archetypes!$F$2:$F$127, MATCH(D10, Archetypes!$A$2:$A$127, 0))*INDEX(Unit_Grades!$B$2:$B$7, MATCH(F10, Unit_Grades!$A$2:$A$7, 0))*INDEX(Unit_Paths!$C$2:$C$4, MATCH(E10, Unit_Paths!$A$2:$A$4, 0)),1) -> 21.4 | J10: =ROUND(INDEX(Archetypes!$G$2:$G$127, MATCH(D10, Archetypes!$A$2:$A$127, 0))*INDEX(Unit_Grades!$B$2:$B$7, MATCH(F10, Unit_Grades!$A$2:$A$7, 0))*INDEX(Unit_Paths!$D$2:$D$4, MATCH(E10, Unit_Paths!$A$2:$A$4, 0)),0) -> 103 | K10: =ROUND(INDEX(Archetypes!$H$2:$H$127, MATCH(D10, Archetypes!$A$2:$A$127, 0))*INDEX(Unit_Paths!$E$2:$E$4, MATCH(E10, Unit_Paths!$A$2:$A$4, 0)),1) -> 18.9 | L10: =ROUND(INDEX(Archetypes!$I$2:$I$127, MATCH(D10, Archetypes!$A$2:$A$127, 0))*INDEX(Unit_Grades!$C$2:$C$7, MATCH(F10, Unit_Grades!$A$2:$A$7, 0)),1) -> 3.2 | M10: =ROUND(INDEX(Archetypes!$J$2:$J$127, MATCH(D10, Archetypes!$A$2:$A$127, 0))*INDEX(Unit_Grades!$D$2:$D$7, MATCH(F10, Unit_Grades!$A$2:$A$7, 0)),1) -> 2 | N10: =ROUND(M10/24,2) -> 0.08
A11: 1 | B11: Ascendant Asura Militia | C11: Militia | D11: =A11&"|"&C11 -> 1|Militia | E11: Asura (Offense) | F11: Ascendant | G11: =INDEX(Archetypes!$D$2:$D$127, MATCH(D11, Archetypes!$A$2:$A$127, 0)) -> Line Infantry | H11: =ROUND(INDEX(Archetypes!$E$2:$E$127, MATCH(D11, Archetypes!$A$2:$A$127, 0))*INDEX(Unit_Grades!$B$2:$B$7, MATCH(F11, Unit_Grades!$A$2:$A$7, 0))*INDEX(Unit_Paths!$B$2:$B$4, MATCH(E11, Unit_Paths!$A$2:$A$4, 0)),1) -> 23 | I11: =ROUND(INDEX(Archetypes!$F$2:$F$127, MATCH(D11, Archetypes!$A$2:$A$127, 0))*INDEX(Unit_Grades!$B$2:$B$7, MATCH(F11, Unit_Grades!$A$2:$A$7, 0))*INDEX(Unit_Paths!$C$2:$C$4, MATCH(E11, Unit_Paths!$A$2:$A$4, 0)),1) -> 28.6 | J11: =ROUND(INDEX(Archetypes!$G$2:$G$127, MATCH(D11, Archetypes!$A$2:$A$127, 0))*INDEX(Unit_Grades!$B$2:$B$7, MATCH(F11, Unit_Grades!$A$2:$A$7, 0))*INDEX(Unit_Paths!$D$2:$D$4, MATCH(E11, Unit_Paths!$A$2:$A$4, 0)),0) -> 137 | K11: =ROUND(INDEX(Archetypes!$H$2:$H$127, MATCH(D11, Archetypes!$A$2:$A$127, 0))*INDEX(Unit_Paths!$E$2:$E$4, MATCH(E11, Unit_Paths!$A$2:$A$4, 0)),1) -> 18.9 | L11: =ROUND(INDEX(Archetypes!$I$2:$I$127, MATCH(D11, Archetypes!$A$2:$A$127, 0))*INDEX(Unit_Grades!$C$2:$C$7, MATCH(F11, Unit_Grades!$A$2:$A$7, 0)),1) -> 4.2 | M11: =ROUND(INDEX(Archetypes!$J$2:$J$127, MATCH(D11, Archetypes!$A$2:$A$127, 0))*INDEX(Unit_Grades!$D$2:$D$7, MATCH(F11, Unit_Grades!$A$2:$A$7, 0)),1) -> 3.2 | N11: =ROUND(M11/24,2) -> 0.13
A12: 1 | B12: Transcendent Asura Militia | C12: Militia | D12: =A12&"|"&C12 -> 1|Militia | E12: Asura (Offense) | F12: Transcendent | G12: =INDEX(Archetypes!$D$2:$D$127, MATCH(D12, Archetypes!$A$2:$A$127, 0)) -> Line Infantry | H12: =ROUND(INDEX(Archetypes!$E$2:$E$127, MATCH(D12, Archetypes!$A$2:$A$127, 0))*INDEX(Unit_Grades!$B$2:$B$7, MATCH(F12, Unit_Grades!$A$2:$A$7, 0))*INDEX(Unit_Paths!$B$2:$B$4, MATCH(E12, Unit_Paths!$A$2:$A$4, 0)),1) -> 30.7 | I12: =ROUND(INDEX(Archetypes!$F$2:$F$127, MATCH(D12, Archetypes!$A$2:$A$127, 0))*INDEX(Unit_Grades!$B$2:$B$7, MATCH(F12, Unit_Grades!$A$2:$A$7, 0))*INDEX(Unit_Paths!$C$2:$C$4, MATCH(E12, Unit_Paths!$A$2:$A$4, 0)),1) -> 38.1 | J12: =ROUND(INDEX(Archetypes!$G$2:$G$127, MATCH(D12, Archetypes!$A$2:$A$127, 0))*INDEX(Unit_Grades!$B$2:$B$7, MATCH(F12, Unit_Grades!$A$2:$A$7, 0))*INDEX(Unit_Paths!$D$2:$D$4, MATCH(E12, Unit_Paths!$A$2:$A$4, 0)),0) -> 182 | K12: =ROUND(INDEX(Archetypes!$H$2:$H$127, MATCH(D12, Archetypes!$A$2:$A$127, 0))*INDEX(Unit_Paths!$E$2:$E$4, MATCH(E12, Unit_Paths!$A$2:$A$4, 0)),1) -> 18.9 | L12: =ROUND(INDEX(Archetypes!$I$2:$I$127, MATCH(D12, Archetypes!$A$2:$A$127, 0))*INDEX(Unit_Grades!$C$2:$C$7, MATCH(F12, Unit_Grades!$A$2:$A$7, 0)),1) -> 5.6 | M12: =ROUND(INDEX(Archetypes!$J$2:$J$127, MATCH(D12, Archetypes!$A$2:$A$127, 0))*INDEX(Unit_Grades!$D$2:$D$7, MATCH(F12, Unit_Grades!$A$2:$A$7, 0)),1) -> 5.7 | N12: =ROUND(M12/24,2) -> 0.24
A13: 1 | B13: Mythic Asura Militia | C13: Militia | D13: =A13&"|"&C13 -> 1|Militia | E13: Asura (Offense) | F13: Mythic | G13: =INDEX(Archetypes!$D$2:$D$127, MATCH(D13, Archetypes!$A$2:$A$127, 0)) -> Line Infantry | H13: =ROUND(INDEX(Archetypes!$E$2:$E$127, MATCH(D13, Archetypes!$A$2:$A$127, 0))*INDEX(Unit_Grades!$B$2:$B$7, MATCH(F13, Unit_Grades!$A$2:$A$7, 0))*INDEX(Unit_Paths!$B$2:$B$4, MATCH(E13, Unit_Paths!$A$2:$A$4, 0)),1) -> 40.3 | I13: =ROUND(INDEX(Archetypes!$F$2:$F$127, MATCH(D13, Archetypes!$A$2:$A$127, 0))*INDEX(Unit_Grades!$B$2:$B$7, MATCH(F13, Unit_Grades!$A$2:$A$7, 0))*INDEX(Unit_Paths!$C$2:$C$4, MATCH(E13, Unit_Paths!$A$2:$A$4, 0)),1) -> 50 | J13: =ROUND(INDEX(Archetypes!$G$2:$G$127, MATCH(D13, Archetypes!$A$2:$A$127, 0))*INDEX(Unit_Grades!$B$2:$B$7, MATCH(F13, Unit_Grades!$A$2:$A$7, 0))*INDEX(Unit_Paths!$D$2:$D$4, MATCH(E13, Unit_Paths!$A$2:$A$4, 0)),0) -> 239 | K13: =ROUND(INDEX(Archetypes!$H$2:$H$127, MATCH(D13, Archetypes!$A$2:$A$127, 0))*INDEX(Unit_Paths!$E$2:$E$4, MATCH(E13, Unit_Paths!$A$2:$A$4, 0)),1) -> 18.9 | L13: =ROUND(INDEX(Archetypes!$I$2:$I$127, MATCH(D13, Archetypes!$A$2:$A$127, 0))*INDEX(Unit_Grades!$C$2:$C$7, MATCH(F13, Unit_Grades!$A$2:$A$7, 0)),1) -> 7.4 | M13: =ROUND(INDEX(Archetypes!$J$2:$J$127, MATCH(D13, Archetypes!$A$2:$A$127, 0))*INDEX(Unit_Grades!$D$2:$D$7, MATCH(F13, Unit_Grades!$A$2:$A$7, 0)),1) -> 9.7 | N13: =ROUND(M13/24,2) -> 0.4
... A2269: 7 | B2269: Mythic Guardian Boundless Swarm | C2269: Boundless Swarm | D2269: =A2269&"|"&C2269 -> 7|Boundless Swarm | E2269: Guardian (Defense) | F2269: Mythic | G2269: =INDEX(Archetypes!$D$2:$D$127, MATCH(D2269, Archetypes!$A$2:$A$127, 0)) -> Drone | H2269: =ROUND(INDEX(Archetypes!$E$2:$E$127, MATCH(D2269, Archetypes!$A$2:$A$127, 0))*INDEX(Unit_Grades!$B$2:$B$7, MATCH(F2269, Unit_Grades!$A$2:$A$7, 0))*INDEX(Unit_Paths!$B$2:$B$4, MATCH(E2269, Unit_Paths!$A$2:$A$4, 0)),1) -> 6783 | I2269: =ROUND(INDEX(Archetypes!$F$2:$F$127, MATCH(D2269, Archetypes!$A$2:$A$127, 0))*INDEX(Unit_Grades!$B$2:$B$7, MATCH(F2269, Unit_Grades!$A$2:$A$7, 0))*INDEX(Unit_Paths!$C$2:$C$4, MATCH(E2269, Unit_Paths!$A$2:$A$4, 0)),1) -> 4725 | J2269: =ROUND(INDEX(Archetypes!$G$2:$G$127, MATCH(D2269, Archetypes!$A$2:$A$127, 0))*INDEX(Unit_Grades!$B$2:$B$7, MATCH(F2269, Unit_Grades!$A$2:$A$7, 0))*INDEX(Unit_Paths!$D$2:$D$4, MATCH(E2269, Unit_Paths!$A$2:$A$4, 0)),0) -> 33810 | K2269: =ROUND(INDEX(Archetypes!$H$2:$H$127, MATCH(D2269, Archetypes!$A$2:$A$127, 0))*INDEX(Unit_Paths!$E$2:$E$4, MATCH(E2269, Unit_Paths!$A$2:$A$4, 0)),1) -> 73.6 | L2269: =ROUND(INDEX(Archetypes!$I$2:$I$127, MATCH(D2269, Archetypes!$A$2:$A$127, 0))*INDEX(Unit_Grades!$C$2:$C$7, MATCH(F2269, Unit_Grades!$A$2:$A$7, 0)),1) -> 888 | M2269: =ROUND(INDEX(Archetypes!$J$2:$J$127, MATCH(D2269, Archetypes!$A$2:$A$127, 0))*INDEX(Unit_Grades!$D$2:$D$7, MATCH(F2269, Unit_Grades!$A$2:$A$7, 0)),1) -> 1168.8 | N2269: =ROUND(M2269/24,2) -> 48.7

Sheet Counter_Matrix
A1: Attacker role ↓ / Defender role → | B1: Line Infantry | C1: Anti-Cavalry | D1: Shock Infantry | E1: Ranged | F1: Skirmisher | G1: Shock Cavalry | H1: Elite Shock | I1: Screen | J1: Siege | K1: Recon | L1: Agent | M1: Logistics | N1: Support | O1: Armor | P1: Anti-Armor | Q1: Anti-Infantry | R1: Anti-Air | S1: Air Superiority | T1: Air Strike | U1: Naval Raider | V1: Naval Escort | W1: Naval Logistics | X1: Capital | Y1: Line Warship | Z1: Carrier | AA1: Drone | AB1: EW/Utility | AC1: Alpha Strike | AD1: Static Defense | AE1: Flagship | AF1: Mobile Capital | AG1: Ultimate Siege | AH1: Conquest | AI1: Cultivator
A2: Line Infantry | B2: 1 | C2: 1.3 | D2: 1 | E2: 1 | F2: 1 | G2: 1 | H2: 1 | I2: 1 | J2: 1 | K2: 1 | L2: 1 | M2: 1 | N2: 1 | O2: 1 | P2: 1 | Q2: 1 | R2: 1 | S2: 1 | T2: 1 | U2: 1 | V2: 1 | W2: 1 | X2: 1 | Y2: 1 | Z2: 1 | AA2: 1 | AB2: 1 | AC2: 1 | AD2: 1 | AE2: 1 | AF2: 1 | AG2: 1 | AH2: 1 | AI2: 1
A3: Anti-Cavalry | B3: 1 | C3: 1 | D3: 1 | E3: 1 | F3: 1 | G3: 1.8 | H3: 1 | I3: 1 | J3: 1 | K3: 1 | L3: 1 | M3: 1 | N3: 1 | O3: 1 | P3: 1 | Q3: 1 | R3: 1 | S3: 1 | T3: 1 | U3: 1 | V3: 1 | W3: 1 | X3: 1 | Y3: 1 | Z3: 1 | AA3: 1 | AB3: 1 | AC3: 1 | AD3: 1 | AE3: 1 | AF3: 1 | AG3: 1 | AH3: 1 | AI3: 1
A4: Shock Infantry | B4: 1 | C4: 1 | D4: 1 | E4: 1.5 | F4: 1 | G4: 1 | H4: 1 | I4: 1 | J4: 1 | K4: 1 | L4: 1 | M4: 1 | N4: 1 | O4: 1 | P4: 1 | Q4: 1 | R4: 1 | S4: 1 | T4: 1 | U4: 1 | V4: 1 | W4: 1 | X4: 1 | Y4: 1 | Z4: 1 | AA4: 1 | AB4: 1 | AC4: 1 | AD4: 1 | AE4: 1 | AF4: 1 | AG4: 1 | AH4: 1 | AI4: 1
A5: Ranged | B5: 1.4 | C5: 1 | D5: 1 | E5: 1 | F5: 1 | G5: 1 | H5: 1 | I5: 1 | J5: 1 | K5: 1 | L5: 1 | M5: 1 | N5: 1 | O5: 1 | P5: 1 | Q5: 1 | R5: 1 | S5: 1 | T5: 1 | U5: 1 | V5: 1 | W5: 1 | X5: 1 | Y5: 1 | Z5: 1 | AA5: 1 | AB5: 1 | AC5: 1 | AD5: 1 | AE5: 1 | AF5: 1 | AG5: 1 | AH5: 1 | AI5: 1
A6: Skirmisher | B6: 1 | C6: 1 | D6: 1 | E6: 1 | F6: 1 | G6: 1 | H6: 1 | I6: 1 | J6: 1.8 | K6: 1 | L6: 1 | M6: 1.9 | N6: 1 | O6: 1 | P6: 1 | Q6: 1 | R6: 1 | S6: 1 | T6: 1 | U6: 1 | V6: 1 | W6: 1 | X6: 1 | Y6: 1 | Z6: 1 | AA6: 1 | AB6: 1 | AC6: 1 | AD6: 1 | AE6: 1 | AF6: 1 | AG6: 1 | AH6: 1 | AI6: 1
A7: Shock Cavalry | B7: 1 | C7: 1 | D7: 1 | E7: 1.7 | F7: 1 | G7: 1 | H7: 1 | I7: 1 | J7: 1.8 | K7: 1 | L7: 1 | M7: 1 | N7: 1 | O7: 1 | P7: 1 | Q7: 1 | R7: 1 | S7: 1 | T7: 1 | U7: 1 | V7: 1 | W7: 1 | X7: 1 | Y7: 1 | Z7: 1 | AA7: 1 | AB7: 1 | AC7: 1 | AD7: 1 | AE7: 1 | AF7: 1 | AG7: 1 | AH7: 1 | AI7: 1
A8: Elite Shock | B8: 1.5 | C8: 1 | D8: 1 | E8: 1 | F8: 1 | G8: 1 | H8: 1 | I8: 1 | J8: 1 | K8: 1 | L8: 1 | M8: 1 | N8: 1 | O8: 1 | P8: 1 | Q8: 1 | R8: 1 | S8: 1 | T8: 1 | U8: 1 | V8: 1 | W8: 1 | X8: 1 | Y8: 1 | Z8: 1 | AA8: 1 | AB8: 1 | AC8: 1 | AD8: 1 | AE8: 1 | AF8: 1 | AG8: 1 | AH8: 1 | AI8: 1
A9: Screen | B9: 1 | C9: 1 | D9: 1 | E9: 1 | F9: 1.4 | G9: 1 | H9: 1 | I9: 1 | J9: 1 | K9: 1 | L9: 1 | M9: 1 | N9: 1 | O9: 1 | P9: 1 | Q9: 1 | R9: 1 | S9: 1 | T9: 1 | U9: 1 | V9: 1 | W9: 1 | X9: 1 | Y9: 1 | Z9: 1 | AA9: 1 | AB9: 1 | AC9: 1.5 | AD9: 1 | AE9: 1 | AF9: 1 | AG9: 1 | AH9: 1 | AI9: 1
A10: Siege | B10: 1 | C10: 1 | D10: 1 | E10: 1 | F10: 1 | G10: 1 | H10: 1 | I10: 1 | J10: 1 | K10: 1 | L10: 1 | M10: 1 | N10: 1 | O10: 1 | P10: 1 | Q10: 1 | R10: 1 | S10: 1 | T10: 1 | U10: 1 | V10: 1 | W10: 1 | X10: 1 | Y10: 1 | Z10: 1 | AA10: 1 | AB10: 1 | AC10: 1 | AD10: 1.8 | AE10: 1 | AF10: 1 | AG10: 1 | AH10: 1 | AI10: 1
A11: Recon | B11: 0.4 | C11: 0.4 | D11: 0.4 | E11: 0.4 | F11: 0.4 | G11: 0.4 | H11: 0.4 | I11: 0.4 | J11: 0.4 | K11: 1 | L11: 0.4 | M11: 1 | N11: 0.4 | O11: 0.4 | P11: 0.4 | Q11: 0.4 | R11: 0.4 | S11: 0.4 | T11: 0.4 | U11: 0.4 | V11: 0.4 | W11: 0.4 | X11: 0.4 | Y11: 0.4 | Z11: 0.4 | AA11: 0.4 | AB11: 0.4 | AC11: 0.4 | AD11: 0.4 | AE11: 0.4 | AF11: 0.4 | AG11: 0.4 | AH11: 0.4 | AI11: 0.4
A12: Agent | B12: 1 | C12: 1 | D12: 1 | E12: 1 | F12: 1 | G12: 1 | H12: 1 | I12: 1 | J12: 1 | K12: 1 | L12: 1 | M12: 1 | N12: 1 | O12: 1 | P12: 1 | Q12: 1 | R12: 1 | S12: 1 | T12: 1 | U12: 1 | V12: 1 | W12: 1 | X12: 1 | Y12: 1 | Z12: 1 | AA12: 1 | AB12: 1 | AC12: 1 | AD12: 1 | AE12: 1 | AF12: 1 | AG12: 1 | AH12: 1.6 | AI12: 1
A13: Logistics | B13: 0.4 | C13: 0.4 | D13: 0.4 | E13: 0.4 | F13: 0.4 | G13: 0.4 | H13: 0.4 | I13: 0.4 | J13: 0.4 | K13: 1 | L13: 0.4 | M13: 1 | N13: 0.4 | O13: 0.4 | P13: 0.4 | Q13: 0.4 | R13: 0.4 | S13: 0.4 | T13: 0.4 | U13: 0.4 | V13: 0.4 | W13: 0.4 | X13: 0.4 | Y13: 0.4 | Z13: 0.4 | AA13: 0.4 | AB13: 0.4 | AC13: 0.4 | AD13: 0.4 | AE13: 0.4 | AF13: 0.4 | AG13: 0.4 | AH13: 0.4 | AI13: 0.4
... A35: Cultivator | B35: 1.3 | C35: 1 | D35: 1 | E35: 1 | F35: 1 | G35: 1 | H35: 1 | I35: 1 | J35: 1 | K35: 1 | L35: 1 | M35: 1 | N35: 1 | O35: 1 | P35: 1 | Q35: 1 | R35: 1 | S35: 1 | T35: 1 | U35: 1 | V35: 1 | W35: 1 | X35: 1 | Y35: 1 | Z35: 1 | AA35: 1 | AB35: 1 | AC35: 1 | AD35: 1 | AE35: 1 | AF35: 1 | AG35: 1 | AH35: 1 | AI35: 1
A37: Damage multiplier applied to attacker vs. that defender role. 1.0 = neutral. Design inputs (blue), server-tunable.

Sheet Research_Disciplines
A1: Discipline | B1: Era | C1: Branch | D1: Levels | E1: Grades | F1: Per-level effect (base) | G1: Grade breakthrough effect | H1: Prerequisite
A2: Agrarian Arts | B2: 1 | C2: Economy | D2: 0–1337 | E2: 42 | F2: +0.3% output in era systems / level | G2: Each grade (every 32 levels): unlocks a fork choice, a unit-grade gate, or an edict; requires Grade-Up cost + prerequisite (Grades_Realms) | H2: None
A3: Tribal Warfare | B3: 1 | C3: Military | D3: 0–1337 | E3: 42 | F3: +0.25% era unit effectiveness / level | G3: Each grade (every 32 levels): unlocks a fork choice, a unit-grade gate, or an edict; requires Grade-Up cost + prerequisite (Grades_Realms) | H3: None
A4: Hearth Law | B4: 1 | C4: Statecraft | D4: 0–1337 | E4: 42 | F4: +0.3% era governance metric / level | G4: Each grade (every 32 levels): unlocks a fork choice, a unit-grade gate, or an edict; requires Grade-Up cost + prerequisite (Grades_Realms) | H4: None
A5: Guild Economics | B5: 2 | C5: Economy | D5: 0–1337 | E5: 42 | F5: +0.3% output in era systems / level | G5: Each grade (every 32 levels): unlocks a fork choice, a unit-grade gate, or an edict; requires Grade-Up cost + prerequisite (Grades_Realms) | H5: All Era 1 disciplines at Grade 12+ and era ascension complete
A6: Feudal Arms | B6: 2 | C6: Military | D6: 0–1337 | E6: 42 | F6: +0.25% era unit effectiveness / level | G6: Each grade (every 32 levels): unlocks a fork choice, a unit-grade gate, or an edict; requires Grade-Up cost + prerequisite (Grades_Realms) | H6: All Era 1 disciplines at Grade 12+ and era ascension complete
A7: Crown & Charter | B7: 2 | C7: Statecraft | D7: 0–1337 | E7: 42 | F7: +0.3% era governance metric / level | G7: Each grade (every 32 levels): unlocks a fork choice, a unit-grade gate, or an edict; requires Grade-Up cost + prerequisite (Grades_Realms) | H7: All Era 1 disciplines at Grade 12+ and era ascension complete
A8: Mercantile Science | B8: 3 | C8: Economy | D8: 0–1337 | E8: 42 | F8: +0.3% output in era systems / level | G8: Each grade (every 32 levels): unlocks a fork choice, a unit-grade gate, or an edict; requires Grade-Up cost + prerequisite (Grades_Realms) | H8: All Era 2 disciplines at Grade 12+ and era ascension complete
A9: Powder Doctrine | B9: 3 | C9: Military | D9: 0–1337 | E9: 42 | F9: +0.25% era unit effectiveness / level | G9: Each grade (every 32 levels): unlocks a fork choice, a unit-grade gate, or an edict; requires Grade-Up cost + prerequisite (Grades_Realms) | H9: All Era 2 disciplines at Grade 12+ and era ascension complete
A10: Imperial Administration | B10: 3 | C10: Statecraft | D10: 0–1337 | E10: 42 | F10: +0.3% era governance metric / level | G10: Each grade (every 32 levels): unlocks a fork choice, a unit-grade gate, or an edict; requires Grade-Up cost + prerequisite (Grades_Realms) | H10: All Era 2 disciplines at Grade 12+ and era ascension complete
A11: Industrial Method | B11: 4 | C11: Economy | D11: 0–1337 | E11: 42 | F11: +0.3% output in era systems / level | G11: Each grade (every 32 levels): unlocks a fork choice, a unit-grade gate, or an edict; requires Grade-Up cost + prerequisite (Grades_Realms) | H11: All Era 3 disciplines at Grade 12+ and era ascension complete
A12: Combined Arms | B12: 4 | C12: Military | D12: 0–1337 | E12: 42 | F12: +0.25% era unit effectiveness / level | G12: Each grade (every 32 levels): unlocks a fork choice, a unit-grade gate, or an edict; requires Grade-Up cost + prerequisite (Grades_Realms) | H12: All Era 3 disciplines at Grade 12+ and era ascension complete
A13: Mass Society | B13: 4 | C13: Statecraft | D13: 0–1337 | E13: 42 | F13: +0.3% era governance metric / level | G13: Each grade (every 32 levels): unlocks a fork choice, a unit-grade gate, or an edict; requires Grade-Up cost + prerequisite (Grades_Realms) | H13: All Era 3 disciplines at Grade 12+ and era ascension complete
... A22: Dao of Rule | B22: 7 | C22: Statecraft | D22: 0–1337 | E22: 42 | F22: +0.3% era governance metric / level | G22: Each grade (every 32 levels): unlocks a fork choice, a unit-grade gate, or an edict; requires Grade-Up cost + prerequisite (Grades_Realms) | H22: All Era 6 disciplines at Grade 12+ and era ascension complete
A24: Research time uses the same 500-year curve as buildings: Time(L) = K × (L+1)^1.9 × 1.003^L with K from Building_Levels!H2, so a full 0→1337 discipline climb totals exactly 500 years. Research cost at level L = base_rp × (L+1)^2.2 × 1.0035^L; grade breakthroughs use Grades_Realms Qi/resource costs. Per-level effects soft-cap: total joint non-doctrine bonus ≤ +40% (GDD §17.1).

Sheet Equipment_Catalog
A1: Item | B1: Slot | C1: Tier | D1: Quality | E1: Bonus % | F1: Material Cost Mult | G1: Source | I1: Slot base %
A2: Crude Bronze War Axe | B2: Weapon | C2: 1 | D2: Crude | E2: =ROUND($J$2*(1+0.12*(C2-1))*0.7,1) -> 4.2 | F2: 0.8 | G2: Crafted (Smithy line by tier; Masterwork needs max Construction or Great Engineer) | I2: Weapon | J2: 6
A3: Standard Bronze War Axe | B3: Weapon | C3: 1 | D3: Standard | E3: =ROUND($J$2*(1+0.12*(C3-1))*1,1) -> 6 | F3: 1 | G3: Crafted (Smithy line by tier; Masterwork needs max Construction or Great Engineer) | I3: Protection | J3: 5
A4: Fine Bronze War Axe | B4: Weapon | C4: 1 | D4: Fine | E4: =ROUND($J$2*(1+0.12*(C4-1))*1.25,1) -> 7.5 | F4: 1.5 | G4: Crafted (Smithy line by tier; Masterwork needs max Construction or Great Engineer) | I4: Utility | J4: 4
A5: Masterwork Bronze War Axe | B5: Weapon | C5: 1 | D5: Masterwork | E5: =ROUND($J$2*(1+0.12*(C5-1))*1.6,1) -> 9.6 | F5: 2.6 | G5: Crafted (Smithy line by tier; Masterwork needs max Construction or Great Engineer)
A6: Relic Bronze War Axe | B6: Weapon | C6: 1 | D6: Relic | E6: =ROUND($J$2*(1+0.12*(C6-1))*2.2,1) -> 13.2 | F6: — | G6: Drop only: vaults, archaeology, tribulation forging | I6: Tier mult = 1 + 0.12×(tier−1)
A7: Crude Iron Pike | B7: Weapon | C7: 2 | D7: Crude | E7: =ROUND($J$2*(1+0.12*(C7-1))*0.7,1) -> 4.7 | F7: 0.8 | G7: Crafted (Smithy line by tier; Masterwork needs max Construction or Great Engineer)
A8: Standard Iron Pike | B8: Weapon | C8: 2 | D8: Standard | E8: =ROUND($J$2*(1+0.12*(C8-1))*1,1) -> 6.7 | F8: 1 | G8: Crafted (Smithy line by tier; Masterwork needs max Construction or Great Engineer)
A9: Fine Iron Pike | B9: Weapon | C9: 2 | D9: Fine | E9: =ROUND($J$2*(1+0.12*(C9-1))*1.25,1) -> 8.4 | F9: 1.5 | G9: Crafted (Smithy line by tier; Masterwork needs max Construction or Great Engineer)
A10: Masterwork Iron Pike | B10: Weapon | C10: 2 | D10: Masterwork | E10: =ROUND($J$2*(1+0.12*(C10-1))*1.6,1) -> 10.8 | F10: 2.6 | G10: Crafted (Smithy line by tier; Masterwork needs max Construction or Great Engineer)
A11: Relic Iron Pike | B11: Weapon | C11: 2 | D11: Relic | E11: =ROUND($J$2*(1+0.12*(C11-1))*2.2,1) -> 14.8 | F11: — | G11: Drop only: vaults, archaeology, tribulation forging
A12: Crude Folded Steel Blade | B12: Weapon | C12: 3 | D12: Crude | E12: =ROUND($J$2*(1+0.12*(C12-1))*0.7,1) -> 5.2 | F12: 0.8 | G12: Crafted (Smithy line by tier; Masterwork needs max Construction or Great Engineer)
A13: Standard Folded Steel Blade | B13: Weapon | C13: 3 | D13: Standard | E13: =ROUND($J$2*(1+0.12*(C13-1))*1,1) -> 7.4 | F13: 1 | G13: Crafted (Smithy line by tier; Masterwork needs max Construction or Great Engineer)
A14: Fine Folded Steel Blade | B14: Weapon | C14: 3 | D14: Fine | E14: =ROUND($J$2*(1+0.12*(C14-1))*1.25,1) -> 9.3 | F14: 1.5 | G14: Crafted (Smithy line by tier; Masterwork needs max Construction or Great Engineer)
A15: Masterwork Folded Steel Blade | B15: Weapon | C15: 3 | D15: Masterwork | E15: =ROUND($J$2*(1+0.12*(C15-1))*1.6,1) -> 11.9 | F15: 2.6 | G15: Crafted (Smithy line by tier; Masterwork needs max Construction or Great Engineer)
A16: Relic Folded Steel Blade | B16: Weapon | C16: 3 | D16: Relic | E16: =ROUND($J$2*(1+0.12*(C16-1))*2.2,1) -> 16.4 | F16: — | G16: Drop only: vaults, archaeology, tribulation forging
A17: Crude Rifled Musket | B17: Weapon | C17: 4 | D17: Crude | E17: =ROUND($J$2*(1+0.12*(C17-1))*0.7,1) -> 5.7 | F17: 0.8 | G17: Crafted (Smithy line by tier; Masterwork needs max Construction or Great Engineer)
A18: Standard Rifled Musket | B18: Weapon | C18: 4 | D18: Standard | E18: =ROUND($J$2*(1+0.12*(C18-1))*1,1) -> 8.2 | F18: 1 | G18: Crafted (Smithy line by tier; Masterwork needs max Construction or Great Engineer)
A19: Fine Rifled Musket | B19: Weapon | C19: 4 | D19: Fine | E19: =ROUND($J$2*(1+0.12*(C19-1))*1.25,1) -> 10.2 | F19: 1.5 | G19: Crafted (Smithy line by tier; Masterwork needs max Construction or Great Engineer)
A20: Masterwork Rifled Musket | B20: Weapon | C20: 4 | D20: Masterwork | E20: =ROUND($J$2*(1+0.12*(C20-1))*1.6,1) -> 13.1 | F20: 2.6 | G20: Crafted (Smithy line by tier; Masterwork needs max Construction or Great Engineer)
A21: Relic Rifled Musket | B21: Weapon | C21: 4 | D21: Relic | E21: =ROUND($J$2*(1+0.12*(C21-1))*2.2,1) -> 18 | F21: — | G21: Drop only: vaults, archaeology, tribulation forging
A22: Crude Bolt-Action Rifle | B22: Weapon | C22: 5 | D22: Crude | E22: =ROUND($J$2*(1+0.12*(C22-1))*0.7,1) -> 6.2 | F22: 0.8 | G22: Crafted (Smithy line by tier; Masterwork needs max Construction or Great Engineer)
A23: Standard Bolt-Action Rifle | B23: Weapon | C23: 5 | D23: Standard | E23: =ROUND($J$2*(1+0.12*(C23-1))*1,1) -> 8.9 | F23: 1 | G23: Crafted (Smithy line by tier; Masterwork needs max Construction or Great Engineer)
A24: Fine Bolt-Action Rifle | B24: Weapon | C24: 5 | D24: Fine | E24: =ROUND($J$2*(1+0.12*(C24-1))*1.25,1) -> 11.1 | F24: 1.5 | G24: Crafted (Smithy line by tier; Masterwork needs max Construction or Great Engineer)
A25: Masterwork Bolt-Action Rifle | B25: Weapon | C25: 5 | D25: Masterwork | E25: =ROUND($J$2*(1+0.12*(C25-1))*1.6,1) -> 14.2 | F25: 2.6 | G25: Crafted (Smithy line by tier; Masterwork needs max Construction or Great Engineer)
A26: Relic Bolt-Action Rifle | B26: Weapon | C26: 5 | D26: Relic | E26: =ROUND($J$2*(1+0.12*(C26-1))*2.2,1) -> 19.5 | F26: — | G26: Drop only: vaults, archaeology, tribulation forging
A27: Crude Composite Railgun | B27: Weapon | C27: 6 | D27: Crude | E27: =ROUND($J$2*(1+0.12*(C27-1))*0.7,1) -> 6.7 | F27: 0.8 | G27: Crafted (Smithy line by tier; Masterwork needs max Construction or Great Engineer)
A28: Standard Composite Railgun | B28: Weapon | C28: 6 | D28: Standard | E28: =ROUND($J$2*(1+0.12*(C28-1))*1,1) -> 9.6 | F28: 1 | G28: Crafted (Smithy line by tier; Masterwork needs max Construction or Great Engineer)
A29: Fine Composite Railgun | B29: Weapon | C29: 6 | D29: Fine | E29: =ROUND($J$2*(1+0.12*(C29-1))*1.25,1) -> 12 | F29: 1.5 | G29: Crafted (Smithy line by tier; Masterwork needs max Construction or Great Engineer)
A30: Masterwork Composite Railgun | B30: Weapon | C30: 6 | D30: Masterwork | E30: =ROUND($J$2*(1+0.12*(C30-1))*1.6,1) -> 15.4 | F30: 2.6 | G30: Crafted (Smithy line by tier; Masterwork needs max Construction or Great Engineer)
A31: Relic Composite Railgun | B31: Weapon | C31: 6 | D31: Relic | E31: =ROUND($J$2*(1+0.12*(C31-1))*2.2,1) -> 21.1 | F31: — | G31: Drop only: vaults, archaeology, tribulation forging
A32: Crude Titanium Gauss Cannon | B32: Weapon | C32: 7 | D32: Crude | E32: =ROUND($J$2*(1+0.12*(C32-1))*0.7,1) -> 7.2 | F32: 0.8 | G32: Crafted (Smithy line by tier; Masterwork needs max Construction or Great Engineer)
A33: Standard Titanium Gauss Cannon | B33: Weapon | C33: 7 | D33: Standard | E33: =ROUND($J$2*(1+0.12*(C33-1))*1,1) -> 10.3 | F33: 1 | G33: Crafted (Smithy line by tier; Masterwork needs max Construction or Great Engineer)
A34: Fine Titanium Gauss Cannon | B34: Weapon | C34: 7 | D34: Fine | E34: =ROUND($J$2*(1+0.12*(C34-1))*1.25,1) -> 12.9 | F34: 1.5 | G34: Crafted (Smithy line by tier; Masterwork needs max Construction or Great Engineer)
A35: Masterwork Titanium Gauss Cannon | B35: Weapon | C35: 7 | D35: Masterwork | E35: =ROUND($J$2*(1+0.12*(C35-1))*1.6,1) -> 16.5 | F35: 2.6 | G35: Crafted (Smithy line by tier; Masterwork needs max Construction or Great Engineer)
A36: Relic Titanium Gauss Cannon | B36: Weapon | C36: 7 | D36: Relic | E36: =ROUND($J$2*(1+0.12*(C36-1))*2.2,1) -> 22.7 | F36: — | G36: Drop only: vaults, archaeology, tribulation forging
A37: Crude Exotic Plasma Lance | B37: Weapon | C37: 8 | D37: Crude | E37: =ROUND($J$2*(1+0.12*(C37-1))*0.7,1) -> 7.7 | F37: 0.8 | G37: Crafted (Smithy line by tier; Masterwork needs max Construction or Great Engineer)
A38: Standard Exotic Plasma Lance | B38: Weapon | C38: 8 | D38: Standard | E38: =ROUND($J$2*(1+0.12*(C38-1))*1,1) -> 11 | F38: 1 | G38: Crafted (Smithy line by tier; Masterwork needs max Construction or Great Engineer)
A39: Fine Exotic Plasma Lance | B39: Weapon | C39: 8 | D39: Fine | E39: =ROUND($J$2*(1+0.12*(C39-1))*1.25,1) -> 13.8 | F39: 1.5 | G39: Crafted (Smithy line by tier; Masterwork needs max Construction or Great Engineer)
A40: Masterwork Exotic Plasma Lance | B40: Weapon | C40: 8 | D40: Masterwork | E40: =ROUND($J$2*(1+0.12*(C40-1))*1.6,1) -> 17.7 | F40: 2.6 | G40: Crafted (Smithy line by tier; Masterwork needs max Construction or Great Engineer)
A41: Relic Exotic Plasma Lance | B41: Weapon | C41: 8 | D41: Relic | E41: =ROUND($J$2*(1+0.12*(C41-1))*2.2,1) -> 24.3 | F41: — | G41: Drop only: vaults, archaeology, tribulation forging
A42: Crude Lattice Projector | B42: Weapon | C42: 9 | D42: Crude | E42: =ROUND($J$2*(1+0.12*(C42-1))*0.7,1) -> 8.2 | F42: 0.8 | G42: Crafted (Smithy line by tier; Masterwork needs max Construction or Great Engineer)
A43: Standard Lattice Projector | B43: Weapon | C43: 9 | D43: Standard | E43: =ROUND($J$2*(1+0.12*(C43-1))*1,1) -> 11.8 | F43: 1 | G43: Crafted (Smithy line by tier; Masterwork needs max Construction or Great Engineer)
A44: Fine Lattice Projector | B44: Weapon | C44: 9 | D44: Fine | E44: =ROUND($J$2*(1+0.12*(C44-1))*1.25,1) -> 14.7 | F44: 1.5 | G44: Crafted (Smithy line by tier; Masterwork needs max Construction or Great Engineer)
A45: Masterwork Lattice Projector | B45: Weapon | C45: 9 | D45: Masterwork | E45: =ROUND($J$2*(1+0.12*(C45-1))*1.6,1) -> 18.8 | F45: 2.6 | G45: Crafted (Smithy line by tier; Masterwork needs max Construction or Great Engineer)
A46: Relic Lattice Projector | B46: Weapon | C46: 9 | D46: Relic | E46: =ROUND($J$2*(1+0.12*(C46-1))*2.2,1) -> 25.9 | F46: — | G46: Drop only: vaults, archaeology, tribulation forging
A47: Crude Hide Cuirass | B47: Protection | C47: 1 | D47: Crude | E47: =ROUND($J$3*(1+0.12*(C47-1))*0.7,1) -> 3.5 | F47: 0.8 | G47: Crafted (Smithy line by tier; Masterwork needs max Construction or Great Engineer)
A48: Standard Hide Cuirass | B48: Protection | C48: 1 | D48: Standard | E48: =ROUND($J$3*(1+0.12*(C48-1))*1,1) -> 5 | F48: 1 | G48: Crafted (Smithy line by tier; Masterwork needs max Construction or Great Engineer)
A49: Fine Hide Cuirass | B49: Protection | C49: 1 | D49: Fine | E49: =ROUND($J$3*(1+0.12*(C49-1))*1.25,1) -> 6.3 | F49: 1.5 | G49: Crafted (Smithy line by tier; Masterwork needs max Construction or Great Engineer)
A50: Masterwork Hide Cuirass | B50: Protection | C50: 1 | D50: Masterwork | E50: =ROUND($J$3*(1+0.12*(C50-1))*1.6,1) -> 8 | F50: 2.6 | G50: Crafted (Smithy line by tier; Masterwork needs max Construction or Great Engineer)
A51: Relic Hide Cuirass | B51: Protection | C51: 1 | D51: Relic | E51: =ROUND($J$3*(1+0.12*(C51-1))*2.2,1) -> 11 | F51: — | G51: Drop only: vaults, archaeology, tribulation forging
A52: Crude Riveted Mail | B52: Protection | C52: 2 | D52: Crude | E52: =ROUND($J$3*(1+0.12*(C52-1))*0.7,1) -> 3.9 | F52: 0.8 | G52: Crafted (Smithy line by tier; Masterwork needs max Construction or Great Engineer)
A53: Standard Riveted Mail | B53: Protection | C53: 2 | D53: Standard | E53: =ROUND($J$3*(1+0.12*(C53-1))*1,1) -> 5.6 | F53: 1 | G53: Crafted (Smithy line by tier; Masterwork needs max Construction or Great Engineer)
A54: Fine Riveted Mail | B54: Protection | C54: 2 | D54: Fine | E54: =ROUND($J$3*(1+0.12*(C54-1))*1.25,1) -> 7 | F54: 1.5 | G54: Crafted (Smithy line by tier; Masterwork needs max Construction or Great Engineer)
A55: Masterwork Riveted Mail | B55: Protection | C55: 2 | D55: Masterwork | E55: =ROUND($J$3*(1+0.12*(C55-1))*1.6,1) -> 9 | F55: 2.6 | G55: Crafted (Smithy line by tier; Masterwork needs max Construction or Great Engineer)
A56: Relic Riveted Mail | B56: Protection | C56: 2 | D56: Relic | E56: =ROUND($J$3*(1+0.12*(C56-1))*2.2,1) -> 12.3 | F56: — | G56: Drop only: vaults, archaeology, tribulation forging
A57: Crude Plate Harness | B57: Protection | C57: 3 | D57: Crude | E57: =ROUND($J$3*(1+0.12*(C57-1))*0.7,1) -> 4.3 | F57: 0.8 | G57: Crafted (Smithy line by tier; Masterwork needs max Construction or Great Engineer)
A58: Standard Plate Harness | B58: Protection | C58: 3 | D58: Standard | E58: =ROUND($J$3*(1+0.12*(C58-1))*1,1) -> 6.2 | F58: 1 | G58: Crafted (Smithy line by tier; Masterwork needs max Construction or Great Engineer)
A59: Fine Plate Harness | B59: Protection | C59: 3 | D59: Fine | E59: =ROUND($J$3*(1+0.12*(C59-1))*1.25,1) -> 7.8 | F59: 1.5 | G59: Crafted (Smithy line by tier; Masterwork needs max Construction or Great Engineer)
A60: Masterwork Plate Harness | B60: Protection | C60: 3 | D60: Masterwork | E60: =ROUND($J$3*(1+0.12*(C60-1))*1.6,1) -> 9.9 | F60: 2.6 | G60: Crafted (Smithy line by tier; Masterwork needs max Construction or Great Engineer)
A61: Relic Plate Harness | B61: Protection | C61: 3 | D61: Relic | E61: =ROUND($J$3*(1+0.12*(C61-1))*2.2,1) -> 13.6 | F61: — | G61: Drop only: vaults, archaeology, tribulation forging
A62: Crude Sapper Breastplate | B62: Protection | C62: 4 | D62: Crude | E62: =ROUND($J$3*(1+0.12*(C62-1))*0.7,1) -> 4.8 | F62: 0.8 | G62: Crafted (Smithy line by tier; Masterwork needs max Construction or Great Engineer)
A63: Standard Sapper Breastplate | B63: Protection | C63: 4 | D63: Standard | E63: =ROUND($J$3*(1+0.12*(C63-1))*1,1) -> 6.8 | F63: 1 | G63: Crafted (Smithy line by tier; Masterwork needs max Construction or Great Engineer)
A64: Fine Sapper Breastplate | B64: Protection | C64: 4 | D64: Fine | E64: =ROUND($J$3*(1+0.12*(C64-1))*1.25,1) -> 8.5 | F64: 1.5 | G64: Crafted (Smithy line by tier; Masterwork needs max Construction or Great Engineer)
A65: Masterwork Sapper Breastplate | B65: Protection | C65: 4 | D65: Masterwork | E65: =ROUND($J$3*(1+0.12*(C65-1))*1.6,1) -> 10.9 | F65: 2.6 | G65: Crafted (Smithy line by tier; Masterwork needs max Construction or Great Engineer)
A66: Relic Sapper Breastplate | B66: Protection | C66: 4 | D66: Relic | E66: =ROUND($J$3*(1+0.12*(C66-1))*2.2,1) -> 15 | F66: — | G66: Drop only: vaults, archaeology, tribulation forging
A67: Crude Steel Helm & Webbing | B67: Protection | C67: 5 | D67: Crude | E67: =ROUND($J$3*(1+0.12*(C67-1))*0.7,1) -> 5.2 | F67: 0.8 | G67: Crafted (Smithy line by tier; Masterwork needs max Construction or Great Engineer)
A68: Standard Steel Helm & Webbing | B68: Protection | C68: 5 | D68: Standard | E68: =ROUND($J$3*(1+0.12*(C68-1))*1,1) -> 7.4 | F68: 1 | G68: Crafted (Smithy line by tier; Masterwork needs max Construction or Great Engineer)
A69: Fine Steel Helm & Webbing | B69: Protection | C69: 5 | D69: Fine | E69: =ROUND($J$3*(1+0.12*(C69-1))*1.25,1) -> 9.3 | F69: 1.5 | G69: Crafted (Smithy line by tier; Masterwork needs max Construction or Great Engineer)
A70: Masterwork Steel Helm & Webbing | B70: Protection | C70: 5 | D70: Masterwork | E70: =ROUND($J$3*(1+0.12*(C70-1))*1.6,1) -> 11.8 | F70: 2.6 | G70: Crafted (Smithy line by tier; Masterwork needs max Construction or Great Engineer)
A71: Relic Steel Helm & Webbing | B71: Protection | C71: 5 | D71: Relic | E71: =ROUND($J$3*(1+0.12*(C71-1))*2.2,1) -> 16.3 | F71: — | G71: Drop only: vaults, archaeology, tribulation forging
A72: Crude Composite Plate | B72: Protection | C72: 6 | D72: Crude | E72: =ROUND($J$3*(1+0.12*(C72-1))*0.7,1) -> 5.6 | F72: 0.8 | G72: Crafted (Smithy line by tier; Masterwork needs max Construction or Great Engineer)
A73: Standard Composite Plate | B73: Protection | C73: 6 | D73: Standard | E73: =ROUND($J$3*(1+0.12*(C73-1))*1,1) -> 8 | F73: 1 | G73: Crafted (Smithy line by tier; Masterwork needs max Construction or Great Engineer)
A74: Fine Composite Plate | B74: Protection | C74: 6 | D74: Fine | E74: =ROUND($J$3*(1+0.12*(C74-1))*1.25,1) -> 10 | F74: 1.5 | G74: Crafted (Smithy line by tier; Masterwork needs max Construction or Great Engineer)
A75: Masterwork Composite Plate | B75: Protection | C75: 6 | D75: Masterwork | E75: =ROUND($J$3*(1+0.12*(C75-1))*1.6,1) -> 12.8 | F75: 2.6 | G75: Crafted (Smithy line by tier; Masterwork needs max Construction or Great Engineer)
A76: Relic Composite Plate | B76: Protection | C76: 6 | D76: Relic | E76: =ROUND($J$3*(1+0.12*(C76-1))*2.2,1) -> 17.6 | F76: — | G76: Drop only: vaults, archaeology, tribulation forging
A77: Crude Titanium Ablative | B77: Protection | C77: 7 | D77: Crude | E77: =ROUND($J$3*(1+0.12*(C77-1))*0.7,1) -> 6 | F77: 0.8 | G77: Crafted (Smithy line by tier; Masterwork needs max Construction or Great Engineer)
A78: Standard Titanium Ablative | B78: Protection | C78: 7 | D78: Standard | E78: =ROUND($J$3*(1+0.12*(C78-1))*1,1) -> 8.6 | F78: 1 | G78: Crafted (Smithy line by tier; Masterwork needs max Construction or Great Engineer)
A79: Fine Titanium Ablative | B79: Protection | C79: 7 | D79: Fine | E79: =ROUND($J$3*(1+0.12*(C79-1))*1.25,1) -> 10.8 | F79: 1.5 | G79: Crafted (Smithy line by tier; Masterwork needs max Construction or Great Engineer)
A80: Masterwork Titanium Ablative | B80: Protection | C80: 7 | D80: Masterwork | E80: =ROUND($J$3*(1+0.12*(C80-1))*1.6,1) -> 13.8 | F80: 2.6 | G80: Crafted (Smithy line by tier; Masterwork needs max Construction or Great Engineer)
A81: Relic Titanium Ablative | B81: Protection | C81: 7 | D81: Relic | E81: =ROUND($J$3*(1+0.12*(C81-1))*2.2,1) -> 18.9 | F81: — | G81: Drop only: vaults, archaeology, tribulation forging
A82: Crude Exotic Phase Armor | B82: Protection | C82: 8 | D82: Crude | E82: =ROUND($J$3*(1+0.12*(C82-1))*0.7,1) -> 6.4 | F82: 0.8 | G82: Crafted (Smithy line by tier; Masterwork needs max Construction or Great Engineer)
A83: Standard Exotic Phase Armor | B83: Protection | C83: 8 | D83: Standard | E83: =ROUND($J$3*(1+0.12*(C83-1))*1,1) -> 9.2 | F83: 1 | G83: Crafted (Smithy line by tier; Masterwork needs max Construction or Great Engineer)
A84: Fine Exotic Phase Armor | B84: Protection | C84: 8 | D84: Fine | E84: =ROUND($J$3*(1+0.12*(C84-1))*1.25,1) -> 11.5 | F84: 1.5 | G84: Crafted (Smithy line by tier; Masterwork needs max Construction or Great Engineer)
A85: Masterwork Exotic Phase Armor | B85: Protection | C85: 8 | D85: Masterwork | E85: =ROUND($J$3*(1+0.12*(C85-1))*1.6,1) -> 14.7 | F85: 2.6 | G85: Crafted (Smithy line by tier; Masterwork needs max Construction or Great Engineer)
A86: Relic Exotic Phase Armor | B86: Protection | C86: 8 | D86: Relic | E86: =ROUND($J$3*(1+0.12*(C86-1))*2.2,1) -> 20.2 | F86: — | G86: Drop only: vaults, archaeology, tribulation forging
A87: Crude Lattice Aegis | B87: Protection | C87: 9 | D87: Crude | E87: =ROUND($J$3*(1+0.12*(C87-1))*0.7,1) -> 6.9 | F87: 0.8 | G87: Crafted (Smithy line by tier; Masterwork needs max Construction or Great Engineer)
A88: Standard Lattice Aegis | B88: Protection | C88: 9 | D88: Standard | E88: =ROUND($J$3*(1+0.12*(C88-1))*1,1) -> 9.8 | F88: 1 | G88: Crafted (Smithy line by tier; Masterwork needs max Construction or Great Engineer)
A89: Fine Lattice Aegis | B89: Protection | C89: 9 | D89: Fine | E89: =ROUND($J$3*(1+0.12*(C89-1))*1.25,1) -> 12.3 | F89: 1.5 | G89: Crafted (Smithy line by tier; Masterwork needs max Construction or Great Engineer)
A90: Masterwork Lattice Aegis | B90: Protection | C90: 9 | D90: Masterwork | E90: =ROUND($J$3*(1+0.12*(C90-1))*1.6,1) -> 15.7 | F90: 2.6 | G90: Crafted (Smithy line by tier; Masterwork needs max Construction or Great Engineer)
A91: Relic Lattice Aegis | B91: Protection | C91: 9 | D91: Relic | E91: =ROUND($J$3*(1+0.12*(C91-1))*2.2,1) -> 21.6 | F91: — | G91: Drop only: vaults, archaeology, tribulation forging
A92: Crude Ration Satchel | B92: Utility | C92: 1 | D92: Crude | E92: =ROUND($J$4*(1+0.12*(C92-1))*0.7,1) -> 2.8 | F92: 0.8 | G92: Crafted (Smithy line by tier; Masterwork needs max Construction or Great Engineer)
A93: Standard Ration Satchel | B93: Utility | C93: 1 | D93: Standard | E93: =ROUND($J$4*(1+0.12*(C93-1))*1,1) -> 4 | F93: 1 | G93: Crafted (Smithy line by tier; Masterwork needs max Construction or Great Engineer)
A94: Fine Ration Satchel | B94: Utility | C94: 1 | D94: Fine | E94: =ROUND($J$4*(1+0.12*(C94-1))*1.25,1) -> 5 | F94: 1.5 | G94: Crafted (Smithy line by tier; Masterwork needs max Construction or Great Engineer)
A95: Masterwork Ration Satchel | B95: Utility | C95: 1 | D95: Masterwork | E95: =ROUND($J$4*(1+0.12*(C95-1))*1.6,1) -> 6.4 | F95: 2.6 | G95: Crafted (Smithy line by tier; Masterwork needs max Construction or Great Engineer)
A96: Relic Ration Satchel | B96: Utility | C96: 1 | D96: Relic | E96: =ROUND($J$4*(1+0.12*(C96-1))*2.2,1) -> 8.8 | F96: — | G96: Drop only: vaults, archaeology, tribulation forging
A97: Crude War Banner | B97: Utility | C97: 2 | D97: Crude | E97: =ROUND($J$4*(1+0.12*(C97-1))*0.7,1) -> 3.1 | F97: 0.8 | G97: Crafted (Smithy line by tier; Masterwork needs max Construction or Great Engineer)
A98: Standard War Banner | B98: Utility | C98: 2 | D98: Standard | E98: =ROUND($J$4*(1+0.12*(C98-1))*1,1) -> 4.5 | F98: 1 | G98: Crafted (Smithy line by tier; Masterwork needs max Construction or Great Engineer)
A99: Fine War Banner | B99: Utility | C99: 2 | D99: Fine | E99: =ROUND($J$4*(1+0.12*(C99-1))*1.25,1) -> 5.6 | F99: 1.5 | G99: Crafted (Smithy line by tier; Masterwork needs max Construction or Great Engineer)
A100: Masterwork War Banner | B100: Utility | C100: 2 | D100: Masterwork | E100: =ROUND($J$4*(1+0.12*(C100-1))*1.6,1) -> 7.2 | F100: 2.6 | G100: Crafted (Smithy line by tier; Masterwork needs max Construction or Great Engineer)
...

Sheet Celestial_Sites
A1: Site Type | B1: Layer | C1: Yields / Contents | D1: Conquest / Use
A2: Barren Village (ruined start) | B2: Province | C2: Empty plots; minor salvage | D2: Resettle at 60% discount; instant Era I foothold
A3: Abandoned Hamlet | B3: Province | C3: Salvage; loyalty-free plots | D3: Claim by garrisoning 24h
A4: Ruined City (player-made) | B4: Province | C4: Archaeology strata; relic chance | D4: Excavate or resettle; history entries
A5: Ancient Capital Ruins | B5: Continent | C5: Relic equipment, lost blueprints | D5: Multi-week dig; contested digs possible
A6: Barbarian Camp | B6: Province | C6: Loot; captives (pop) | D6: Clear for loot; court for mercenaries
A7: Lost Tribe Enclave | B7: Continent | C7: Recruitable population | D7: Diplomacy or conquest
A8: Natural Wonder | B8: Continent | C8: Unique yields; happiness aura | D8: Control by province ownership
A9: Spirit Vein Node | B9: Any land | C9: Qi 20/h regional aura | D9: Cultivation buildings 2× on node
A10: Beast Lair (Spirit) | B10: Continent | C10: Beast cores; tame chance | D10: PvE clear; respawns elsewhere
A11: Sea Trench Vent | B11: Ocean | C11: Rare minerals | D11: Era IV+ platforms
A12: Polar Vault | B12: Planet | C12: Era V tech hints; volatiles | D12: Expedition + escort
... A42: Fallen Galaxy Husk | B42: Intergalactic | C42: Mass archaeology; relics | D42: Era VII expedition frontier

Sheet Cultivation
A1: Element | B1: Detail
A2: The Sovereign | B2: The player avatar cultivates. Realm = the 42 grades in Grades_Realms (14 realms × 3 stages). Realm gates unit grades, building grade-ups, and Era VII paths.
A3: Qi / Aether | B3: Cultivation resource. Sources: Spirit Groves, Qi Gathering Stones, Spirit Wells, Star Qi Condensers, Primordial Qi Sea Taps, Spirit Vein nodes, meditation (idle trickle), pills. Era VII Aether is refined celestial Qi.
A4: Breakthroughs | B4: Spend Qi (Grades_Realms col E) + pass the Tribulation. Tribulations are live events — several are visible/crashable by rivals, making breakthroughs political moments.
A5: Tri-Cultivation | B5: Three tracks: Body (unit HP/def auras), Mind (research/Data auras), Soul (agent/culture auras). Points per realm; respec via Severance only.
A6: Techniques | B6: Skill scrolls from exploration, archaeology, sect libraries. Slots grow with realm. Examples: Cloud Stride (army speed), Iron Skin Sutra (siege defense), Heaven Sundering Slash (first-strike), Merchant God Ledger (trade margin).
A7: Pills & Spirit Herbs | B7: New chain: Spirit Herbs (raw) → Pills (refined) at Alchemy line (T1–T9). Pills: Qi recovery, temporary stat buffs (bounded), tribulation aids, healing. Pill toxicity: stacking penalty prevents chugging.
A8: Sects | B8: Formalized mentorship inside alliances: Sect Halls host master–disciple contracts; masters earn Prestige/traditions from disciple milestones; disciples get aura boosts. Sects can hold inter-sect tournaments (scheduled PvP with cosmetics/Prestige stakes).
A9: Spirit Beasts | B9: Tamable from lairs; act as unit-attached companions (equipment-like slot) or cavalry archetype mounts; beast cores fuel reactors and high-tier crafting.
A10: Dao Comprehension | B10: Passive insight track fed by proficiency milestones; at realm peaks, choose a Dao (Sword, Shield, Wealth, Stars, Silence…) granting one signature active ability on a long cooldown.
A11: Karma | B11: Reputation system hooks: karmic weight modifies tribulation difficulty and Saint-realm gating. Betrayal is allowed — and cultivating past it is expensive.
A12: Balance caps | B12: All cultivation combat bonuses fold into the joint non-doctrine cap (+40% total, GDD §17.1). Realms primarily gate CONTENT (grades, paths, tiers), not raw stats.
A13: Death & Samsara | B13: If a dynasty falls, Samsara Wheel (Era VII) or standard Succession rebirths the heir with partial realm retention (−6 grades, floor G1), keeping veterans strong-but-not-apex on refound.

Sheet Chrono_Shards
A1: DENOMINATIONS (Chrono Shards compress remaining build/train/research time)
A2: Shard | B2: Hours granted | C2: Typical source | D2: Notes
A3: Moment | B3: 1 | C3: Daily quests | D3: Common; clears trivial queues
A4: Watch | B4: 8 | C4: Event tiers, NPC raids | D4: The workhorse denomination
A5: Day | B5: 24 | C5: Weekly event completion
A6: Fortnight | B6: 336 | C6: Epoch placement, tribulation clear | D6: Mid-game meaningful
A7: Season | B7: 2190 | C7: Epoch top placements, first-discoveries | D7: Rare; 3 months
A8: Age | B8: 8766 | C8: Megaproject firsts, Silent Nexus raid clears | D8: 1 year; legendary drop
A10: GUARDRAIL 1 — ABSORPTION CEILING (the core balance lever)
A11: Construction rank | B11: Era | C11: Max compression | D11: Meaning
A12: 0 | B12: 1 | C12: =ROUND($B$21+$B$22*A12+$B$23*B12,2) -> 2.5 | D12: New player, first week
A13: 3 | B13: 2 | C13: =ROUND($B$21+$B$22*A13+$B$23*B13,2) -> 3.9 | D13: Established villager
A14: 5 | B14: 3 | C14: =ROUND($B$21+$B$22*A14+$B$23*B14,2) -> 5 | D14: Competent kingdom
A15: 7 | B15: 4 | C15: =ROUND($B$21+$B$22*A15+$B$23*B15,2) -> 6.1 | D15: Industrial power
A16: 10 | B16: 5 | C16: =ROUND($B$21+$B$22*A16+$B$23*B16,2) -> 7.5 | D16: Maxed stellar builder
A17: 10 | B17: 6 | C17: =ROUND($B$21+$B$22*A17+$B$23*B17,2) -> 8 | D17: Maxed galactic builder
A18: 10 | B18: 7 | C18: =ROUND($B$21+$B$22*A18+$B$23*B18,2) -> 8.5 | D18: Maxed transcendent builder — the hard ceiling
A21: Base ceiling | B21: 2
A22: Per Construction rank | B22: 0.3
A23: Per era | B23: 0.5
A25: Rule | D25: A player may never compress elapsed time by more than this multiple, regardless of shards held or purchased. Money buys you UP TO your earned ceiling, never past it. Excess shards simply cannot be spent that day.
A27: GUARDRAIL 2 — PROHIBITED TARGETS (shards never apply, earned or bought)
A28: ✗ | D28: Any queue in a settlement with hostile movement inbound, or within 4h of impact
A29: ✗ | D29: Troop training during a declared war in which you are a belligerent (defensive garrison units exempt)
A30: ✗ | D30: Era Ascension Projects — these stay on real time and stay politically dramatic
A31: ✗ | D31: Epoch victory projects (Ascendancy Spire, Great Work) and all megastructures
A32: ✗ | D32: Cultivation breakthroughs and tribulations — the Sovereign's path cannot be bought
A33: ✗ | D33: Wall, shield, and fortification repair while under siege
A34: ✗ | D34: Any action against a player two or more eras below you (Escalation rules, GDD §17.4)
A36: GUARDRAIL 3 — TEMPORAL DEBT (diegetic karmic cost)
A37: Shard-hours spent (rolling 30d) | B37: Temporal Debt | C37: Tribulation difficulty | D37: Effect
A38: 0 | B38: 0 | C38: ×1.00 | D38: Clean cultivator; heaven is indifferent
A39: 500 | B39: 1 | C39: ×1.15 | D39: Qi regeneration −5%
A40: 2000 | B40: 2 | C40: ×1.35 | D40: Qi regeneration −12%; tribulation adds a wave
A41: 8000 | B41: 3 | C41: ×1.70 | D41: Qi −20%; breakthrough failure chance appears
A42: 25000 | B42: 4 | C42: ×2.20 | D42: Qi −30%; failed breakthroughs cost a grade
A43: 75000 | B43: 5 | C43: ×3.00 | D43: Heaven's Scrutiny: tribulations become public events rivals can join against you
D44: Debt decays 1 tier per 30 days of abstention. Rationale: stealing time from the heavens is the oldest sin in the genre. A player may buy pace; they cannot buy the realm ladder, and buying pace makes the ladder harder.
A46: GUARDRAIL 4 — DISCLOSURE & THROTTLE
A47: • | D47: Shard expenditure is public on the player profile as a 30-day rolling total. The world can see who bought their skyline.
A48: • | D48: Monthly purchase throttle per account, hard-capped. Beyond it, no further shards may be bought at any price.
A49: • | D49: Purchased and earned shards are the same currency and obey the same ceiling and prohibitions — no premium tier of time.
A50: • | D50: Alliances may query member shard spend; many will set their own internal norms. The design supports that, it does not enforce it.
A52: EPOCH CARRYOVER (partial decay)
A53: Prestige tier | B53: Carry cap (shard-hrs) | C53: Decay on excess | D53: Notes
A54: I — Unranked | B54: 720 | C54: 60% | D54: 30 days banked
A55: II — Noted | B55: 1440 | C55: 55%
A56: III — Renowned | B56: 2880 | C56: 50%
A57: IV — Illustrious | B57: 5760 | C57: 45%
A58: V — Legendary | B58: 11520 | C58: 40% | D58: 480 days banked; a true war chest
D59: At epoch close: keep everything up to the cap, lose the stated share of the excess. Hoarding toward a level-1200 project across epochs is viable and intended; hoarding indefinitely is not.
A61: PACKAGES (what money actually buys)
A62: Package | B62: Shard-hours | C62: Also includes | D62: Notes
A63: Wanderer | B63: 48 | C63: 1 cosmetic banner | D63: Entry tier
A64: Artisan | B64: 240 | C64: Settlement skin | D64: Most-purchased tier target
A65: Chronomancer | B65: 1200 | C65: Unit livery set
A66: Dynasty | B66: 4800 | C66: Heraldry editor + monument style | D66: Near the monthly throttle
A67: Epoch Pass | B67: 600 | C67: Full cosmetic track | D67: Also has a free track
D68: Pricing deliberately omitted — set against live ARPU and the monthly throttle, not fixed here. Everything except shards remains cosmetic.

Sheet Reachable_Levels
A1: Level reached on a single structure, by years of continuous focus × sustained compression
A2: Read: a player who put every hour of N years into ONE building at a sustained compression multiple reaches this level. Real players spread across many structures, so treat these as ceilings, not expectations.
A4: Years played | B4: 1.0× (no shards) | C4: 1.5× (casual earned) | D4: 2.0× (active earned) | E4: 3.0× (heavy earned) | F4: 5.0× (mid ceiling) | G4: 8.5× (hard ceiling)
A5: 0.25 | B5: =MATCH($A5*8766*1, Building_Levels!$G$2:$G$1339, 1)-1 -> 243 | C5: =MATCH($A5*8766*1.5, Building_Levels!$G$2:$G$1339, 1)-1 -> 273 | D5: =MATCH($A5*8766*2, Building_Levels!$G$2:$G$1339, 1)-1 -> 296 | E5: =MATCH($A5*8766*3, Building_Levels!$G$2:$G$1339, 1)-1 -> 331 | F5: =MATCH($A5*8766*5, Building_Levels!$G$2:$G$1339, 1)-1 -> 380 | G5: =MATCH($A5*8766*8.5, Building_Levels!$G$2:$G$1339, 1)-1 -> 436
A6: 0.5 | B6: =MATCH($A6*8766*1, Building_Levels!$G$2:$G$1339, 1)-1 -> 296 | C6: =MATCH($A6*8766*1.5, Building_Levels!$G$2:$G$1339, 1)-1 -> 331 | D6: =MATCH($A6*8766*2, Building_Levels!$G$2:$G$1339, 1)-1 -> 358 | E6: =MATCH($A6*8766*3, Building_Levels!$G$2:$G$1339, 1)-1 -> 399 | F6: =MATCH($A6*8766*5, Building_Levels!$G$2:$G$1339, 1)-1 -> 455 | G6: =MATCH($A6*8766*8.5, Building_Levels!$G$2:$G$1339, 1)-1 -> 518
A7: 1 | B7: =MATCH($A7*8766*1, Building_Levels!$G$2:$G$1339, 1)-1 -> 358 | C7: =MATCH($A7*8766*1.5, Building_Levels!$G$2:$G$1339, 1)-1 -> 399 | D7: =MATCH($A7*8766*2, Building_Levels!$G$2:$G$1339, 1)-1 -> 430 | E7: =MATCH($A7*8766*3, Building_Levels!$G$2:$G$1339, 1)-1 -> 476 | F7: =MATCH($A7*8766*5, Building_Levels!$G$2:$G$1339, 1)-1 -> 539 | G7: =MATCH($A7*8766*8.5, Building_Levels!$G$2:$G$1339, 1)-1 -> 610
A8: 2 | B8: =MATCH($A8*8766*1, Building_Levels!$G$2:$G$1339, 1)-1 -> 430 | C8: =MATCH($A8*8766*1.5, Building_Levels!$G$2:$G$1339, 1)-1 -> 476 | D8: =MATCH($A8*8766*2, Building_Levels!$G$2:$G$1339, 1)-1 -> 511 | E8: =MATCH($A8*8766*3, Building_Levels!$G$2:$G$1339, 1)-1 -> 563 | F8: =MATCH($A8*8766*5, Building_Levels!$G$2:$G$1339, 1)-1 -> 633 | G8: =MATCH($A8*8766*8.5, Building_Levels!$G$2:$G$1339, 1)-1 -> 712
A9: 3 | B9: =MATCH($A9*8766*1, Building_Levels!$G$2:$G$1339, 1)-1 -> 476 | C9: =MATCH($A9*8766*1.5, Building_Levels!$G$2:$G$1339, 1)-1 -> 526 | D9: =MATCH($A9*8766*2, Building_Levels!$G$2:$G$1339, 1)-1 -> 563 | E9: =MATCH($A9*8766*3, Building_Levels!$G$2:$G$1339, 1)-1 -> 618 | F9: =MATCH($A9*8766*5, Building_Levels!$G$2:$G$1339, 1)-1 -> 693 | G9: =MATCH($A9*8766*8.5, Building_Levels!$G$2:$G$1339, 1)-1 -> 776
A10: 5 | B10: =MATCH($A10*8766*1, Building_Levels!$G$2:$G$1339, 1)-1 -> 539 | C10: =MATCH($A10*8766*1.5, Building_Levels!$G$2:$G$1339, 1)-1 -> 593 | D10: =MATCH($A10*8766*2, Building_Levels!$G$2:$G$1339, 1)-1 -> 633 | E10: =MATCH($A10*8766*3, Building_Levels!$G$2:$G$1339, 1)-1 -> 693 | F10: =MATCH($A10*8766*5, Building_Levels!$G$2:$G$1339, 1)-1 -> 773 | G10: =MATCH($A10*8766*8.5, Building_Levels!$G$2:$G$1339, 1)-1 -> 862
A11: 7 | B11: =MATCH($A11*8766*1, Building_Levels!$G$2:$G$1339, 1)-1 -> 584 | C11: =MATCH($A11*8766*1.5, Building_Levels!$G$2:$G$1339, 1)-1 -> 640 | D11: =MATCH($A11*8766*2, Building_Levels!$G$2:$G$1339, 1)-1 -> 683 | E11: =MATCH($A11*8766*3, Building_Levels!$G$2:$G$1339, 1)-1 -> 745 | F11: =MATCH($A11*8766*5, Building_Levels!$G$2:$G$1339, 1)-1 -> 829 | G11: =MATCH($A11*8766*8.5, Building_Levels!$G$2:$G$1339, 1)-1 -> 920
A12: 10 | B12: =MATCH($A12*8766*1, Building_Levels!$G$2:$G$1339, 1)-1 -> 633 | C12: =MATCH($A12*8766*1.5, Building_Levels!$G$2:$G$1339, 1)-1 -> 693 | D12: =MATCH($A12*8766*2, Building_Levels!$G$2:$G$1339, 1)-1 -> 738 | E12: =MATCH($A12*8766*3, Building_Levels!$G$2:$G$1339, 1)-1 -> 803 | F12: =MATCH($A12*8766*5, Building_Levels!$G$2:$G$1339, 1)-1 -> 890 | G12: =MATCH($A12*8766*8.5, Building_Levels!$G$2:$G$1339, 1)-1 -> 985
A13: 15 | B13: =MATCH($A13*8766*1, Building_Levels!$G$2:$G$1339, 1)-1 -> 693 | C13: =MATCH($A13*8766*1.5, Building_Levels!$G$2:$G$1339, 1)-1 -> 756 | D13: =MATCH($A13*8766*2, Building_Levels!$G$2:$G$1339, 1)-1 -> 803 | E13: =MATCH($A13*8766*3, Building_Levels!$G$2:$G$1339, 1)-1 -> 871 | F13: =MATCH($A13*8766*5, Building_Levels!$G$2:$G$1339, 1)-1 -> 962 | G13: =MATCH($A13*8766*8.5, Building_Levels!$G$2:$G$1339, 1)-1 -> 1061
A14: 20 | B14: =MATCH($A14*8766*1, Building_Levels!$G$2:$G$1339, 1)-1 -> 738 | C14: =MATCH($A14*8766*1.5, Building_Levels!$G$2:$G$1339, 1)-1 -> 803 | D14: =MATCH($A14*8766*2, Building_Levels!$G$2:$G$1339, 1)-1 -> 851 | E14: =MATCH($A14*8766*3, Building_Levels!$G$2:$G$1339, 1)-1 -> 922 | F14: =MATCH($A14*8766*5, Building_Levels!$G$2:$G$1339, 1)-1 -> 1015 | G14: =MATCH($A14*8766*8.5, Building_Levels!$G$2:$G$1339, 1)-1 -> 1117
A15: 30 | B15: =MATCH($A15*8766*1, Building_Levels!$G$2:$G$1339, 1)-1 -> 803 | C15: =MATCH($A15*8766*1.5, Building_Levels!$G$2:$G$1339, 1)-1 -> 871 | D15: =MATCH($A15*8766*2, Building_Levels!$G$2:$G$1339, 1)-1 -> 922 | E15: =MATCH($A15*8766*3, Building_Levels!$G$2:$G$1339, 1)-1 -> 995 | F15: =MATCH($A15*8766*5, Building_Levels!$G$2:$G$1339, 1)-1 -> 1092 | G15: =MATCH($A15*8766*8.5, Building_Levels!$G$2:$G$1339, 1)-1 -> 1197
A16: 50 | B16: =MATCH($A16*8766*1, Building_Levels!$G$2:$G$1339, 1)-1 -> 890 | C16: =MATCH($A16*8766*1.5, Building_Levels!$G$2:$G$1339, 1)-1 -> 962 | D16: =MATCH($A16*8766*2, Building_Levels!$G$2:$G$1339, 1)-1 -> 1015 | E16: =MATCH($A16*8766*3, Building_Levels!$G$2:$G$1339, 1)-1 -> 1092 | F16: =MATCH($A16*8766*5, Building_Levels!$G$2:$G$1339, 1)-1 -> 1193 | G16: =MATCH($A16*8766*8.5, Building_Levels!$G$2:$G$1339, 1)-1 -> 1302
A18: Design read-out: even at the hard 8.5× ceiling, a decade of total focus does not approach level 1337. The ladder stays mythic; shards decide how far up the practical range a dynasty climbs, not whether the top is reachable.

Sheet Heavens_Envy
A1: HEAVEN'S ENVY — the mark of stolen time (public, stacking)
A2: Scope | B2: Debuff | C2: Duration | D2: Ranking basis
A3: Universe — top 10 daily buyers | B3: -10% defensive strength | C3: 24 hours | D3: Shard-hours PURCHASED in the 24h measurement window, universe-wide
A4: Stellar Quadrant — top 10 | B4: -10% defensive strength | C4: 24 hours | D4: Same window, ranked within the buyer's home quadrant
A5: Alliance — top 10 | B5: -10% defensive strength | C5: 24 hours | D5: Same window, ranked within the buyer's alliance
A6: MAXIMUM STACK | B6: -30% defensive strength | C6: 24 hours | D6: A player topping all three lists simultaneously
A8: WHAT "DEFENSIVE STRENGTH" MEANS
A9: • | D9: Applies to the defense pool of every unit the player owns, at every map layer, garrisoned or in the field.
A10: • | D10: Applies to fortification multipliers (walls, castles, star forts, bunkers, defense grids, citadels).
A11: • | D11: Does NOT apply to attack values. A marked player is a glass cannon, not a cripple — see design note below.
A12: • | D12: Does NOT stack beyond -30%, and is applied after all other modifiers as a final multiplier.
A13: • | D13: Cannot be cleansed, cancelled, offset by shards, or dodged by vacation mode (vacation entry is blocked while marked).
A15: PUBLICITY — the mark is the point
A16: • | D16: Marked players carry a visible sigil on their profile, on every settlement and fleet they own, and on the map overlay.
A17: • | D17: The three leaderboards are public, live, and queryable: anyone can see who is on them and at what rank.
A18: • | D18: The mark resolves at a fixed, publicly posted daily server tick, so the 24h window is predictable and huntable by design.
A19: • | D19: Attacking a marked player carries NO reputation penalty for the duration of the mark — the design makes hunting them socially free.
A20: • | D20: Historical record: marks are logged permanently to the World Atlas and the player's dynasty hall.
A22: ANTI-GAMING RULES (without these the mechanic is trivially dodged)
A23: Exploit | D23: Countermeasure
A24: Alt-account splitting | D24: Purchases by device/payment/network-linked accounts aggregate to the primary for all three leaderboards. Detection is the same system used for multi-account transfer caps.
A25: Hovering at rank 11 | D25: Intended and acceptable. Sitting just under the cut suppresses spend, which is the mechanic working. Rank 10 and rank 11 spend converge over time.
A26: Quiet-scope trivial marking | D26: Each scope has a minimum spend floor: a player is only marked if their window purchase exceeds the median active player's 30-day EARNED shard income. In a quiet alliance or quadrant, the list may return fewer than 10 names — or none.
A27: Quadrant-hopping to dodge | D27: Home quadrant for ranking purposes is the one holding the plurality of your settlements, evaluated on a 7-day lag. Relocating to dodge takes longer than the mark lasts.
A28: Alliance-hopping to dodge | D28: Alliance for ranking purposes is the one held at the start of the measurement window. Leaving after a purchase does not clear the mark.
A29: Buying during peacetime only | D29: Intended and acceptable — this is the mechanic shaping behavior toward safer spending, and the mark still logs publicly.
A30: Timing purchases just after the tick | D30: Window is rolling-24h-measured but resolved at the fixed tick, so a purchase made 23h before the tick still ranks. No safe hour exists.
A31: Dumping spend before going inactive | D31: Vacation mode and stewardship entry are blocked for the duration of the mark.
A33: WORKED EXAMPLE
D34: A player buys 900 shard-hours on Tuesday. At the 00:00 UTC tick they rank #3 universe-wide, #1 in the Perseus-Rim quadrant, and #2 in their alliance.
D35: They are marked on all three lists: -30% defensive strength for 24 hours, sigil visible universe-wide.
D36: Their Ascendant Void Cruiser fleet defends at 70% of its normal defense pool. Their planetary shield and defense grid multipliers are likewise cut by 30%.
D37: Their attack values are untouched. They can still strike at full force — and rivals know exactly where to strike back.
D38: Three rival alliances see the mark on the public board. Attacking them costs no reputation for 24 hours. Two of them launch.
D39: Design outcome: the purchase bought real development pace, and it bought a day of danger that the entire universe could see coming.
A41: DESIGN NOTES & OPEN QUESTIONS
D42: Defense-only is deliberate: it makes heavy spenders aggressive glass cannons rather than punishing them flatly. Note the loophole honestly — a player who buys purely to fuel offensives is not directly penalized, and in a permanent-conquest world offense is where purchased advantage bites hardest. If beta telemetry shows buy-to-blitz behavior, the cleanest fix is adding a smaller offensive component (-5% per scope) rather than raising the defensive number.
D43: The rank-10 cliff is a hard discontinuity (#10 takes -10%, #11 takes nothing). This is dramatic and legible, and the spend floor prevents the worst unfairness. A smoothed curve is the alternative if the cliff proves frustrating.
D44: Interaction with Temporal Debt: these are separate systems. Temporal Debt tracks lifetime spending and taxes cultivation; Heaven's Envy tracks daily spending and taxes defense. A player can carry both simultaneously and they do not offset.
D45: The third scope is implemented as ALLIANCE. The brief listed "top 10 daily buyers" twice; swap to era-band, epoch-cumulative, or federation by changing this sheet and the ranking service.
D46: All three -10% values and the three spend floors are server-tunable constants.

Sheet Building_Framework
A1: System | B1: How it works | C1: Why it exists (design intent)
A2: Plots & size class | B2: Every settlement has a finite plot count. Buildings occupy 1–4 plots by size class: Minor (1), Standard (2), Major (3), Monumental (4). Plot count starts at 24 and grows +2 per HQ grade, reaching ~110 at HQ grade 42 — never enough for all 69 era buildings plus their predecessors. | C2: Forced specialization. A settlement is a statement of intent, not a checklist. Scarcity of plots is the single biggest driver of empire-wide planning.
A3: Level gating | B3: A building may never exceed its settlement HQ level. HQ upgrades are therefore the universal bottleneck, and HQ itself is Monumental and expensive. Grade breakthroughs additionally require the matching research discipline grade (Grades_Realms). | C3: Gives a clean, legible progression spine and makes the HQ the highest-value sabotage and siege target in any settlement.
A4: Staffing & population | B4: Buildings draw Workers from settlement Population. Output scales linearly with staffing percentage: a Mine at 50% staffing produces 50%. Higher levels need more workers, so raising a building without growing population starves your other buildings. | C4: Makes Population a genuine strategic resource, gives plague, siege starvation, and conquest real economic teeth, and creates the classic "wide vs. tall" tension inside a single settlement.
A5: Upkeep & decay | B5: From Era II buildings cost Coin upkeep; from Era IV they additionally require Electricity from the grid. Unpaid upkeep causes Brownout: output halves, and after 72h the building loses one level per day until solvent. | C5: Prevents infinite accumulation, punishes overbuilding, and makes power-grid sabotage a devastating Era IV+ attack vector.
A6: Adjacency & terrain | B6: Buildings gain or lose output from neighbours and tiles. Positive: Sawmill beside Lumber Camp (+15%), Fusion Plant beside Shipyard Ring (+20%). Negative: Tannery beside Housing (−10% happiness), Powder Magazine beside anything (blast radius on destruction). Yield tiles (fertile, deep-vein, He-3-rich) multiply extraction 1.5–2.5×. | C6: Turns settlement construction into a spatial puzzle rather than a menu, and makes map position matter permanently — the good ground is worth fighting over forever.
A7: Build queues | B7: HQ grade grants queue slots (1 at grade 1, +1 per 4 grades). Factory and its successors grant separate parallel production lines for units only. Queued items may be reordered freely; cancelling refunds 80%. | C7: Queue depth is what makes offline play viable, and the 80% refund keeps misclicks from being punishing.
A8: Damage, repair & razing | B8: Siege reduces buildings by damage levels rather than destroying them. Repair costs 30% of the original level cost and takes 20% of the original time. An attacker may spend extra siege actions to raze a building entirely, which is slow, wasteful, and reputation-costly. | C8: Keeps war destructive without being erasive. In a permanent world, a burned city that can be rebuilt is a better story than a deleted one.
A9: Capture | B9: Captured settlements retain their buildings at level minus 3 grades (floor: grade 1). Cultivation and Special-category buildings are exceptions — they fully reset, because they are bound to their builder's dao. | C9: Conquest yields real infrastructure (the reason to take cities intact) while denying the attacker a free endgame economy.
A10: Synergy chains | B10: Processing buildings require input resources physically present in the settlement or delivered by logistics. A Steelworks with no Coal produces nothing regardless of level. Chains run raw → refined → component (workbook Section 6). | C10: Creates supply-line warfare. Cutting an enemy's rubber shuts down their tank assembly two steps downstream, which is far more interesting than destroying tanks.
A11: Heritage (no obsolescence) | B11: Buildings from earlier eras never stop functioning. Once a settlement advances an era, older buildings gain Heritage status: they keep their full output and additionally generate Culture equal to 2% of their level. | C11: Enforces Pillar 1 (every layer stays alive) at the building level, and gives ancient, deeply-levelled villages genuine value in a galactic empire.
A12: Specialization caps | B12: A settlement may hold at most 3 buildings above grade 30, and at most 8 above grade 20. Exceeding the cap is impossible, not merely penalised. | C12: Hard-stops the "one perfect megacity" pattern. Empires must distribute their crown jewels, which distributes their vulnerabilities, which creates targets and therefore wars.
A13: Visibility & intel | B13: Building levels are hidden from enemies until scouted. Monumental buildings and any building above grade 25 are visible on the map at range — a level-800 Citadel is a landmark, not a secret. | C13: Rewards scouting while ensuring the truly enormous structures function as public landmarks that shape strategy for everyone around them.

Sheet Category_Chassis
A1: Category | B1: Core output formula | C1: Distinctive mechanics | D1: Scales with level by | E1: Primary vulnerability
A2: HQ/Governance | B2: — | C2: Gates every other building's level. Grants queue slots, command radius, plot count, policy/doctrine slots. Its destruction caps the whole settlement. | D2: +2 plots, +1 queue per 4 grades, +radius | E2: Siege priority target; loss cascades to every building
A3: Extraction | B3: base × LevelCurve × tile richness × staffing% | C3: Produces raw resources into a local stockpile that raiders can plunder. Tile richness is fixed by map position. Depletion does not exist — but hazard tiles impose attrition on workers. | D3: Output (L+1)^1.12 | E3: Raiding the stockpile; worker loss; tile capture
A4: Processing | B4: min(input supply, throughput) × conversion rate | C4: Converts inputs to outputs. Throughput caps how much it can handle per tick; conversion rate improves with level. Idle without inputs regardless of level. | D4: Throughput and conversion both rise | E4: Supply-line interdiction — starve the inputs
A5: Military | B5: — | C5: Grants unit queue slots, gates unit archetypes and grade tiers, reduces training time by a bounded percentage. Parallel lines from Factory tier onward. | D5: +queue slots, −train time (capped −40%) | E5: Raided mid-production: partial units are destroyed
A6: Defense | B6: defense multiplier + flat garrison HP | C6: Multiplies defending units' defense pool, adds wall HP that must be breached, projects zone of control onto adjacent roads/lanes. Must be reduced by siege before plunder. | D6: Multiplier and HP both rise | E6: Siege engines; sappers; bombardment; Heaven's Envy debuff
A7: Knowledge | B7: research points or intel radius | C7: Generates research, extends intel range, hosts agent operations, recruits Great People. Intel buildings reveal incoming attacks earlier. | D7: Rate and radius rise | E7: Sabotage; counter-intel raids; tech theft targets
A8: Trade | B8: Coin/hour + route slots + market depth | C8: Generates Coin, grants standing trade route slots, deepens local market order books, collects tolls on routes crossing your zone of control. | D8: +routes, +Coin, +depth | E8: Blockade; piracy on the routes it spawns
A9: Culture | B9: Culture/hour + happiness | C9: Raises happiness (productivity multiplier, revolt suppression), generates Culture that exerts border pressure on adjacent low-culture plots, and hosts festivals and ideology projection. | D9: Culture and happiness rise | E9: Slow to rebuild; razing it is a favourite spite target
A10: Logistics | B10: storage cap / movement / supply range | C10: Raises stockpile caps, extends army supply range, speeds movement along owned infrastructure, enables hauling volume. | D10: Caps and ranges rise | E10: Chokepoint capture; convoy raiding
A11: Special | B11: unique | C11: One-off gated effects: Ascension Projects, colony founding, terraforming, megastructures, wonder-class effects. Usually Monumental, usually announced publicly when begun. | D11: Varies per building | E11: Publicly announced; attractive sabotage target
A12: Cultivation | B12: Qi/hour + realm & technique unlocks | C12: Generates Qi, hosts breakthroughs and tribulations, unlocks techniques, refines pills, tames spirit beasts. Fully resets on capture — cultivation infrastructure is bound to its builder. | D12: Qi rate and slot count rise | E12: Cannot be captured usefully; tribulation-crashing raids

Sheet Visual_Tiers
A1: VISUAL TIER SYSTEM — art is authored per tier, not per level
A2: 483 buildings × 1,338 levels = 646,000 states, which cannot be authored. Instead each building has 12 authored visual tiers mapped to level bands, combined with shared modular overlay layers (below). 12 tiers × 6 overlay axes yields thousands of distinct on-screen appearances per building from 12 base renders.
A4: Tier | B4: Level band | C4: Grade band | D4: Universal transformation | E4: Silhouette change | F4: Player read at a glance
A5: 0 | B5: 0 | C5: 1 | D5: Cleared site: stakes, string lines, a spoil heap, one labourer. No structure yet. | E5: Flat ground + markers | F5: "Something is coming here"
A6: 1 | B6: 1–24 | C6: 1 | D6: Improvised and temporary. Raw local material, no foundation, visible lashings and patches. | E6: Small, low, irregular | F6: "Someone just started"
A7: 2 | B7: 25–96 | C7: 1–3 | D7: Permanent footprint. Proper foundation, squared timber or fired brick, a functioning door. | E7: Doubles in height; regular geometry | F7: "This is real now"
A8: 3 | B8: 97–224 | C8: 4–7 | D8: Purposeful craft. Dedicated work yards, storage annexes, a sign of the trade. First decoration. | E8: Spreads horizontally; annexes appear | F8: "They know what they are doing"
A9: 4 | B9: 225–384 | C9: 8–12 | D9: Institutional. Stone or steel core, an entrance worth photographing, staff visible at work. | E9: Vertical emphasis begins | F9: "This is a serious institution"
A10: 5 | B10: 385–544 | C10: 13–17 | D10: Prestige architecture. Ornament, heraldry, a courtyard or forecourt, formal approach. | E10: Complex massing; a tower or spire | F10: "Wealth lives here"
A11: 6 | B11: 545–704 | C11: 18–21 | D11: Era retrofit. Older fabric visibly upgraded with current-era technology grafted on. | E11: Mixed-period silhouette | F11: "Old bones, new power"
A12: 7 | B12: 705–864 | C12: 22–27 | D12: Monumental. Dominates its plot, casts shadow on neighbours, visible from outside the settlement. | E12: Landmark scale | F12: "You can see it from the next province"
A13: 8 | B13: 865–1024 | C13: 28–32 | D13: Industrial/void scale. Continuous operation, exhaust plumes or energy bleed, support structures. | E13: Sprawling complex; auxiliaries | F13: "An economy in one building"
A14: 9 | B14: 1025–1152 | C14: 33–36 | D14: Transcendent. Structure begins to exceed plausible engineering; ambient Qi/energy visibly distorts around it. | E14: Impossible cantilevers; floating elements | F14: "This should not stand up"
A15: 10 | B15: 1153–1280 | C15: 37–41 | D15: Mythic. Architecture and phenomenon merge. Weather, light, and time behave differently nearby. | E15: Partly non-solid; auroral | F15: "The world bends here"
A16: 11 | B16: 1281–1337 | C16: 42 | D16: Legendary. A named wonder. Rendered as a unique hero asset, not a tier variant. Visible from orbit. | E16: Bespoke per building | F16: "There are only a handful of these in existence"
A19: Production note: tiers 0–8 are kit-bashable from a shared modular library per era and category. Tiers 9–11 need bespoke attention. Estimated authored assets: 483 × 9 shared-kit tiers + 483 × 3 bespoke ≈ 5,800 renders, versus 646,000 if authored per level.

Sheet Visual_Overlays
A1: Overlay axis | B1: States | C1: How it renders | D1: Shared or per-building
A2: Era retrofit | B2: 7 (Era I–VII) | C2: Material and technology pass over the same silhouette: thatch → tile → slate → corrugated steel → composite → alloy → lattice. A Farm in a galactic empire is still a Farm, but it has drone seeders and a fusion tap. | D2: Shared per category
A3: Culture / Ideology | B3: 9 (3 axes × 3 positions) | C3: Authority reads as symmetry, columns, banners. Liberty reads as open frontage, mixed use, civic art. Faith reads as shrines and iconography. Reason reads as glass, instrumentation, clean geometry. | D3: Shared decal + trim library
A4: Cultivation aura | B4: 7 (realm bands) | C4: Ambient VFX intensity around cultivation and high-grade buildings: none → faint motes → flowing currents → standing arcs → local weather → gravity distortion → visible time-dilation shimmer. | D4: Shared VFX library
A5: Damage state | B5: 4 | C5: Pristine / scarred (scorch, patched walls) / breached (structural loss, exposed interior) / ruined (collapsed, smoking, salvageable). Damage states persist visibly until repaired. | D5: Shared per size class
A6: Activity state | B6: 3 | C6: Idle (dark, still, no staff) / working (animated, lit, staff and carts) / overdriven (shard-accelerated: temporal shimmer, blurred workers, audible hum). Overdriven is deliberately conspicuous. | D6: Shared per category
A7: Biome & season | B7: 6 | C7: Desert, temperate, tundra, tropical, volcanic, void. Affects roofing, foundations, vegetation, snow accumulation, and light temperature. | D7: Shared environment pass
A8: Heraldry | B8: Player-defined | C8: Owner banners, unit liveries, and dynasty colours applied to defined decal slots. Changes hands visibly on conquest. | D8: Per-player, shared slots
A10: Combinatorics: 12 tiers × 7 eras × 9 culture states × 7 auras × 4 damage × 3 activity × 6 biomes = ~381,000 renderable appearances per building, from roughly 12 authored base assets plus shared libraries. This is how the level-1337 ladder gets visual expression without an impossible art budget.

Sheet Specs_EraI
A1: # | B1: Building | C1: Category | D1: Purpose | E1: Value added | F1: Distinctive mechanic | G1: Key synergies | H1: Visual DNA (art brief)
A2: 1 | B2: Chieftain's Hall | C2: HQ/Governance | D2: Seat of the settlement; the level cap for everything else. | E2: Unlocks plots, queue slots, and command radius; the single most consequential upgrade in Era I. | F2: Hard-caps every other building's level. If reduced by siege, every building above the new cap is suppressed until repaired. | G2: Gates all; Rally Point extends its command radius. | H2: Longhouse on a raised mound. Carved ancestor posts flanking the door, smoke hole, a single banner. Signature: the antler-crowned ridge beam.
A3: 2 | B3: Farm | C3: Extraction | D3: Primary Grain production and the population engine. | E3: Feeds population growth and army upkeep; without it nothing else scales. | F3: Yields ×2 on fertile tiles. Output drops 40% in winter zones unless a Granary buffers it. | G3: Granary (buffers), Windmill later (+conversion). Adjacent Orchard +10%. | H3: Terraced fields around a threshing floor. Signature: the ox-turned grain post and stacked sheaves.
A4: 3 | B4: Fishery | C4: Extraction | D4: Coastal Food alternative independent of arable land. | E4: Lets coastal settlements skip farmland entirely, freeing plots for military or trade. | F4: Immune to the winter Farm penalty but vulnerable to naval blockade from Era III. | G4: Smokehouse (preserves catch), River Dock. | H4: Stilted platform over water, drying nets on frames, beached coracles. Signature: the great net-winch.
A5: 4 | B5: Lumber Camp | C5: Extraction | D5: Timber extraction. | E5: Feeds every construction chain in the game's first two eras. | F5: +25% adjacent to forest tiles; clear-felling is cosmetic only — forests do not deplete. | G5: Sawmill (+15% adjacency), Carpenter Guild later. | H5: Felling yard with stacked trunks, a skid ramp, axes in stumps. Signature: the log flume down the slope.
A6: 5 | B6: Mine | C6: Extraction | D6: Ore extraction. | E6: The bottleneck resource for weapons, tools, and all metal chains. | F6: Deep-vein tiles double output. Workers suffer 2%/day attrition without a Herbalist Hut in the settlement. | G6: Smelter, Bloomery, Herbalist Hut (safety). | H6: Timbered adit into a hillside, spoil heap, ore carts on plank rails. Signature: the headframe winch.
A7: 6 | B7: Hunter's Lodge | C7: Extraction | D7: Hide extraction and scout training support. | E7: Supplies the leather armour chain and grants scouts a small speed bonus. | F7: Grants +5% Scout speed empire-wide at grade 6+. | G7: Tannery, Scout Post, Kennels. | H7: Low cabin hung with pelts and antlers, drying racks. Signature: the trophy gable.
A8: 7 | B8: Clay Pit | C8: Extraction | D8: Clay extraction. | E8: Feeds the Kiln chain that unlocks durable Era II construction. | F8: Output +30% on riverbank tiles; halts entirely during flood events. | G8: Kiln, Pottery Works. | H8: Terraced excavation with water-filled cuts and barrow ramps. Signature: the stacked drying-brick pyramid.
A9: 8 | B9: Herb Garden | C9: Extraction | D9: Spirit Herb cultivation — the cultivation chain's first link. | E9: Opens the entire pill and alchemy economy that runs to Era VII. | F9: Yield ×3 on Spirit Vein tiles. Herb quality (not quantity) scales with the Sovereign's realm. | G9: Alchemy Cauldron Hut, Herbalist Hut, Spirit Grove. | H9: Walled garden of raised beds by species, a moon gate, drying lines. Signature: the one bed that glows faintly at night.
A10: 9 | B10: Apiary | C10: Extraction | D10: Honey: a food source that also raises happiness. | E10: Cheap dual-purpose output; strong early happiness for its plot cost. | F10: Adjacency +20% to Orchard and Herb Garden; the bonus is reciprocal. | G10: Orchard, Herb Garden, Brewhouse. | H10: Row of woven skeps under a lean-to, smoke pot, flowering verge. Signature: the visible bee-cloud VFX.
A11: 10 | B11: Orchard | C11: Extraction | D11: Fruit — a Food variant with a happiness rider. | E11: Diversifies food so a single blight or raid cannot starve the settlement. | F11: Takes 3 days to reach first yield after construction; thereafter steady. | G11: Apiary (+20%), Brewhouse (cider), Farm. | H11: Ranked fruit trees with ladders and picking baskets. Signature: the seasonal blossom-to-fruit colour shift.
A12: 11 | B12: Vegetable Garden | C12: Extraction | D12: Small-plot Food. | E12: The cheapest food per plot; how new players survive their first week. | F12: Minor size class — occupies only one plot, unlike most extraction. | G12: Farm, Village Square. | H12: Fenced kitchen plot in neat rows with a watering butt. Signature: the scarecrow.
A13: 12 | B13: Pig Pen | C13: Extraction | D13: Food from waste conversion. | E13: Converts food surplus into denser food; efficient but unhappy. | F13: −5% happiness to adjacent Culture buildings. Efficient, and everyone hates living next to it. | G13: Butchery later, Smokehouse. | H13: Mud yard with plank shelters and a slop trough. Signature: the wallow.
... A70: 69 | B70: Rally Point | C70: Military | D70: Attack timing precision and command capacity. | E70: Enables synchronized multi-wave attacks — the core skill of tribal strategy. | F70: Higher grades tighten the launch window, allowing waves to land seconds apart. | G70: Chieftain's Hall, Barracks, Palisade Gatehouse. | H70: Raised muster platform with signal horns and unit standards. Signature: the forest of planted banner poles.

Sheet ArtBrief_Exemplars
A1: Building | B1: Tier | C1: Level band | D1: Appearance at this tier
A2: Chieftain's Hall | B2: 0 | C2: 0 | D2: Staked rectangle on a cleared mound, post holes dug, one ancestor pole already planted upright.
B3: 1 | C3: 1–24 | D3: Single-room hut of split logs and turf roof, hide door flap, smoke escaping through a gap. One carved post.
B4: 2 | C4: 25–96 | D4: Proper longhouse: squared timber, thatched ridge, a real door with iron hinges, two ancestor posts flanking.
B5: 3 | C5: 97–224 | D5: Hall extended with side aisles and a porch. Carved ridge-beam with antler crown. Banner on a pole outside.
B6: 4 | C6: 225–384 | D6: Stone plinth beneath the timber. Great doors, a paved forecourt, guards posted. Interior hearth visible through open doors.
B7: 5 | C7: 385–544 | D7: Fortified hall-keep: stone ground floor, timber upper, corner turrets, a walled courtyard with a standing stone.
B8: 6 | C8: 545–704 | D8: Era-retrofitted: original timber hall preserved intact inside a shell of newer construction, deliberately visible as heritage.
B9: 7 | C9: 705–864 | D9: Palace complex around the original hall. Towers, curtain wall, ceremonial approach stair. Dominates the settlement skyline.
B10: 8 | C10: 865–1024 | D10: Administrative city-block: the ancient hall now a shrine at the heart of a vast governance complex with landing platforms.
B11: 9 | C11: 1025–1152 | D11: Structure exceeds plausibility: the hall floats in a stabilized field above its own foundations, ancestor poles orbiting slowly.
B12: 10 | C12: 1153–1280 | D12: Architecture and phenomenon merge. Light bends around the ancestor poles; the original hut is visible at the centre, untouched by ten centuries.
B13: 11 | C13: 1281–1337 | D13: Unique hero asset. A named seat of power visible from orbit, rendered bespoke per dynasty, the original longhouse still burning its hearth at the core.
A14: Farm | B14: 0 | C14: 0 | D14: Furrowed strips marked out with stakes, a single plough abandoned mid-row.
B15: 1 | C15: 1–24 | D15: Two ragged fields, a lean-to shelter, hand tools. Crops uneven and sparse.
B16: 2 | C16: 25–96 | D16: Squared terraced fields with drainage, a threshing floor, an ox-turned grain post.
B17: 3 | C17: 97–224 | D17: Field system with hedgerows, a granary annex, stacked sheaves, working oxen.
B18: 4 | C18: 225–384 | D18: Estate farm: stone farmhouse, ranked outbuildings, irrigation channels, dense uniform crop.
B19: 5 | C19: 385–544 | D19: Manorial complex with a dovecote, walled kitchen garden, and a bell tower over the yard.
B20: 6 | C20: 545–704 | D20: Mechanized retrofit: the old stone farmhouse intact, now surrounded by rails, pumps, and powered threshers.
B21: 7 | C21: 705–864 | D21: Industrial agriculture: vast uniform fields to the horizon, silos, conveyor lines, the original farmhouse preserved as an office.
B22: 8 | C22: 865–1024 | D22: Vertical agriculture towers with automated harvesters. Fields now stacked in climate-controlled tiers.
B23: 9 | C23: 1025–1152 | D23: Crops growing under a stabilized artificial season; the air shimmers with controlled weather over impossible yields.
B24: 10 | C24: 1153–1280 | D24: Fields of light rather than soil. Growth cycles visibly accelerate; the original stone farmhouse sits at the centre, tended by nothing visible.
B25: 11 | C25: 1281–1337 | D25: Unique hero asset: a world-feeding agricultural wonder, the ox-post from tier 2 preserved under glass at its heart.
A26: Palisade | B26: 0 | C26: 0 | D26: Trench line scratched in the dirt, stakes stacked ready, the first post being levered upright.
B27: 1 | C27: 1–24 | D27: Uneven ring of sharpened stakes with gaps, leaning in places, rope-lashed.
B28: 2 | C28: 25–96 | D28: Continuous log wall with a fighting step behind and ladders at intervals.
B29: 3 | C29: 97–224 | D29: Doubled wall with earth fill, corner platforms, banner posts, skull-and-charm markers.
B30: 4 | C30: 225–384 | D30: Stone-footed wall with timber upper works, hoardings, and a patrol walk.
B31: 5 | C31: 385–544 | D31: Full stone curtain with crenellations, arrow slits, and flanking towers. The timber original visible in one preserved section.
B32: 6 | C32: 545–704 | D32: Gunpowder retrofit: angled earthworks and gun embrasures grafted onto the medieval curtain.
B33: 7 | C33: 705–864 | D33: Massive bastioned works dominating the approach, layered ditches, the settlement invisible behind it.
B34: 8 | C34: 865–1024 | D34: Armoured perimeter with hardened emplacements and sensor masts. Original stone preserved as an inner keep-line.
B35: 9 | C35: 1025–1152 | D35: Energy barriers between physical bastions; the air visibly thickens where the shield planes stand.
B36: 10 | C36: 1153–1280 | D36: Wall as phenomenon: a standing wave of force anchored to ancient stone, projectiles visibly slowing before reaching it.
B37: 11 | C37: 1281–1337 | D37: Unique hero asset: a named fortification with its own history, the original sharpened stakes still standing in a preserved bay.
A38: Spirit Grove | B38: 0 | C38: 0 | D38: A quiet clearing, ground swept, saplings newly ringed with stones. Nothing yet unusual.
B39: 1 | C39: 1–24 | D39: Young trees in an uneven ring, a little mist that lingers past dawn.
B40: 2 | C40: 25–96 | D40: Mature ring of trees around still water. Sound is noticeably dampened within.
B41: 3 | C41: 97–224 | D41: Ancient trunks, moss-carpeted stones, faint motes drifting upward. Birds avoid it.
B42: 4 | C42: 225–384 | D42: Trees grown unnaturally large, bark marked with script that no one carved. Permanent low mist.
B43: 5 | C43: 385–544 | D43: The grove has a centre now — a pool that reflects the wrong sky. Currents of light move between trunks.
B44: 6 | C44: 545–704 | D44: Era retrofit: containment rings and measuring instruments installed among the trees, carefully not disturbing them.
B45: 7 | C45: 705–864 | D45: The grove has grown to enclose a courtyard of its own making; the trees lean inward like a cathedral vault.
B46: 8 | C46: 865–1024 | D46: Root systems visibly lift stone. Qi flows in ribbons between canopy and pool, bright enough to read by.
B47: 9 | C47: 1025–1152 | D47: Trees grow at angles gravity does not permit. The pool has no bottom. Seasons inside differ from outside.
B48: 10 | C48: 1153–1280 | D48: The grove exists partly elsewhere. Figures glimpsed between trunks are not present when looked at directly.
B49: 11 | C49: 1281–1337 | D49: Unique hero asset: a named sacred site, one of a handful in the universe, its light visible from the system's edge.
A51: These four are worked exemplars showing the full 12-tier arc. Every other building is briefed by combining its Visual DNA line (Specs_EraI, column H) with the universal tier transformations (Visual_Tiers) and the overlay library (Visual_Overlays) — which is how the remaining 479 buildings get art-directed without 479 bespoke essays.

Sheet Holdings_Hierarchy
A1: Holding type | B1: Era | C1: Layer | D1: Plots at founding | E1: Max plots | F1: Admin cost | G1: What it can produce | H1: Notes
A2: Outpost / Camp | B2: I | C2: Province | D2: 6 | E2: 18 | F2: 1 | G2: Extraction only; no unit training | H2: Cheapest foothold. Feeds a parent settlement by haul.
A3: Village | B3: I | C3: Province | D3: 24 | E3: 110 | F3: 2 | G3: Full Era I roster; infantry and ranged | H3: The baseline settlement. Every player starts as one.
A4: Town | B4: II | C4: Province | D4: 34 | E4: 130 | F4: 4 | G4: Era I–II; cavalry, siege, Nobles | H4: Village promoted via Keep. Gains vassal management.
A5: City | B5: III | C5: Continent | D5: 48 | E5: 160 | F5: 8 | G5: Era I–III; navies, artillery, colonists | H5: Requires Imperial Palace. Governs subordinate provinces.
A6: Metropolis | B6: IV | C6: Planet | D6: 64 | E6: 200 | F6: 16 | G6: Era I–IV; armour, aircraft, capital ships | H6: Requires Capitol. Industrial heart of a planet.
A7: Asteroid Station | B7: V | C7: Belt | D7: 12 | E7: 40 | F7: 4 | G7: Extraction and refining only; no crewed units | H7: Mining specialist. Cheap, exposed, high-yield on M-type rock.
A8: Moon Base | B8: V | C8: System | D8: 20 | E8: 70 | F8: 6 | G8: Extraction, refining, light hulls | H8: He-3 and Titanium specialist. Common forward repair base.
A9: Orbital Station | B9: V | C9: Orbit | D9: 30 | E9: 100 | F9: 8 | G9: Ship modules, hulls up to cruiser; void marines | H9: The workhorse of stellar warfare. Cannot feed itself.
A10: Colony | B10: V | C10: System | D10: 40 | E10: 140 | F10: 12 | G10: Full planetary roster for its body class | H10: A second homeworld in miniature. Body class sets its yields.
A11: Planetary Capital | B11: V–VI | C11: Planet | D11: 80 | E11: 240 | F11: 24 | G11: Everything the planet has researched; capital hulls | H11: One per planet. Issues standing orders to that planet.
A12: System Hub | B12: VI | C12: System | D12: 100 | E12: 280 | F12: 40 | G12: Dreadnoughts, Titans, megastructure segments | H12: One per system. Gates system-wide control bonuses.
A13: Galactic Throne | B13: VI–VII | C13: Galaxy | D13: 140 | E13: 340 | F13: 80 | G13: Everything; Path Avatars, Void Arks | H13: One per galaxy per empire. Seat of edicts and hegemony.
A15: Every entry above is a fully independent settlement with its own plots, its own 69-building roster per era, its own queues, its own stockpile, and its own population. Capturing a planet does not give you the planet — it gives you every settlement on it, each of which must be built and run separately.

Sheet Production_Isolation
A1: Rule | B1: Detail | C1: Consequence in play
A2: Stockpiles are local | B2: Resources exist in the settlement that produced them. There is no empire treasury, no shared pool, no instant transfer. Moving goods requires carts, wagons, convoys, rail, freighters, or void haulers — all of which travel on the map and can be intercepted. | C2: Supply lines become the primary strategic geometry. Raiding a convoy is as valuable as raiding a city.
A3: Queues are local | B3: Each settlement has its own build queue (HQ-granted slots) and its own unit production lines (Barracks/Factory/Shipyard-granted). A queue slot in one city does nothing for another. | C3: More holdings genuinely means more parallel throughput. This is the core reward for conquest.
A4: Buildings do not share | B4: A level-900 Shipyard Ring accelerates production only in its own settlement. Building the same structure again in a second settlement costs full price from level 0. | C4: Wide empires rebuild constantly; every new holding is a fresh 0→N climb. Depth is expensive, breadth is expensive differently.
A5: Units spawn where built | B5: Trained units appear in their production settlement and must physically travel to the front. | C5: Forward bases are essential. A shipyard near the frontier is worth more than a better one at home.
A6: Population is local | B6: Workers cannot be transferred. A settlement grows its own population or stays small. | C6: Newly captured settlements are weak for weeks regardless of how rich their owner is. Money cannot import labour.
A7: Research is empire-wide | B7: The single exception. Research, proficiency, cultivation realm, doctrines, and dynasty traditions are properties of the player, not of a settlement. | C7: Without this, a wide empire would be unplayable. Knowledge travels; matter does not.
A8: Equipment is local stock | B8: Crafted equipment sits in the armoury that made it and must be hauled to be worn elsewhere. Captured armouries yield their contents as loot. | C8: Creates a real arms-logistics layer and makes armoury raids worthwhile.
A9: Capture preserves, barren does not | B9: A conquered developed settlement keeps its buildings at −3 grades (Cultivation and Special reset fully). A barren village, empty asteroid, or dead moon starts from plot zero. | C9: Taking a built city and settling empty rock are two completely different strategies with different costs and timelines.
A10: Specialization caps are per settlement | B10: Max 3 buildings above grade 30 and 8 above grade 20, enforced per settlement, not per empire. | C10: A thousand-holding empire can have three thousand grade-30+ buildings — but only three in any one place, so it can never be defended from one point.
A11: No administrative cap | B11: There is no limit on how many holdings a player may own and no overload penalty. A player may hold ten thousand settlements if they can take them. The only constraint is their own available attention, and the only relief is a Governor at 2× time. | C11: Empire size is bounded by what a human can actually run, not by a designer's number. Scale is earned in hours, and delegation is bought in time.

Sheet Governors
A1: GOVERNORS — automation priced in time, not efficiency
A2: There is no cap on how many holdings a player may own and no administrative overload penalty. The only limit is the player's own attention. A Governor removes the clicking and charges for it at a flat, published rate: ANYTHING A GOVERNOR INITIATES TAKES 2× TIME. Building, training, and research alike. The player may always do it themselves at full speed.
A4: Governor tier | B4: Area of authority | C4: Commander level | D4: Holdings covered | E4: Notes
A5: Bailiff | B5: One province | C5: 5+ | D5: All your holdings in it | E5: Entry tier. Most players appoint their first by mid Era II.
A6: Planetary Governor | B6: One planet | C6: 15+ | D6: All your holdings on it | E6: Covers every continent, sea, and polar settlement on that world.
A7: System Governor | B7: One star system | C7: 25+ | D7: Planet, moons, belts, orbitals | E7: The tier where wide play genuinely becomes possible.
A8: Sector Governor | B8: One galactic arm | C8: 40+ | D8: Every holding in the arm | E8: Era VI+. Rare; each occupies a scarce command slot.
A10: THE 2× RULE — exact behaviour
A11: Case | B11: Speed | C11: Detail
A12: Player initiates in person | B12: 1.0× | C12: Full speed. Occupies one of the settlement's HQ-granted personal queue slots.
A13: Governor initiates from spec | B13: 2.0× | C13: Double time. Runs in the governor's own parallel queue, which does not consume personal slots.
A14: Player SEIZES a governor job | B14: 1.0× on remaining time | C14: Requires a free personal queue slot in that settlement. Elapsed progress is kept; the remainder is recalculated at full speed. This is how attention gets spent where it matters.
A15: Governor job with no free personal slot | B15: 2.0× | C15: Cannot be seized until a personal slot frees up. Slot scarcity is what stops "governor everything, then seize everything".
A16: Governor research mandate | B16: 2.0× | C16: A governor may be granted authority over exactly one research discipline. Only one governor may hold a given discipline at a time.
A17: Governor training order | B17: 2.0× | C17: Applies per unit, so a Mythic Path Avatar ordered by a governor takes a year rather than six months.
A18: Repair and rebuilding | B18: 2.0× | C18: Governors repair siege damage at double time. Emergency repairs are a classic reason to seize.
A20: WHERE THE 2× RULE SELF-SORTS
A21: Example job | B21: By hand | C21: By governor | D21: Rational choice
A22: Farm to level 60 | B22: ~40 minutes | C22: ~80 minutes | D22: Governor. The difference is irrelevant.
A23: Barracks to level 200 | B23: ~1.6 days | C23: ~3.2 days | D23: Governor, usually. Seize if a war is coming.
A24: Militia batch, 200 units | B24: ~6 days | C24: ~12 days | D24: Governor for garrison; by hand for an offensive.
A25: Shipyard Ring to level 700 | B25: ~1.5 months | C25: ~3 months | D25: By hand. This is a crown jewel.
A26: Mythic Path Avatar | B26: 6 months | C26: 1 year | D26: Always by hand. Nobody governs an Avatar.
A27: Citadel to level 1200 | B27: ~1.4 years | C27: ~2.8 years | D27: By hand, over epochs. A governor would never finish it.
A29: The mechanic sorts itself: trivial work is automated because doubling nothing is nothing, and the structures that define an empire are hand-built because doubling years is unaffordable. A player's personal attention flows naturally to exactly the things that matter, which is what an attention economy should do.
A31: GOVERNOR FAILURE MODES — automation is not safety
A32: Assassination | B32: A dead governor's entire area stalls — running jobs continue, nothing new is initiated — until a replacement is appointed and travels there. Enemy spymasters target governors precisely because the blast radius is a whole province.
A33: Subversion | B33: An enemy Spymaster may turn a governor rather than kill them. A turned governor follows corrupted specs: building the wrong things, training the wrong mix, leaking your stockpiles. Detectable by audit, but only if you look.
A34: Literal interpretation | B34: Governors execute specs exactly as written, with no judgement. A build order that does not account for a resource shortfall will stall the whole queue rather than skip ahead.
A35: Spec starvation | B35: A governor ordered to build what the settlement cannot afford simply waits. Idle governor areas show on the attention dashboard, but a player who is not looking will find a province that did nothing for a week.
A36: Capture | B36: A captured settlement drops out of its governor's area immediately. Governors do not follow conquered ground.

Sheet Governor_Specs
A1: Spec sheet | B1: What the player defines | C1: Governor behaviour | D1: Failure if left vague
A2: Build Order | B2: An ordered blueprint: building names with target grades, in sequence. May include conditional entries ("Granary to grade 8 if stored Food falls below 3 days"). | C2: Works down the list, initiating each at 2× time. Never reorders, never improvises. | D2: Stalls on the first unaffordable entry and builds nothing further.
A3: Training Standing Order | B3: A unit template mix with target counts, plus a reinforce-or-hold flag and a garrison floor. | C3: Maintains the target counts at 2× per unit, replacing losses automatically. | D3: Trains nothing, or drains the settlement on an unbounded order.
A4: Research Mandate | B4: One discipline and a target grade. Only one governor may hold any given discipline. | C4: Advances that discipline at 2× time using the settlement's Data and resources. | D4: Idles. Research is the easiest mandate to forget you granted.
A5: Resource Policy | B5: Stockpile floors per resource, a surplus haul destination, and market sell thresholds. | C5: Dispatches haul convoys and market orders automatically, within the floors. | D5: Warehouses overflow and the surplus is lost permanently.
A6: Defence Posture | B6: One of: Turtle (garrison only), Hold (garrison plus local counter-attack), Sally (counter-attack siege engines), Evacuate (haul out and abandon). | C6: Applies the posture to every engagement in the area without consulting the player. | D6: Defaults to Turtle, which loses winnable fights and wins unwinnable ones slowly.
A7: Escalation Rules | B7: Thresholds at which the governor stops acting and alerts the player instead: incoming force size, noble/conquest units detected, stockpile below floor, spec stalled. | C7: Pushes an alert to the attention dashboard and, if configured, pauses its own queue. | D7: The player learns about a lost province from the battle report.
A9: Specs are saved as named profiles and reusable across areas. Writing a good spec sheet is a genuine skill and a shareable artefact — expect veteran players to publish "mining colony v3" and "frontier fortress" templates the way they publish build orders today.

Sheet Empire_Management
A1: Tool | B1: What it does | C1: Relationship to the 2× rule
A2: Blueprints | B2: Save any settlement's build order as a named template, then apply it to a new holding or hand it to a governor as a Build Order spec. | C2: A blueprint applied by the player runs at 1×. The same blueprint handed to a governor runs at 2×. Same list, different price.
A3: Governors | B3: Appoint a Governor-archetype commander over a province, planet, system, or galactic arm to execute spec sheets without the player clicking. | C3: This IS the 2× rule. Convenience purchased with time.
A4: Seize | B4: Take direct control of any single in-progress governor job. Elapsed progress is kept and the remainder recalculates at full speed. | C4: Requires a free personal queue slot. Slot scarcity is the only thing stopping a player from governing everything and seizing it all back.
A5: Attention dashboard | B5: Sortable stream of everything needing the player: idle queues, stalled governor specs, full warehouses, understaffed buildings, incoming attacks, escalation alerts. | C5: The single most important interface in the game. With full isolation and no admin cap, this is where players will actually live — build it before the map.
A6: Multi-select operations | B6: Filter and select many holdings to issue the same personal order to each. | C6: Every order is still initiated personally, so every order runs at 1×. This is honest clicking made faster, not automation.
A7: Settlement search | B7: Query the empire in plain terms: shipyards above grade 20 within three jumps of the front, governor areas with stalled specs, holdings with surplus titanium. | C7: Pure information. Makes an unbounded empire legible without making it smaller or faster.
A8: Governor audit | B8: Compare a governor's actual output against their spec to detect subversion, starvation, or a spec that no longer fits the situation. | C8: The counter-espionage tool for the automation layer. A turned governor is invisible until audited.
A9: Spec library | B9: Save, name, version, and share spec profiles within an alliance. | C9: Turns spec-writing into transferable expertise. Veterans mentor newcomers by handing over a good spec, not by doing the work for them.

Sheet Veterancy_XP
A1: THE SPLIT CURVE — difficulty from two gentle slopes instead of one brutal one
A2: Difficulty is the PRODUCT of two curves: XP required rises slowly, and XP earned per battle decays slowly (Experience Fatigue). Neither number ever leaves a readable range, but multiplied together they produce the steep pacing the ladder needs. This replaces the pure-exponential requirement, which reached 10^402 and could not be stored.
A4: REQUIREMENT SIDE | D4: EARN SIDE (Experience Fatigue) | G4: EMPIRE WEIGHT (requirement side)
A5: Base XP per level | B5: 100 | D5: Base XP per battle | E5: 1000 | G5: Empire Weight W | H5: 400
A6: Level exponent | B6: 0.21 | D6: Level decay exponent | E6: 0.21 | G6: Requirement multiplier | H6: =MIN(Empire_Weight_Multiplier!$F$8, 1+($H$5/Empire_Weight_Multiplier!$B$8)^Empire_Weight_Multiplier!$D$8) -> 29.246496
A7: Tier multiplier | B7: 1.3 | D7: Tier divisor | E7: 1.25 | G7: Stacks on top of level and tier factors
A9: RESULTING SPREAD
A10: Largest XP requirement ever shown | B10: =ROUND($B$5*1338^$B$6*$B$7^23,0) -> 189345 | G10: A number a player can read at a glance
A11: Smallest XP award ever shown | B11: =ROUND($E$5/(1338^$E$6*$E$7^23),1) -> 1.3 | G11: Still a whole number on screen
A12: Requirement growth across a tier | B12: =ROUND(1338^$B$6,2)&"x" -> 4.53x | G12: Gentle
A13: Earn decay across a tier | B13: ="1/"&ROUND(1338^$E$6,2) -> 1/4.53 | G13: Gentle
A14: Effective difficulty across a tier | B14: =ROUND(1338^($B$6+$E$6),1)&"x" -> 20.6x | G14: The product — this is what players feel
A15: Effective difficulty per tier step | B15: =ROUND($B$7*$E$7,3)&"x" -> 1.625x | G15: Each tier takes this much longer than the last
A16: Effective difficulty, whole ladder | B16: =ROUND(1338^($B$6+$E$6)*($B$7*$E$7)^23,0) -> 1454585 | G16: Steep pacing from two shallow curves
A17: Largest XP requirement at this Empire Weight | B17: =ROUND($B$5*1338^$B$6*$B$7^23*$H$6,0) -> 5537666
A18: PACING — tiers reached, assuming tier 1 clears in one month of active war
A19: Tier | B19: Name | C19: Months to clear this tier | D19: Cumulative years | E19: Who gets here
A20: 1 | B20: Copper | C20: =ROUND(($B$7*$E$7)^(A20-1),1) -> 1 | D20: =ROUND(C20/12,2) -> 0.08 | E20: Every formation that survives a war
A21: 2 | B21: Bronze | C21: =ROUND(($B$7*$E$7)^(A21-1),1) -> 1.6 | D21: =ROUND(D20+C21/12,2) -> 0.21
A22: 3 | B22: Iron | C22: =ROUND(($B$7*$E$7)^(A22-1),1) -> 2.6 | D22: =ROUND(D21+C22/12,2) -> 0.43
A23: 4 | B23: Steel | C23: =ROUND(($B$7*$E$7)^(A23-1),1) -> 4.3 | D23: =ROUND(D22+C23/12,2) -> 0.79 | E23: A season of steady campaigning
A24: 5 | B24: Silver | C24: =ROUND(($B$7*$E$7)^(A24-1),1) -> 7 | D24: =ROUND(D23+C24/12,2) -> 1.37
A25: 6 | B25: Electrum | C25: =ROUND(($B$7*$E$7)^(A25-1),1) -> 11.3 | D25: =ROUND(D24+C25/12,2) -> 2.31
A26: 7 | B26: Gold | C26: =ROUND(($B$7*$E$7)^(A26-1),1) -> 18.4 | D26: =ROUND(D25+C26/12,2) -> 3.84
A27: 8 | B27: Jade | C27: =ROUND(($B$7*$E$7)^(A27-1),1) -> 29.9 | D27: =ROUND(D26+C27/12,2) -> 6.33 | E27: A dedicated formation kept alive for years
A28: 9 | B28: Amber | C28: =ROUND(($B$7*$E$7)^(A28-1),1) -> 48.6 | D28: =ROUND(D27+C28/12,2) -> 10.38
A29: 10 | B29: Emerald | C29: =ROUND(($B$7*$E$7)^(A29-1),1) -> 79 | D29: =ROUND(D28+C29/12,2) -> 16.96
A30: 11 | B30: Sapphire | C30: =ROUND(($B$7*$E$7)^(A30-1),1) -> 128.4 | D30: =ROUND(D29+C30/12,2) -> 27.66
A31: 12 | B31: Ruby | C31: =ROUND(($B$7*$E$7)^(A31-1),1) -> 208.6 | D31: =ROUND(D30+C31/12,2) -> 45.04 | E31: A dynasty-defining asset
A32: 13 | B32: Diamond | C32: =ROUND(($B$7*$E$7)^(A32-1),1) -> 339 | D32: =ROUND(D31+C32/12,2) -> 73.29
A33: 14 | B33: Platinum | C33: =ROUND(($B$7*$E$7)^(A33-1),1) -> 550.9 | D33: =ROUND(D32+C33/12,2) -> 119.2
A34: 15 | B34: Mithril | C34: =ROUND(($B$7*$E$7)^(A34-1),1) -> 895.3 | D34: =ROUND(D33+C34/12,2) -> 193.81
A35: 16 | B35: Adamant | C35: =ROUND(($B$7*$E$7)^(A35-1),1) -> 1454.8 | D35: =ROUND(D34+C35/12,2) -> 315.04 | E35: Legendary; a handful per galaxy
A36: 17 | B36: Orichalcum | C36: =ROUND(($B$7*$E$7)^(A36-1),1) -> 2364 | D36: =ROUND(D35+C36/12,2) -> 512.04
A37: 18 | B37: Meteoric | C37: =ROUND(($B$7*$E$7)^(A37-1),1) -> 3841.6 | D37: =ROUND(D36+C37/12,2) -> 832.17
A38: 19 | B38: Starsteel | C38: =ROUND(($B$7*$E$7)^(A38-1),1) -> 6242.5 | D38: =ROUND(D37+C38/12,2) -> 1352.38
A39: 20 | B39: Void Iron | C39: =ROUND(($B$7*$E$7)^(A39-1),1) -> 10144.1 | D39: =ROUND(D38+C39/12,2) -> 2197.72 | E39: Mythic; spoken of universe-wide
A40: 21 | B40: Aetherium | C40: =ROUND(($B$7*$E$7)^(A40-1),1) -> 16484.2 | D40: =ROUND(D39+C40/12,2) -> 3571.4
A41: 22 | B41: Empyrean | C41: =ROUND(($B$7*$E$7)^(A41-1),1) -> 26786.8 | D41: =ROUND(D40+C41/12,2) -> 5803.63
A42: 23 | B42: Primordial | C42: =ROUND(($B$7*$E$7)^(A42-1),1) -> 43528.5 | D42: =ROUND(D41+C42/12,2) -> 9431.01
A43: 24 | B43: Eternal | C43: =ROUND(($B$7*$E$7)^(A43-1),1) -> 70733.9 | D43: =ROUND(D42+C43/12,2) -> 15325.5 | E43: One formation in recorded history

Sheet Veterancy_Levels
A1: Level in tier | B1: XP required (tier 1) | C1: Earn multiplier | D1: XP per battle (tier 1) | E1: Battles for this level | F1: Cumulative battles in tier
A2: 0 | B2: =ROUND(Veterancy_XP!$B$5*(A2+1)^Veterancy_XP!$B$6,0) -> 100 | C2: =ROUND(1/(A2+1)^Veterancy_XP!$E$6,4) -> 1 | D2: =ROUND(Veterancy_XP!$E$5*C2,1) -> 1000 | E2: =ROUND(B2/D2,2) -> 0.1 | F2: =E2 -> 0.1
A3: 1 | B3: =ROUND(Veterancy_XP!$B$5*(A3+1)^Veterancy_XP!$B$6,0) -> 116 | C3: =ROUND(1/(A3+1)^Veterancy_XP!$E$6,4) -> 0.8645 | D3: =ROUND(Veterancy_XP!$E$5*C3,1) -> 864.5 | E3: =ROUND(B3/D3,2) -> 0.13 | F3: =ROUND(F2+E3,2) -> 0.23
A4: 2 | B4: =ROUND(Veterancy_XP!$B$5*(A4+1)^Veterancy_XP!$B$6,0) -> 126 | C4: =ROUND(1/(A4+1)^Veterancy_XP!$E$6,4) -> 0.794 | D4: =ROUND(Veterancy_XP!$E$5*C4,1) -> 794 | E4: =ROUND(B4/D4,2) -> 0.16 | F4: =ROUND(F3+E4,2) -> 0.39
A5: 3 | B5: =ROUND(Veterancy_XP!$B$5*(A5+1)^Veterancy_XP!$B$6,0) -> 134 | C5: =ROUND(1/(A5+1)^Veterancy_XP!$E$6,4) -> 0.7474 | D5: =ROUND(Veterancy_XP!$E$5*C5,1) -> 747.4 | E5: =ROUND(B5/D5,2) -> 0.18 | F5: =ROUND(F4+E5,2) -> 0.57
A6: 4 | B6: =ROUND(Veterancy_XP!$B$5*(A6+1)^Veterancy_XP!$B$6,0) -> 140 | C6: =ROUND(1/(A6+1)^Veterancy_XP!$E$6,4) -> 0.7132 | D6: =ROUND(Veterancy_XP!$E$5*C6,1) -> 713.2 | E6: =ROUND(B6/D6,2) -> 0.2 | F6: =ROUND(F5+E6,2) -> 0.77
A7: 5 | B7: =ROUND(Veterancy_XP!$B$5*(A7+1)^Veterancy_XP!$B$6,0) -> 146 | C7: =ROUND(1/(A7+1)^Veterancy_XP!$E$6,4) -> 0.6864 | D7: =ROUND(Veterancy_XP!$E$5*C7,1) -> 686.4 | E7: =ROUND(B7/D7,2) -> 0.21 | F7: =ROUND(F6+E7,2) -> 0.98
A8: 6 | B8: =ROUND(Veterancy_XP!$B$5*(A8+1)^Veterancy_XP!$B$6,0) -> 150 | C8: =ROUND(1/(A8+1)^Veterancy_XP!$E$6,4) -> 0.6646 | D8: =ROUND(Veterancy_XP!$E$5*C8,1) -> 664.6 | E8: =ROUND(B8/D8,2) -> 0.23 | F8: =ROUND(F7+E8,2) -> 1.21
A9: 7 | B9: =ROUND(Veterancy_XP!$B$5*(A9+1)^Veterancy_XP!$B$6,0) -> 155 | C9: =ROUND(1/(A9+1)^Veterancy_XP!$E$6,4) -> 0.6462 | D9: =ROUND(Veterancy_XP!$E$5*C9,1) -> 646.2 | E9: =ROUND(B9/D9,2) -> 0.24 | F9: =ROUND(F8+E9,2) -> 1.45
A10: 8 | B10: =ROUND(Veterancy_XP!$B$5*(A10+1)^Veterancy_XP!$B$6,0) -> 159 | C10: =ROUND(1/(A10+1)^Veterancy_XP!$E$6,4) -> 0.6304 | D10: =ROUND(Veterancy_XP!$E$5*C10,1) -> 630.4 | E10: =ROUND(B10/D10,2) -> 0.25 | F10: =ROUND(F9+E10,2) -> 1.7
A11: 9 | B11: =ROUND(Veterancy_XP!$B$5*(A11+1)^Veterancy_XP!$B$6,0) -> 162 | C11: =ROUND(1/(A11+1)^Veterancy_XP!$E$6,4) -> 0.6166 | D11: =ROUND(Veterancy_XP!$E$5*C11,1) -> 616.6 | E11: =ROUND(B11/D11,2) -> 0.26 | F11: =ROUND(F10+E11,2) -> 1.96
A12: 10 | B12: =ROUND(Veterancy_XP!$B$5*(A12+1)^Veterancy_XP!$B$6,0) -> 165 | C12: =ROUND(1/(A12+1)^Veterancy_XP!$E$6,4) -> 0.6044 | D12: =ROUND(Veterancy_XP!$E$5*C12,1) -> 604.4 | E12: =ROUND(B12/D12,2) -> 0.27 | F12: =ROUND(F11+E12,2) -> 2.23
A13: 11 | B13: =ROUND(Veterancy_XP!$B$5*(A13+1)^Veterancy_XP!$B$6,0) -> 169 | C13: =ROUND(1/(A13+1)^Veterancy_XP!$E$6,4) -> 0.5934 | D13: =ROUND(Veterancy_XP!$E$5*C13,1) -> 593.4 | E13: =ROUND(B13/D13,2) -> 0.28 | F13: =ROUND(F12+E13,2) -> 2.51
A14: 12 | B14: =ROUND(Veterancy_XP!$B$5*(A14+1)^Veterancy_XP!$B$6,0) -> 171 | C14: =ROUND(1/(A14+1)^Veterancy_XP!$E$6,4) -> 0.5835 | D14: =ROUND(Veterancy_XP!$E$5*C14,1) -> 583.5 | E14: =ROUND(B14/D14,2) -> 0.29 | F14: =ROUND(F13+E14,2) -> 2.8
... A1339: 1337 | B1339: =ROUND(Veterancy_XP!$B$5*(A1339+1)^Veterancy_XP!$B$6,0) -> 453 | C1339: =ROUND(1/(A1339+1)^Veterancy_XP!$E$6,4) -> 0.2205 | D1339: =ROUND(Veterancy_XP!$E$5*C1339,1) -> 220.5 | E1339: =ROUND(B1339/D1339,2) -> 2.05 | F1339: =ROUND(F1338+E1339,2) -> 1938.65

Sheet Veterancy_Tiers
A1: VETERANCY TIERS — gates bought with resources, not stat bonuses
A2: A tier grants no stats. It unlocks the next 1,337 levels and must be purchased. All combat benefit comes from levels: +1% each, accumulating across every tier to 322x at the top of Eternal.
A4: Tier-2 base cost | B4: 50000 | C4: Cost multiplier per tier | D4: 2.75
A5: Benchmark empire output / hour | B5: 1000000000 | C5: Lifetime budget (500 yr) | D5: =B5*8766*500 -> 4.383e+15
A7: Tier | B7: Name | C7: Cumulative levels | D7: Total stat bonus | E7: Tier-up cost | F7: Years of benchmark output | G7: XP req mult | H7: Earn divisor | I7: Reputation at this tier
A8: 1 | B8: Copper | C8: =A8*1337 -> 1337 | D8: =ROUND(1+0.01*C8,2)&"x" -> 14.37x | E8: — (starting tier) | F8: — | G8: =ROUND(Veterancy_XP!$B$7^(A8-1),2) -> 1 | H8: =ROUND(Veterancy_XP!$E$7^(A8-1),2) -> 1 | I8: Green troops who have survived one real fight.
A9: 2 | B9: Bronze | C9: =A9*1337 -> 2674 | D9: =ROUND(1+0.01*C9,2)&"x" -> 27.74x | E9: =ROUND($B$4*$D$4^(A9-2),0) -> 50000 | F9: =ROUND($B$4*$D$4^(A9-2)/($B$5*8766),3) -> 0 | G9: =ROUND(Veterancy_XP!$B$7^(A9-1),2) -> 1.3 | H9: =ROUND(Veterancy_XP!$E$7^(A9-1),2) -> 1.25 | I9: Blooded. They no longer break on contact.
A10: 3 | B10: Iron | C10: =A10*1337 -> 4011 | D10: =ROUND(1+0.01*C10,2)&"x" -> 41.11x | E10: =ROUND($B$4*$D$4^(A10-2),0) -> 137500 | F10: =ROUND($B$4*$D$4^(A10-2)/($B$5*8766),3) -> 0 | G10: =ROUND(Veterancy_XP!$B$7^(A10-1),2) -> 1.69 | H10: =ROUND(Veterancy_XP!$E$7^(A10-1),2) -> 1.56 | I10: Disciplined. They hold a line without an officer shouting.
A11: 4 | B11: Steel | C11: =A11*1337 -> 5348 | D11: =ROUND(1+0.01*C11,2)&"x" -> 54.48x | E11: =ROUND($B$4*$D$4^(A11-2),0) -> 378125 | F11: =ROUND($B$4*$D$4^(A11-2)/($B$5*8766),3) -> 0 | G11: =ROUND(Veterancy_XP!$B$7^(A11-1),2) -> 2.2 | H11: =ROUND(Veterancy_XP!$E$7^(A11-1),2) -> 1.95 | I11: Hardened. Casualties stop frightening them.
A12: 5 | B12: Silver | C12: =A12*1337 -> 6685 | D12: =ROUND(1+0.01*C12,2)&"x" -> 67.85x | E12: =ROUND($B$4*$D$4^(A12-2),0) -> 1039844 | F12: =ROUND($B$4*$D$4^(A12-2)/($B$5*8766),3) -> 0 | G12: =ROUND(Veterancy_XP!$B$7^(A12-1),2) -> 2.86 | H12: =ROUND(Veterancy_XP!$E$7^(A12-1),2) -> 2.44 | I12: Professional. Other formations copy their drill.
A13: 6 | B13: Electrum | C13: =A13*1337 -> 8022 | D13: =ROUND(1+0.01*C13,2)&"x" -> 81.22x | E13: =ROUND($B$4*$D$4^(A13-2),0) -> 2859570 | F13: =ROUND($B$4*$D$4^(A13-2)/($B$5*8766),3) -> 0 | G13: =ROUND(Veterancy_XP!$B$7^(A13-1),2) -> 3.71 | H13: =ROUND(Veterancy_XP!$E$7^(A13-1),2) -> 3.05 | I13: Renowned in their own province.
A14: 7 | B14: Gold | C14: =A14*1337 -> 9359 | D14: =ROUND(1+0.01*C14,2)&"x" -> 94.59x | E14: =ROUND($B$4*$D$4^(A14-2),0) -> 7863818 | F14: =ROUND($B$4*$D$4^(A14-2)/($B$5*8766),3) -> 0 | G14: =ROUND(Veterancy_XP!$B$7^(A14-1),2) -> 4.83 | H14: =ROUND(Veterancy_XP!$E$7^(A14-1),2) -> 3.81 | I14: Renowned across the continent. Enemies name them in reports.
A15: 8 | B15: Jade | C15: =A15*1337 -> 10696 | D15: =ROUND(1+0.01*C15,2)&"x" -> 107.96x | E15: =ROUND($B$4*$D$4^(A15-2),0) -> 21625500 | F15: =ROUND($B$4*$D$4^(A15-2)/($B$5*8766),3) -> 0 | G15: =ROUND(Veterancy_XP!$B$7^(A15-1),2) -> 6.27 | H15: =ROUND(Veterancy_XP!$E$7^(A15-1),2) -> 4.77 | I15: The formation has a banner and a history.
A16: 9 | B16: Amber | C16: =A16*1337 -> 12033 | D16: =ROUND(1+0.01*C16,2)&"x" -> 121.33x | E16: =ROUND($B$4*$D$4^(A16-2),0) -> 59470126 | F16: =ROUND($B$4*$D$4^(A16-2)/($B$5*8766),3) -> 0 | G16: =ROUND(Veterancy_XP!$B$7^(A16-1),2) -> 8.16 | H16: =ROUND(Veterancy_XP!$E$7^(A16-1),2) -> 5.96 | I16: Songs exist about a battle they won.
A17: 10 | B17: Emerald | C17: =A17*1337 -> 13370 | D17: =ROUND(1+0.01*C17,2)&"x" -> 134.7x | E17: =ROUND($B$4*$D$4^(A17-2),0) -> 163542847 | F17: =ROUND($B$4*$D$4^(A17-2)/($B$5*8766),3) -> 0 | G17: =ROUND(Veterancy_XP!$B$7^(A17-1),2) -> 10.6 | H17: =ROUND(Veterancy_XP!$E$7^(A17-1),2) -> 7.45 | I17: Their presence changes how an enemy plans an attack.
A18: 11 | B18: Sapphire | C18: =A18*1337 -> 14707 | D18: =ROUND(1+0.01*C18,2)&"x" -> 148.07x | E18: =ROUND($B$4*$D$4^(A18-2),0) -> 449742830 | F18: =ROUND($B$4*$D$4^(A18-2)/($B$5*8766),3) -> 0 | G18: =ROUND(Veterancy_XP!$B$7^(A18-1),2) -> 13.79 | H18: =ROUND(Veterancy_XP!$E$7^(A18-1),2) -> 9.31 | I18: A commander will refuse an engagement rather than face them.
A19: 12 | B19: Ruby | C19: =A19*1337 -> 16044 | D19: =ROUND(1+0.01*C19,2)&"x" -> 161.44x | E19: =ROUND($B$4*$D$4^(A19-2),0) -> 1236792784 | F19: =ROUND($B$4*$D$4^(A19-2)/($B$5*8766),3) -> 0 | G19: =ROUND(Veterancy_XP!$B$7^(A19-1),2) -> 17.92 | H19: =ROUND(Veterancy_XP!$E$7^(A19-1),2) -> 11.64 | I19: A strategic asset in their own right.
A20: 13 | B20: Diamond | C20: =A20*1337 -> 17381 | D20: =ROUND(1+0.01*C20,2)&"x" -> 174.81x | E20: =ROUND($B$4*$D$4^(A20-2),0) -> 3401180155 | F20: =ROUND($B$4*$D$4^(A20-2)/($B$5*8766),3) -> 0 | G20: =ROUND(Veterancy_XP!$B$7^(A20-1),2) -> 23.3 | H20: =ROUND(Veterancy_XP!$E$7^(A20-1),2) -> 14.55 | I20: Their reputation is worth a garrison on its own.
... A31: 24 | B31: Eternal | C31: =A31*1337 -> 32088 | D31: =ROUND(1+0.01*C31,2)&"x" -> 321.88x | E31: =ROUND($B$4*$D$4^(A31-2),0) -> 231360528990876 | F31: =ROUND($B$4*$D$4^(A31-2)/($B$5*8766),3) -> 26.393 | G31: =ROUND(Veterancy_XP!$B$7^(A31-1),2) -> 417.54 | H31: =ROUND(Veterancy_XP!$E$7^(A31-1),2) -> 169.41 | I31: One formation in recorded history may hold this.
A32: Total of all tier-ups | E32: =ROUND(SUM(E9:E31),0) -> 363566545528516 | F32: =ROUND(SUM(E9:E31)/($B$5*8766),2)&" years of full output" -> 41.47 years of full output

Sheet Veterancy_Calculator
A1: Formation standing
A3: Tier (1-24) | B3: 12 | C3: Level in tier (0-1337) | D3: 800 | E3: Empire Weight | F3: 400
A5: Tier name | B5: =INDEX(Veterancy_Tiers!$B$8:$B$31, $B$3) -> Ruby
A6: Cumulative levels earned | B6: =($B$3-1)*1337+$D$3 -> 15507
A7: Total stat bonus (all stats) | B7: =ROUND(1+0.01*B6,2)&"x" -> 156.07x
A8: XP required for next level (base, before weight) | B8: =ROUND(Veterancy_XP!$B$5*($D$3+1)^Veterancy_XP!$B$6*Veterancy_XP!$B$7^($B$3-1),0) -> 7297
A9: XP earned per standard battle | B9: =ROUND(Veterancy_XP!$E$5/(($D$3+1)^Veterancy_XP!$E$6*Veterancy_XP!$E$7^($B$3-1)),1) -> 21.1
A10: Battles for the next level (at this weight) | B10: =ROUND(B14/B9,1) -> 10098.2
A11: Cost of next tier-up | B11: =IF($B$3>=24,"MAX TIER",ROUND(Veterancy_Tiers!$B$4*Veterancy_Tiers!$D$4^($B$3-1),0)) -> 3401180155
A12: Max era allowed | B12: =MIN(7, ROUNDUP($B$3/3.5,0)) -> 4
A13: Empire Weight multiplier | B13: =ROUND(MIN(Empire_Weight_Multiplier!$F$8, 1+($F$3/Empire_Weight_Multiplier!$B$8)^Empire_Weight_Multiplier!$D$8),1) -> 29.2
A14: XP REQUIRED (fully stacked) | B14: =ROUND(B8*B13,0) -> 213072
A15: THE LADDER AT KEY RUNGS
A16: Tier | B16: Name | C16: Level | D16: Stat bonus | E16: XP needed | F16: Battles per level
A17: 1 | B17: =INDEX(Veterancy_Tiers!$B$8:$B$31, A17) -> Copper | C17: 0 | D17: =ROUND(1+0.01*((A17-1)*1337+C17),2)&"x" -> 1x | E17: =ROUND(Veterancy_XP!$B$5*(C17+1)^Veterancy_XP!$B$6*Veterancy_XP!$B$7^(A17-1),0) -> 100 | F17: =ROUND(E17/(Veterancy_XP!$E$5/((C17+1)^Veterancy_XP!$E$6*Veterancy_XP!$E$7^(A17-1))),1) -> 0.1
A18: 1 | B18: =INDEX(Veterancy_Tiers!$B$8:$B$31, A18) -> Copper | C18: 1337 | D18: =ROUND(1+0.01*((A18-1)*1337+C18),2)&"x" -> 14.37x | E18: =ROUND(Veterancy_XP!$B$5*(C18+1)^Veterancy_XP!$B$6*Veterancy_XP!$B$7^(A18-1),0) -> 453 | F18: =ROUND(E18/(Veterancy_XP!$E$5/((C18+1)^Veterancy_XP!$E$6*Veterancy_XP!$E$7^(A18-1))),1) -> 2.1
A19: 4 | B19: =INDEX(Veterancy_Tiers!$B$8:$B$31, A19) -> Steel | C19: 0 | D19: =ROUND(1+0.01*((A19-1)*1337+C19),2)&"x" -> 41.11x | E19: =ROUND(Veterancy_XP!$B$5*(C19+1)^Veterancy_XP!$B$6*Veterancy_XP!$B$7^(A19-1),0) -> 220 | F19: =ROUND(E19/(Veterancy_XP!$E$5/((C19+1)^Veterancy_XP!$E$6*Veterancy_XP!$E$7^(A19-1))),1) -> 0.4
A20: 8 | B20: =INDEX(Veterancy_Tiers!$B$8:$B$31, A20) -> Jade | C20: 668 | D20: =ROUND(1+0.01*((A20-1)*1337+C20),2)&"x" -> 101.27x | E20: =ROUND(Veterancy_XP!$B$5*(C20+1)^Veterancy_XP!$B$6*Veterancy_XP!$B$7^(A20-1),0) -> 2460 | F20: =ROUND(E20/(Veterancy_XP!$E$5/((C20+1)^Veterancy_XP!$E$6*Veterancy_XP!$E$7^(A20-1))),1) -> 46
A21: 12 | B21: =INDEX(Veterancy_Tiers!$B$8:$B$31, A21) -> Ruby | C21: 1337 | D21: =ROUND(1+0.01*((A21-1)*1337+C21),2)&"x" -> 161.44x | E21: =ROUND(Veterancy_XP!$B$5*(C21+1)^Veterancy_XP!$B$6*Veterancy_XP!$B$7^(A21-1),0) -> 8127 | F21: =ROUND(E21/(Veterancy_XP!$E$5/((C21+1)^Veterancy_XP!$E$6*Veterancy_XP!$E$7^(A21-1))),1) -> 429
A22: 16 | B22: =INDEX(Veterancy_Tiers!$B$8:$B$31, A22) -> Adamant | C22: 0 | D22: =ROUND(1+0.01*((A22-1)*1337+C22),2)&"x" -> 201.55x | E22: =ROUND(Veterancy_XP!$B$5*(C22+1)^Veterancy_XP!$B$6*Veterancy_XP!$B$7^(A22-1),0) -> 5119 | F22: =ROUND(E22/(Veterancy_XP!$E$5/((C22+1)^Veterancy_XP!$E$6*Veterancy_XP!$E$7^(A22-1))),1) -> 145.5
A23: 20 | B23: =INDEX(Veterancy_Tiers!$B$8:$B$31, A23) -> Void Iron | C23: 800 | D23: =ROUND(1+0.01*((A23-1)*1337+C23),2)&"x" -> 263.03x | E23: =ROUND(Veterancy_XP!$B$5*(C23+1)^Veterancy_XP!$B$6*Veterancy_XP!$B$7^(A23-1),0) -> 59523 | F23: =ROUND(E23/(Veterancy_XP!$E$5/((C23+1)^Veterancy_XP!$E$6*Veterancy_XP!$E$7^(A23-1))),1) -> 16816.6
A24: 24 | B24: =INDEX(Veterancy_Tiers!$B$8:$B$31, A24) -> Eternal | C24: 1337 | D24: =ROUND(1+0.01*((A24-1)*1337+C24),2)&"x" -> 321.88x | E24: =ROUND(Veterancy_XP!$B$5*(C24+1)^Veterancy_XP!$B$6*Veterancy_XP!$B$7^(A24-1),0) -> 189345 | F24: =ROUND(E24/(Veterancy_XP!$E$5/((C24+1)^Veterancy_XP!$E$6*Veterancy_XP!$E$7^(A24-1))),1) -> 145458.8

Sheet Veterancy_Rules
A1: Rule | B1: Detail | C1: Why
A2: Tiers are gates, not bonuses | B2: A tier-up grants no stats. It purchases the right to keep earning levels. All combat benefit comes from +1% per level, accumulating across every tier to 322x at the top of Eternal. | C2: Keeps the lifetime ladder in the same order of magnitude as the era spread, so counters, terrain, timing and force size all stay decisive.
A3: Tier-ups cost resources | B3: Paid from the formation's home settlement stockpile and hauled there like anything else. Cost multiplies 2.75x per tier, from 50,000 at Bronze to roughly 2.3 x 10^14 at Eternal. The payment is announced regionally. | C3: Makes veterancy an economic commitment and a public political fact. Rivals learn the moment a neighbour has spent a fortune on their army.
A4: Difficulty is a product, not a curve | B4: XP required rises gently with level and tier; XP earned per battle decays gently with level and tier. Neither number leaves a readable range. Multiplied, they produce roughly 20x difficulty growth across a tier and 1.625x per tier step. | C4: Two shallow slopes give the same pacing as one brutal exponential while keeping every displayed figure small. The largest XP requirement in the whole game is about 189,000; the smallest award is about 1 XP.
A5: Experience Fatigue | B5: A formation learns less from each fight as it advances. Earn rate falls to 1/4.5 across a tier and 1/169 by Eternal. | C5: Diegetically true — there is less left to learn — and it means an elite formation cannot be grown on easy fights.
A6: XP scales with the opposition | B6: Awards scale with the defeated force's veterancy and grade. Losing grants roughly 60% of the winning rate. | C6: Combined with fatigue, elite formations only advance meaningfully by fighting worthy enemies. Farming weak targets stops working entirely.
A7: Two separate tracks | B7: Every formation carries Attack and Defence veterancy with independent tiers, levels and tier-up bills. Attacking earns Attack XP; defending earns Defence XP. | C7: A raiding column and a garrison that began identical become different things, and a player must choose which to fund.
A8: Green dilution | B8: Reinforcing lowers veterancy proportionally by headcount. A Tier 12 formation of 100 merged with 900 recruits lands near Tier 1, and every resource spent on those promotions is gone. | C8: The most important balancing rule in the system. Veteran formations stay scarce, attrition genuinely hurts, and green troops cannot be laundered into elite status.
A9: Era gating | B9: A formation cannot exceed tier 3.5 x its era, rounded up. Era I caps at Steel, Era IV at Platinum, Era VII at Eternal. | C9: Keeps opponents in a theatre within a few tiers, where the stat gap is modest and everything else still matters.
A10: Promotion needs a deed | B10: Reaching level 1,337 and holding the resources only makes a formation eligible. The promotion also requires a qualifying feat appropriate to the tier. | C10: Stops tiers from being purely bought. A Diamond formation earned its rank in a battle somebody remembers.
A11: Veterancy does not transfer | B11: Disbanding loses it permanently and refunds nothing. Re-equipping within an archetype keeps it; changing archetype resets to Copper. | C11: A militia formation that becomes swordsmen keeps its history; infantry that becomes a fleet does not.
A12: Visible and deterrent | B12: Tier is revealed by successful scouting and always shown in battle reports. Formations above Diamond appear on the map. | C12: An enemy declining an engagement because of a formation's reputation is the system working as intended.

Sheet XP_Attribution
A1: KILL-ATTRIBUTED EXPERIENCE — how XP is earned when thousands of battles resolve daily
A2: Flat XP per battle fails at scale: it makes a skirmish worth as much as a decisive siege, it rewards spamming trivial attacks, and it detaches progression from what a formation actually did. XP is instead computed from kills credited to each unit type, valued by what was killed and discounted by how easy the kill was.
A4: THE FORMULA
A5: Per unit type, per battle:
A6: XP = Σ over credited victims [ UPV(victim) × RoleFactor × RelativeFactor ] × Fatigue × Repetition
A8: Term | B8: Definition | F8: Effect in play
A9: Credited victims | B9: Kills are attributed by CONTRIBUTION SHARE, not tracked individually. In each combat phase, a unit type's share = its effective attack pool ÷ the total friendly attack pool for that phase. Enemy losses in the phase are divided by that share. | F9: The resolver already computes these pools to decide the battle, so attribution costs no extra work.
A10: UPV — Unit Power Value | B10: UPV = the victim's upkeep × its own veterancy stat multiplier. Upkeep already encodes era, archetype and grade, so it is a ready-made measure of what a unit is worth. | F10: Killing a Mythic Dreadnought is worth thousands of times killing a militiaman, automatically, with no separate table to maintain.
A11: RoleFactor | B11: 1 ÷ the counter-matrix multiplier for killer-role against victim-role. Killing what you are built to kill teaches little; killing something that counters you teaches a great deal. | F11: Pikemen slaughtering cavalry earn 0.56×. Pikemen somehow killing crossbowmen earn 1.4×. Formations grow fastest doing what they are bad at.
A12: RelativeFactor | B12: (victim UPV ÷ killer UPV)^0.5, clamped to [0.05, 4.0]. Killing something stronger than you teaches more; killing something far weaker teaches almost nothing. | F12: This is the primary anti-farming lever. A Ruby formation killing Copper militia earns near zero regardless of how many it kills.
A13: Fatigue | B13: 1 ÷ ((level+1)^0.21 × 1.25^(tier−1)) — the Experience Fatigue curve from the Veterancy_XP sheet. | F13: Unchanged. Veterans learn less from every fight.
A14: Repetition | B14: Diminishing returns against the same defender: 1.0, 0.6, 0.35, 0.2, then 0.1 for each further engagement against the same player within 24 hours. | F14: Stops a formation grinding the same helpless neighbour all day.
A16: THE DEFENCE TRACK — two components, because screens do not get kills
A17: Component | B17: Applies to | C17: Formula | F17: Why
A18: Kill XP | B18: Any defending unit type that inflicted losses | C18: Same formula as above, credited to the Defence track instead of Attack | F18: Defending killers advance normally.
A19: Absorption XP | B19: Screens, shields, walls, garrison infantry, point-defence | C19: 0.5 × (damage absorbed ÷ total damage the attack delivered) × Σ UPV of the attacking force × Fatigue | F19: A Guardian shield wall or an Aegis screen may kill nothing all siege and still be the reason the settlement held. Without this component those archetypes could never advance, and the Guardian identity path would be a trap.
A21: ANTI-FARMING FLOORS (hard rules, evaluated before XP is awarded)
A22: ✗ | B22: Beneath notice — a victim whose UPV is below 2% of the killer's UPV awards zero XP, not merely reduced XP. Elite formations gain literally nothing from slaughtering peasants.
A23: ✗ | B23: NPC ceiling — kills against barbarians, pirates and other neutral factions cannot advance a formation past Steel (tier 4). Beyond that, only players and the endgame PvE factions count.
A24: ✗ | B24: Escalation — attacks two or more eras down already award near-zero plunder and reputation damage; they also award zero veterancy XP.
A25: ✗ | B25: Self-dealing — kills against a player sharing a device, payment method or network with the attacker award zero, using the same detection as multi-account transfer caps.
A26: • | B26: Losing side — a defeated formation still earns roughly 60% of the rate it would have earned winning, computed on the same kill attribution. Fighting a losing war still develops an army.
A27: • | B27: Wipe rule — a formation destroyed entirely loses all accrued XP with it. XP is held by the formation, not banked by the player.
A29: SCALE & PERFORMANCE
A30: • | B30: Attribution is per unit TYPE per battle, not per soldier. A large battle involves perhaps 20–60 unit-type rows per side, so a server resolving 10,000 battles a day writes on the order of one million XP rows — trivial for the event log that already records every engagement.
A31: • | B31: Every input (attack pools, phase losses, absorbed damage) is already computed by the combat resolver to decide the outcome. Attribution adds arithmetic, not simulation.
A32: • | B32: XP is applied to formations asynchronously after resolution, so it never sits on the critical path of a battle a player is watching.
A33: • | B33: The battle report shows the full attribution table — which unit type was credited with what, and the factor breakdown. Players should be able to see exactly why a formation earned what it earned, the same way combat maths is fully visible.
A35: NOTE — EMPIRE WEIGHT
A36: Empire size no longer reduces XP earned. It multiplies XP REQUIRED instead (see Empire_Weight_Multiplier). Battle reports therefore show the full, undiminished value of every kill, and the effect of empire size appears once, as a single line on the formation sheet. Pacing is mathematically identical either way.

Sheet XP_Worked_Example
A1: WORKED EXAMPLE — one siege, fully attributed
A2: Blue cells are inputs. Everything else computes. Change the inputs to test any engagement.
A4: THE ENGAGEMENT
A5: Attacker: the Ninth Musket (Elite Musketeers) with a cannon battery, assaulting a fortified town.
A6: Defender: Bronze-tier pikemen and Copper-tier crossbowmen behind a star fort.
A8: Attacker inputs | B8: Musketeers | C8: Field Cannon | D8: Defender inputs | E8: Pikemen | F8: Crossbowmen
A9: Count engaged | B9: 2000 | C9: 300 | D9: Count engaged | E9: 1500 | F9: 800
A10: Unit upkeep | B10: 9.6 | C10: 11 | D10: Unit upkeep | E10: 4 | F10: 4
A11: Veterancy tier | B11: 12 | C11: 5 | D11: Veterancy tier | E11: 2 | F11: 1
A12: Veterancy level | B12: 800 | C12: 200 | D12: Veterancy level | E12: 400 | F12: 600
A13: Stat multiplier (1 + 1% × cumulative levels) | B13: =ROUND(1+0.01*((B11-1)*1337+B12),2) -> 156.07 | C13: =ROUND(1+0.01*((C11-1)*1337+C12),2) -> 56.48 | E13: =ROUND(1+0.01*((E11-1)*1337+E12),2) -> 18.37 | F13: =ROUND(1+0.01*((F11-1)*1337+F12),2) -> 7
A14: UPV (upkeep × stat multiplier) | B14: =ROUND(B10*B13,1) -> 1498.3 | C14: =ROUND(C10*C13,1) -> 621.3 | E14: =ROUND(E10*E13,1) -> 73.5 | F14: =ROUND(F10*F13,1) -> 28
A16: PHASE RESULT — attacker wins; contribution shares from the resolver
B17: Musketeers | C17: Field Cannon
A18: Contribution share of friendly attack pool | B18: 0.78 | C18: 0.22
A19: Defender losses: pikemen | B19: 900
A20: Defender losses: crossbowmen | B20: 400
A22: ATTRIBUTION — Musketeer formation
A23: Step | B23: vs Pikemen | C23: vs Crossbowmen
A24: Kills credited | B24: =ROUND($B$19*B18,0) -> 702 | C24: =ROUND($B$20*B18,0) -> 312
A25: UPV of each victim | B25: =E14 -> 73.5 | C25: =F14 -> 28
A26: Raw kill value | B26: =ROUND(B24*B25,0) -> 51597 | C26: =ROUND(C24*C25,0) -> 8736
A27: RoleFactor (1 ÷ counter multiplier) | B27: 0.77 | C27: 1
A28: RelativeFactor ((victimUPV÷killerUPV)^0.5, clamped) | B28: =ROUND(MAX(0.05,MIN(4,(B25/$B$14)^0.5)),3) -> 0.221 | C28: =ROUND(MAX(0.05,MIN(4,(C25/$B$14)^0.5)),3) -> 0.137
A29: Weighted value | B29: =ROUND(B26*B27*B28,0) -> 8780 | C29: =ROUND(C26*C27*C28,0) -> 1197
A31: FINAL XP — Musketeer formation, Attack track
A32: Sum of weighted value | B32: =B29+C29 -> 9977
A33: Fatigue at tier 12, level 800 | B33: =ROUND(1/(($B$12+1)^0.21*1.25^($B$11-1)),5) -> 0.0211
A34: Repetition factor (first attack today) | B34: 1
A35: XP AWARDED | B35: =ROUND(B32*B33*B34,0) -> 211
A36: XP required for the next level | B36: =ROUND(100*($B$12+1)^0.21*1.3^($B$11-1),0) -> 7297
A37: Fraction of a level from this battle | B37: =ROUND(B35/B36*100,1)&"% of a level" -> 2.9% of a level
A38: Equivalent standard battles | B38: =ROUND(B32/1000,1)&" standard battles" -> 10 standard battles
A40: Read-out: a large, genuinely contested siege is worth many ordinary skirmishes, and the same formation attacking a defenceless village would earn almost nothing because RelativeFactor collapses and the beneath-notice floor applies. That is the whole point of attributing XP to kills rather than to battles.

Sheet Empire_Weight_Multiplier
A1: EMPIRE WEIGHT MULTIPLIER — applied to XP REQUIRED, not XP earned
A2: The larger a player's holdings, the more total experience every formation needs to advance. This multiplier stacks on top of the level requirement and the tier requirement, rising to 9,918,521x — the exact reciprocal of the 0.00001% earn-side floor it replaces, so pacing is identical and only the presentation changes.
A4: THE STACK — how a requirement is assembled
A5: XP required = Base × (level+1)^0.21 × 1.30^(tier−1) × EmpireWeightMultiplier
A6: EmpireWeightMultiplier = MIN( cap, 1 + (W / W₀)^k )
A8: Knee W₀ | B8: 100 | C8: Steepness k | D8: 2.41 | E8: Hard cap | F8: 9918521
A9: W is Empire Weight: the sum of admin costs of every holding owned (Outpost 1, Village 2, Town 4, City 8, Metropolis 16, Asteroid Station 4, Moon Base 6, Orbital Station 8, Colony 12, Planetary Capital 24, System Hub 40, Galactic Throne 80). Vassalized holdings are not owned and contribute nothing.
A11: THE CURVE
A12: Empire profile | B12: Weight | C12: XP requirement × | D12: Effect | F12: Comment
A13: One village — a new player | B13: 2 | C13: =MIN($F$8, 1+(B13/$B$8)^$D$8) -> 1.0000804 | D13: =TEXT(C13,"#,##0")&"x more XP" -> 1x more XP | F13: Untouched. Newcomers never see this.
A14: Ten villages | B14: 20 | C14: =MIN($F$8, 1+(B14/$B$8)^$D$8) -> 1.0206768 | D14: =TEXT(C14,"#,##0")&"x more XP" -> 1x more XP | F14: Still essentially free. Early expansion is not discouraged.
A15: 25 villages and 5 towns | B15: 70 | C15: =MIN($F$8, 1+(B15/$B$8)^$D$8) -> 1.423337 | D15: =TEXT(C15,"#,##0")&"x more XP" -> 1x more XP | F15: A normal mid-game player, paying a barely noticeable cost.
A16: The knee — a regional power | B16: 150 | C16: =MIN($F$8, 1+(B16/$B$8)^$D$8) -> 3.6569289 | D16: =TEXT(C16,"#,##0")&"x more XP" -> 4x more XP | F16: Starts to bite here, and is meant to be felt.
A17: 100 villages, 30 towns, 10 cities | B17: 400 | C17: =MIN($F$8, 1+(B17/$B$8)^$D$8) -> 29.246496 | D17: =TEXT(C17,"#,##0")&"x more XP" -> 29x more XP | F17: A serious continental empire needs 29x the experience.
A18: A planet largely held | B18: 1000 | C18: =MIN($F$8, 1+(B18/$B$8)^$D$8) -> 258.03958 | D18: =TEXT(C18,"#,##0")&"x more XP" -> 258x more XP | F18: Elite formations have become impractical to grow.
A19: Several planets | B19: 2000 | C19: =MIN($F$8, 1+(B19/$B$8)^$D$8) -> 1367.0994 | D19: =TEXT(C19,"#,##0")&"x more XP" -> 1,367x more XP | F19: Veterancy progression has effectively stopped.
A20: A galactic power | B20: 8000 | C20: =MIN($F$8, 1+(B20/$B$8)^$D$8) -> 38588.52 | D20: =TEXT(C20,"#,##0")&"x more XP" -> 38,589x more XP | F20: Mass green armies are the only realistic doctrine.
A21: A galaxy largely held | B21: 30000 | C21: =MIN($F$8, 1+(B21/$B$8)^$D$8) -> 932959.28 | D21: =TEXT(C21,"#,##0")&"x more XP" -> 932,959x more XP | F21: Near the cap.
A22: Maximum conceivable holdings | B22: 80000 | C22: =MIN($F$8, 1+(B22/$B$8)^$D$8) -> 9918520.9 | D22: =TEXT(C22,"#,##0")&"x more XP" -> 9,918,521x more XP | F22: Hard cap. No further increase is possible.
A24: WHY THE REQUIREMENT SIDE IS THE BETTER PLACE FOR IT
A25: Mathematically identical | B25: Battles per level is XP required ÷ XP earned. Multiplying the numerator by 29 and dividing the denominator by 29 produce exactly the same pacing. Nothing about game balance changes.
A26: One number instead of every number | B26: On the earn side, every battle report for a large empire showed a shrunken award and the player had to infer why. On the requirement side there is a single figure on the formation sheet — "next level: 47,000,000 XP" — and one line explaining what inflated it.
A27: Battle reports stay honest | B27: A siege that killed nine hundred pikemen now reports the full experience value of those kills. The fight is worth what it was worth; the ladder is simply longer. That is a much clearer story than telling a player their victory was worth almost nothing.
A28: It composes cleanly | B28: The multiplier sits alongside the level and tier factors in one stack, so the balance team tunes three numbers in one formula rather than reasoning about two curves moving in opposite directions.
A29: Numbers stay storable | B29: The largest requirement the game can display is 100 × 4.53 × 418 × 9,918,521 = 1.88 × 10^12. A 64-bit integer holds 9.22 × 10^18, leaving six orders of magnitude of headroom.
A31: SCOPE
A32: System | B32: Affected? | F32: Reasoning
A33: Level-up XP requirement | B33: YES | F33: The primary application. Stacks multiplicatively with level and tier factors.
A34: Tier-up XP requirement | B34: YES | F34: A tier is 1,337 levels, so the cumulative experience to complete one carries the same multiplier throughout.
A35: Tier-up RESOURCE cost | B35: NO | F35: Deliberately untouched — this asymmetry is what creates the Champion economy below. Change one cell if you want it scaled too.
A36: XP earned per battle | B36: NO | F36: No longer decayed by empire size. Kill attribution and Experience Fatigue are unchanged; only empire weight moved.
A37: Player proficiency (5 masteries) | B37: NO | F37: Empire-wide player progression is untouched.
A38: Cultivation realm and Qi | B38: NO | F38: The Sovereign's path is personal and is not an army.
A39: Research | B39: NO | F39: Already empire-wide; slowing it would stall the game rather than balance it.
A40: Commander experience | B40: PARTIAL | F40: Requirement rises at the square root of the multiplier, so great generals can still emerge from large empires — just not great regiments.
A42: CONSEQUENCES AND COUNTERMEASURES
A43: The Champion economy | B43: Tier-up resource costs reach 231 trillion and ignore empire weight, while experience requirements inflate up to ten-millionfold with it. A small player can learn but cannot pay; a galactic power can pay but cannot learn. The resolution is social: large empires bankroll the promotions of small allied players whose formations still advance quickly. Elite armies become an alliance product, and the Champion becomes a recognised strategic role.
A44: Vassalage becomes doubly correct | B44: Vassalized holdings are not owned and add nothing to Empire Weight. A conqueror who vassalizes rather than annexes keeps both administrative burden low and armies capable of learning.
A45: Restraint becomes strategy | B45: There is a real reason not to take every holding within reach. How large to grow becomes a genuine question with costs on both sides rather than a one-way ratchet.
A46: Shedding holdings before a war | B46: Does not work. Empire Weight is a rolling 30-day average, so dumping territory takes a month to pay off and the war will be over.
A47: Parking holdings on an alt | B47: Does not work. Linked-account detection aggregates weight to the primary, using the same system as transfer caps and the Heaven's Envy leaderboards.
A48: Sitting at weight 99 forever | B48: Works, and is meant to. The small elite specialist is a supported playstyle — and a tempting target holding very little land.
A49: The risk, named | B49: This penalises expansion, which is the core loop. Set the knee too low and players stall deliberately, conquest stops and the map freezes, which is worse than the snowballing it prevents. Median empire weight and conquests per player per week are the metrics that say whether W₀ = 100 is right.
A51: CALCULATOR
A52: Empire Weight | B52: 400 | C52: Requirement multiplier | D52: =MIN($F$8, 1+(B52/$B$8)^$D$8) -> 29.246496
